Workbook

Sheet Marketing Dashboard
B2: Marketing Performance Dashboard | AB2: Report Month End
K3: =IF(AB10="","",IF(AB10>0,"↑ "&TEXT(AB10,"0.0%"),IF(AB10<0,"↓ "&TEXT(ABS(AB10),"0.0%"),"→ 0.0%"))) -> ↓ 10.3% | AB3: =TOTAL!C3 -> 46234
AB4: Rolling Months
AB5: =TOTAL!N2 -> 18
AB6: Reporting Month Total Spend
B7: Channel | C7: Spend | D7: MQL | E7: MQA | F7: Meetings | G7: Opps Created | H7: Total Amount Created | I7: ACV Created | J7: Late Stage | K7: Cost/MQL | L7: Cost/Meeting | M7: Cost/Opp | N7: Meeting Rate (Meetings/MQL) | O7: Meeting Rate (Meetings/MQA) | P7: Opp Rate | Q7: Spend / $ Created | R7: Spend / $ Late Stage | S7: Won Deals | T7: Won Net New ACV | U7: ACV Conversion % | V7: Total Amount Won | W7: Total Lost ACV | X7: Win Rate (Decided) | AB7: =TOTAL!F14 -> 75325.15
B8: Digital | C8: =Digital!F15 -> 470640.59 | D8: =Digital!C10 -> 59 | E8: =Digital!C11 -> 52 | F8: =Digital!G10 -> 23 | G8: =Digital!K10 -> 20 | H8: =Digital!K11 -> 10457055 | I8: =Digital!K12 -> 8126285 | J8: =Digital!O11 -> 596510 | K8: =IFERROR(C8/D8,0) -> 7976.9592 | L8: =IFERROR(C8/F8,0) -> 20462.634 | M8: =IFERROR(C8/G8,0) -> 23532.03 | N8: =F8/D8 -> 0.38983051 | O8: =F8/E8 -> 0.44230769 | P8: =G8/F8 -> 0.86956522 | Q8: =IFERROR(I8/C8,0) -> 17.266435 | R8: =IFERROR(J8/C8,0) -> 1.2674427 | S8: =SUMIFS('Stage History'!$T:$T,'Stage History'!$O:$O,"Digital",'Stage History'!$P:$P,">="&EOMONTH($AB$3,-$AB$5)+1,'Stage History'!$P:$P,"<"&EOMONTH($AB$3,0)+1) -> 8 | T8: =SUMIFS('Stage History'!$L:$L,'Stage History'!$O:$O,"Digital",'Stage History'!$T:$T,1,'Stage History'!$P:$P,">="&EOMONTH($AB$3,-$AB$5)+1,'Stage History'!$P:$P,"<"&EOMONTH($AB$3,0)+1) -> 963185 | U8: =IFERROR(T8/I8,0) -> 0.1185271 | V8: =SUMIFS('Stage History'!$K:$K,'Stage History'!$O:$O,"Digital",'Stage History'!$T:$T,1,'Stage History'!$P:$P,">="&EOMONTH($AB$3,-$AB$5)+1,'Stage History'!$P:$P,"<"&EOMONTH($AB$3,0)+1) -> 2853765 | W8: =SUMIFS('Stage History'!$L:$L,'Stage History'!$O:$O,"Digital",'Stage History'!$V:$V,1,'Stage History'!$P:$P,">="&EOMONTH($AB$3,-$AB$5)+1,'Stage History'!$P:$P,"<"&EOMONTH($AB$3,0)+1) -> 1148160 | X8: =IFERROR(T8/(T8+W8),0) -> 0.45619498 | AB8: Prior Month Spend
B9: Events | C9: =Events!F15 -> 829384 | D9: =Events!C10 -> 471 | E9: =Events!C11 -> 331 | F9: =Events!G10 -> 34 | G9: =Events!K10 -> 30 | H9: =Events!K11 -> 9920447.6 | I9: =Events!K12 -> 7134407.6 | J9: =Events!O11 -> 1118283.8 | K9: =IFERROR(C9/D9,0) -> 1760.9002 | L9: =IFERROR(C9/F9,0) -> 24393.647 | M9: =IFERROR(C9/G9,0) -> 27646.133 | N9: =F9/D9 -> 0.072186837 | O9: =F9/E9 -> 0.10271903 | P9: =G9/F9 -> 0.88235294 | Q9: =IFERROR(I9/C9,0) -> 8.602056 | R9: =IFERROR(J9/C9,0) -> 1.3483306 | S9: =SUMIFS('Stage History'!$T:$T,'Stage History'!$O:$O,"Events",'Stage History'!$P:$P,">="&EOMONTH($AB$3,-$AB$5)+1,'Stage History'!$P:$P,"<"&EOMONTH($AB$3,0)+1) -> 0 | T9: =SUMIFS('Stage History'!$L:$L,'Stage History'!$O:$O,"Events",'Stage History'!$T:$T,1,'Stage History'!$P:$P,">="&EOMONTH($AB$3,-$AB$5)+1,'Stage History'!$P:$P,"<"&EOMONTH($AB$3,0)+1) -> 0 | U9: =IFERROR(T9/I9,0) -> 0 | V9: =SUMIFS('Stage History'!$K:$K,'Stage History'!$O:$O,"Events",'Stage History'!$T:$T,1,'Stage History'!$P:$P,">="&EOMONTH($AB$3,-$AB$5)+1,'Stage History'!$P:$P,"<"&EOMONTH($AB$3,0)+1) -> 0 | W9: =SUMIFS('Stage History'!$L:$L,'Stage History'!$O:$O,"Events",'Stage History'!$V:$V,1,'Stage History'!$P:$P,">="&EOMONTH($AB$3,-$AB$5)+1,'Stage History'!$P:$P,"<"&EOMONTH($AB$3,0)+1) -> 2945682 | X9: =IFERROR(T9/(T9+W9),0) -> 0 | AB9: =SUM( IFERROR(SUMIFS('Digital Spend Data'!$C$26:$C$212,'Digital Spend Data'!$B$26:$B$212,">="&EOMONTH($AB$3,-2)+1,'Digital Spend Data'!$B$26:$B$212,"<="&EOMONTH($AB$3,-1)),0), IFERROR(SUMIFS('Event Spend Raw'!$C:$C,'Event Spend Raw'!$G:$G,">="&EOMONTH($AB$3,-2)+1,'Event Spend Raw'!$G:$G,"<="&EOMONTH($AB$3,-1)),0), IFERROR(SUMIFS('Cold Outreach Spend Raw'!$B:$B,'Cold Outreach Spend Raw'!$A:$A,">="&EOMONTH($AB$3,-2)+1,'Cold Outreach Spend Raw'!$A:$A,"<="&EOMONTH($AB$3,-1)),0), IFERROR(SUMIFS('Alliances Spend'!$B:$B,'Alliances Spend'!$C:$C,">="&EOMONTH($AB$3,-2)+1,'Alliances Spend'!$C:$C,"<="&EOMONTH($AB$3,-1)),0) ) -> 83937.21
B10: Cold | C10: ='Cold Outreach'!F15 -> 479675 | D10: ='Cold Outreach'!C10 -> 178 | E10: ='Cold Outreach'!C11 -> 138 | F10: ='Cold Outreach'!G10 -> 141 | G10: ='Cold Outreach'!K10 -> 27 | H10: ='Cold Outreach'!K11 -> 10098778 | I10: ='Cold Outreach'!K12 -> 6961560 | J10: ='Cold Outreach'!O11 -> 1267200 | K10: =IFERROR(C10/D10,0) -> 2694.8034 | L10: =IFERROR(C10/F10,0) -> 3401.9504 | M10: =IFERROR(C10/G10,0) -> 17765.741 | N10: =F10/D10 -> 0.79213483 | O10: =F10/E10 -> 1.0217391 | P10: =G10/F10 -> 0.19148936 | Q10: =IFERROR(I10/C10,0) -> 14.513077 | R10: =IFERROR(J10/C10,0) -> 2.6417887 | S10: =SUMIFS('Stage History'!$T:$T,'Stage History'!$O:$O,"Cold",'Stage History'!$P:$P,">="&EOMONTH($AB$3,-$AB$5)+1,'Stage History'!$P:$P,"<"&EOMONTH($AB$3,0)+1) -> 4 | T10: =SUMIFS('Stage History'!$L:$L,'Stage History'!$O:$O,"Cold",'Stage History'!$T:$T,1,'Stage History'!$P:$P,">="&EOMONTH($AB$3,-$AB$5)+1,'Stage History'!$P:$P,"<"&EOMONTH($AB$3,0)+1) -> 219385.5 | U10: =IFERROR(T10/I10,0) -> 0.031513842 | V10: =SUMIFS('Stage History'!$K:$K,'Stage History'!$O:$O,"Cold",'Stage History'!$T:$T,1,'Stage History'!$P:$P,">="&EOMONTH($AB$3,-$AB$5)+1,'Stage History'!$P:$P,"<"&EOMONTH($AB$3,0)+1) -> 331395.25 | W10: =SUMIFS('Stage History'!$L:$L,'Stage History'!$O:$O,"Cold",'Stage History'!$V:$V,1,'Stage History'!$P:$P,">="&EOMONTH($AB$3,-$AB$5)+1,'Stage History'!$P:$P,"<"&EOMONTH($AB$3,0)+1) -> 7774120 | X10: =IFERROR(T10/(T10+W10),0) -> 0.027445468 | AB10: =IF(AB9=0,"",(AB7-AB9)/AB9) -> -0.10260122 | AC10: MoM%
B11: Alliances | C11: =Alliances!F15 -> 188072.1 | D11: =Alliances!C10 -> 114 | E11: =Alliances!C11 -> 107 | F11: =Alliances!G10 -> 71 | G11: =Alliances!K10 -> 56 | H11: =Alliances!K11 -> 30153720 | I11: =Alliances!K12 -> 18115520 | J11: =Alliances!O11 -> 907364 | K11: =IFERROR(C11/D11,0) -> 1649.7553 | L11: =IFERROR(C11/F11,0) -> 2648.9028 | M11: =IFERROR(C11/G11,0) -> 3358.4304 | N11: =F11/D11 -> 0.62280702 | O11: =F11/E11 -> 0.6635514 | P11: =G11/F11 -> 0.78873239 | Q11: =IFERROR(I11/C11,0) -> 96.322209 | R11: =IFERROR(J11/C11,0) -> 4.824554 | S11: =SUMIFS('Stage History'!$T:$T,'Stage History'!$O:$O,"Alliances",'Stage History'!$P:$P,">="&EOMONTH($AB$3,-$AB$5)+1,'Stage History'!$P:$P,"<"&EOMONTH($AB$3,0)+1) -> 19 | T11: =SUMIFS('Stage History'!$L:$L,'Stage History'!$O:$O,"Alliances",'Stage History'!$T:$T,1,'Stage History'!$P:$P,">="&EOMONTH($AB$3,-$AB$5)+1,'Stage History'!$P:$P,"<"&EOMONTH($AB$3,0)+1) -> 1855153.6 | U11: =IFERROR(T11/I11,0) -> 0.10240686 | V11: =SUMIFS('Stage History'!$K:$K,'Stage History'!$O:$O,"Alliances",'Stage History'!$T:$T,1,'Stage History'!$P:$P,">="&EOMONTH($AB$3,-$AB$5)+1,'Stage History'!$P:$P,"<"&EOMONTH($AB$3,0)+1) -> 3307393.6 | W11: =SUMIFS('Stage History'!$L:$L,'Stage History'!$O:$O,"Alliances",'Stage History'!$V:$V,1,'Stage History'!$P:$P,">="&EOMONTH($AB$3,-$AB$5)+1,'Stage History'!$P:$P,"<"&EOMONTH($AB$3,0)+1) -> 6686773 | X11: =IFERROR(T11/(T11+W11),0) -> 0.2171821 | AB11: =IF(AB10="","", IF(AB10>=0, "↑ "&TEXT(AB10,"0.0%"), "↓ "&TEXT(ABS(AB10),"0.0%") )) -> ↓ 10.3% | AC11: arrow
B12: TOTAL | C12: =SUM(C8:C11) -> 1967771.7 | D12: =SUM(D8:D11) -> 822 | E12: =SUM(E8:E11) -> 628 | F12: =SUM(F8:F11) -> 269 | G12: =SUM(G8:G11) -> 133 | H12: =SUM(H8:H11) -> 60630001 | I12: =SUM(I8:I11) -> 40337773 | J12: =SUM(J8:J11) -> 3889357.8 | K12: =IFERROR(C12/D12,0) -> 2393.8828 | L12: =IFERROR(C12/F12,0) -> 7315.1364 | M12: =IFERROR(C12/G12,0) -> 14795.276 | N12: =F12/D12 -> 0.32725061 | O12: =F12/E12 -> 0.42834395 | P12: =G12/F12 -> 0.49442379 | Q12: =IFERROR(H12/C12,0) -> 30.811502 | R12: =IFERROR(J12/C12,0) -> 1.976529 | S12: =SUM(S8:S11) -> 31 | T12: =SUM(T8:T11) -> 3037724.1 | U12: =IFERROR(T12/I12,0) -> 0.075307184 | V12: =SUM(V8:V11) -> 6492553.8 | W12: =SUM(W8:W11) -> 18554735 | X12: =IFERROR(T12/(T12+W12),0) -> 0.14068449 | AB12: =IFERROR("vs "&TEXT(EOMONTH($AB$3,-1),"mmm-yy")&" ("&TEXT(VALUE(AB9),"$#,##0")&")","") -> vs Jun-26 ($83,937) | AC12: comparison text
AB13: =IF(AB10>0,"↑ "&TEXT(AB10,"0.0%"),"") | AC13: red helper
AB14: green helper
B15: 12-Month Trend | J15: MoM Spend by Channel | O15: Opp Quality by Channel | AC15: =IF(C2=0,"",(B2-C2)/C2) | AD15: channel spend helper
B16: Month Created | C16: Opps Created | D16: Amount Created | E16: MQL | F16: Meetings | G16: Avg Deal Size | H16: Late Stage | J16: Channel | K16: =TEXT($AB$3,"mmmm")&" Spend" -> July Spend | L16: =TEXT(EOMONTH($AB$3,-1),"mmmm")&" Spend" -> June Spend | M16: % Change | O16: Channel | P16: Open Opps | Q16: Avg ACV | R16: % with ACV > $0 | S16: Avg Opp Age (days) | T16: Avg Stage Duration | U16: Late Stage %
B17: =EOMONTH($AB$3,-11) -> 45900 | C17: =COUNTIFS('Opps Created'!$G:$G,">="&EOMONTH($B17,-1)+1,'Opps Created'!$G:$G,"<="&EOMONTH($B17,0),'Opps Created'!$O:$O,"<>",'Opps Created'!$O:$O,"<>0",'Opps Created'!$O:$O,"<>Exclude") -> 5 | D17: =SUM( SUMIFS('Opps Created'!$E:$E,'Opps Created'!$O:$O,"Digital",'Opps Created'!$G:$G,">="&EOMONTH($B17,-1)+1,'Opps Created'!$G:$G,"<="&EOMONTH($B17,0)), SUMIFS('Opps Created'!$E:$E,'Opps Created'!$O:$O,"Events",'Opps Created'!$G:$G,">="&EOMONTH($B17,-1)+1,'Opps Created'!$G:$G,"<="&EOMONTH($B17,0)), SUMIFS('Opps Created'!$E:$E,'Opps Created'!$O:$O,"Alliances",'Opps Created'!$G:$G,">="&EOMONTH($B17,-1)+1,'Opps Created'!$G:$G,"<="&EOMONTH($B17,0)), SUMIFS('Opps Created'!$E:$E,'Opps Created'!$O:$O,"Cold",'Opps Created'!$G:$G,">="&EOMONTH($B17,-1)+1,'Opps Created'!$G:$G,"<="&EOMONTH($B17,0)) ) -> 3009200 | E17: =SUMIFS('Digital Leads Raw'!$B:$B,'Digital Leads Raw'!$E:$E,">="&EOMONTH($B17,-1)+1,'Digital Leads Raw'!$E:$E,"<="&EOMONTH($B17,0)) +SUMIFS('Event Spend Raw'!$D:$D,'Event Spend Raw'!$G:$G,">="&EOMONTH($B17,-1)+1,'Event Spend Raw'!$G:$G,"<="&EOMONTH($B17,0)) +COUNTIFS('Cold outreach data'!$K:$K,"Cold",'Cold outreach data'!$C:$C,">="&EOMONTH($B17,-1)+1,'Cold outreach data'!$C:$C,"<="&EOMONTH($B17,0)) +COUNTIFS('Alliances Data Raw'!$Q:$Q,">="&EOMONTH($B17,-1)+1,'Alliances Data Raw'!$Q:$Q,"<="&EOMONTH($B17,0),'Alliances Data Raw'!$D:$D,"<>Disqualified",'Alliances Data Raw'!$D:$D,"<>Register Lead") -> 58 | F17: =COUNTIFS('Cold outreach data'!$G:$G,"Yes",'Cold outreach data'!$K:$K,"Digital",'Cold outreach data'!$C:$C,">="&EOMONTH($B17,-1)+1,'Cold outreach data'!$C:$C,"<="&EOMONTH($B17,0))+COUNTIFS('Cold outreach data'!$G:$G,"Yes",'Cold outreach data'!$K:$K,"Event",'Cold outreach data'!$C:$C,">="&EOMONTH($B17,-1)+1,'Cold outreach data'!$C:$C,"<="&EOMONTH($B17,0))+COUNTIFS('Cold outreach data'!$G:$G,"Yes",'Cold outreach data'!$K:$K,"Cold",'Cold outreach data'!$C:$C,">="&EOMONTH($B17,-1)+1,'Cold outreach data'!$C:$C,"<="&EOMONTH($B17,0))+COUNTIFS('Alliances Data Raw'!$W:$W,">="&EOMONTH($B17,-1)+1,'Alliances Data Raw'!$W:$W,"<="&EOMONTH($B17,0)) -> 20 | G17: =D17/C17 -> 601840 | H17: =SUMIFS( Table1[Total Net New ACV], Table1[LateStage_Unique_Monthly_Flag], 1, Table1[Change Date], ">="&EOMONTH('Marketing Dashboard'!B17,-1)+1, Table1[Change Date], "<="&EOMONTH('Marketing Dashboard'!B17,0) ) -> 1888583.9 | J17: Digital | K17: =SUMIFS( 'Digital Spend Data'!$C$26:$C$212, 'Digital Spend Data'!$B$26:$B$212,">="&EOMONTH($AB$3,-1)+1, 'Digital Spend Data'!$B$26:$B$212,"<="&EOMONTH($AB$3,0) ) -> 34395.59 | L17: =SUMIFS( 'Digital Spend Data'!$C$26:$C$212, 'Digital Spend Data'!$B$26:$B$212,">="&EOMONTH($AB$3,-2)+1, 'Digital Spend Data'!$B$26:$B$212,"<="&EOMONTH($AB$3,-1) ) -> 31769.46 | M17: =IF(L17=0,"", IF((K17-L17)/L17>0, "↑ "&TEXT((K17-L17)/L17,"0.0%"), IF((K17-L17)/L17<0, "↓ "&TEXT(ABS((K17-L17)/L17),"0.0%"), "→ 0.0%" ))) -> ↑ 8.3% | O17: Digital | P17: =COUNTIFS('Opps Created'!$O:$O,"Digital",'Opps Created'!$R:$R,0,'Opps Created'!$G:$G,">="&EOMONTH($AB$3,-$AB$5)+1,'Opps Created'!$G:$G,"<="&$AB$3) -> 17 | Q17: =IFERROR(AVERAGEIFS('Opps Created'!$M:$M,'Opps Created'!$O:$O,"Digital",'Opps Created'!$R:$R,0,'Opps Created'!$M:$M,">0",'Opps Created'!$G:$G,">="&EOMONTH($AB$3,-$AB$5)+1,'Opps Created'!$G:$G,"<="&$AB$3),0) -> 493518.75 | R17: =IFERROR(COUNTIFS('Opps Created'!$O:$O,"Digital",'Opps Created'!$R:$R,0,'Opps Created'!$M:$M,">0",'Opps Created'!$G:$G,">="&EOMONTH($AB$3,-$AB$5)+1,'Opps Created'!$G:$G,"<="&$AB$3)/P17,0) -> 0.94117647 | S17: =IFERROR(AVERAGEIFS('Opps Created'!$P:$P,'Opps Created'!$O:$O,"Digital",'Opps Created'!$R:$R,0,'Opps Created'!$G:$G,">="&EOMONTH($AB$3,-$AB$5)+1,'Opps Created'!$G:$G,"<="&$AB$3),0) -> 369.52941 | T17: =IFERROR(AVERAGEIFS('Opps Created'!$N:$N,'Opps Created'!$O:$O,"Digital",'Opps Created'!$R:$R,0,'Opps Created'!$G:$G,">="&EOMONTH($AB$3,-$AB$5)+1,'Opps Created'!$G:$G,"<="&$AB$3),0) -> 187.35294 | U17: =IFERROR(COUNTIFS('Opps Created'!$O:$O,"Digital",'Opps Created'!$R:$R,0,'Opps Created'!$Q:$Q,1,'Opps Created'!$G:$G,">="&EOMONTH($AB$3,-$AB$5)+1,'Opps Created'!$G:$G,"<="&$AB$3)/P17,0) -> 0
B18: =EOMONTH($AB$3,-10) -> 45930 | C18: =COUNTIFS('Opps Created'!$G:$G,">="&EOMONTH($B18,-1)+1,'Opps Created'!$G:$G,"<="&EOMONTH($B18,0),'Opps Created'!$O:$O,"<>",'Opps Created'!$O:$O,"<>0",'Opps Created'!$O:$O,"<>Exclude") -> 12 | D18: =SUM( SUMIFS('Opps Created'!$E:$E,'Opps Created'!$O:$O,"Digital",'Opps Created'!$G:$G,">="&EOMONTH($B18,-1)+1,'Opps Created'!$G:$G,"<="&EOMONTH($B18,0)), SUMIFS('Opps Created'!$E:$E,'Opps Created'!$O:$O,"Events",'Opps Created'!$G:$G,">="&EOMONTH($B18,-1)+1,'Opps Created'!$G:$G,"<="&EOMONTH($B18,0)), SUMIFS('Opps Created'!$E:$E,'Opps Created'!$O:$O,"Alliances",'Opps Created'!$G:$G,">="&EOMONTH($B18,-1)+1,'Opps Created'!$G:$G,"<="&EOMONTH($B18,0)), SUMIFS('Opps Created'!$E:$E,'Opps Created'!$O:$O,"Cold",'Opps Created'!$G:$G,">="&EOMONTH($B18,-1)+1,'Opps Created'!$G:$G,"<="&EOMONTH($B18,0)) ) -> 15218160 | E18: =SUMIFS('Digital Leads Raw'!$B:$B,'Digital Leads Raw'!$E:$E,">="&EOMONTH($B18,-1)+1,'Digital Leads Raw'!$E:$E,"<="&EOMONTH($B18,0)) +SUMIFS('Event Spend Raw'!$D:$D,'Event Spend Raw'!$G:$G,">="&EOMONTH($B18,-1)+1,'Event Spend Raw'!$G:$G,"<="&EOMONTH($B18,0)) +COUNTIFS('Cold outreach data'!$K:$K,"Cold",'Cold outreach data'!$C:$C,">="&EOMONTH($B18,-1)+1,'Cold outreach data'!$C:$C,"<="&EOMONTH($B18,0)) +COUNTIFS('Alliances Data Raw'!$Q:$Q,">="&EOMONTH($B18,-1)+1,'Alliances Data Raw'!$Q:$Q,"<="&EOMONTH($B18,0),'Alliances Data Raw'!$D:$D,"<>Disqualified",'Alliances Data Raw'!$D:$D,"<>Register Lead") -> 64 | F18: =COUNTIFS('Cold outreach data'!$G:$G,"Yes",'Cold outreach data'!$K:$K,"Digital",'Cold outreach data'!$C:$C,">="&EOMONTH($B18,-1)+1,'Cold outreach data'!$C:$C,"<="&EOMONTH($B18,0))+COUNTIFS('Cold outreach data'!$G:$G,"Yes",'Cold outreach data'!$K:$K,"Event",'Cold outreach data'!$C:$C,">="&EOMONTH($B18,-1)+1,'Cold outreach data'!$C:$C,"<="&EOMONTH($B18,0))+COUNTIFS('Cold outreach data'!$G:$G,"Yes",'Cold outreach data'!$K:$K,"Cold",'Cold outreach data'!$C:$C,">="&EOMONTH($B18,-1)+1,'Cold outreach data'!$C:$C,"<="&EOMONTH($B18,0))+COUNTIFS('Alliances Data Raw'!$W:$W,">="&EOMONTH($B18,-1)+1,'Alliances Data Raw'!$W:$W,"<="&EOMONTH($B18,0)) -> 13 | G18: =D18/C18 -> 1268180 | H18: =SUMIFS( Table1[Total Net New ACV], Table1[LateStage_Unique_Monthly_Flag], 1, Table1[Change Date], ">="&EOMONTH('Marketing Dashboard'!B18,-1)+1, Table1[Change Date], "<="&EOMONTH('Marketing Dashboard'!B18,0) ) -> 1465250.7 | J18: Events | K18: =SUMIFS( 'Event Spend Raw'!$C:$C, 'Event Spend Raw'!$G:$G,">="&EOMONTH($AB$3,-1)+1, 'Event Spend Raw'!$G:$G,"<="&EOMONTH($AB$3,0) ) -> 5000 | L18: =SUMIFS( 'Event Spend Raw'!$C:$C, 'Event Spend Raw'!$G:$G,">="&EOMONTH($AB$3,-2)+1, 'Event Spend Raw'!$G:$G,"<="&EOMONTH($AB$3,-1) ) -> 19600 | M18: =IF(L18=0,"", IF((K18-L18)/L18>0, "↑ "&TEXT((K18-L18)/L18,"0.0%"), IF((K18-L18)/L18<0, "↓ "&TEXT(ABS((K18-L18)/L18),"0.0%"), "→ 0.0%" ))) -> ↓ 74.5% | O18: Events | P18: =COUNTIFS('Opps Created'!$O:$O,"Events",'Opps Created'!$R:$R,0,'Opps Created'!$G:$G,">="&EOMONTH($AB$3,-$AB$5)+1,'Opps Created'!$G:$G,"<="&$AB$3) -> 30 | Q18: =IFERROR(AVERAGEIFS('Opps Created'!$M:$M,'Opps Created'!$O:$O,"Events",'Opps Created'!$R:$R,0,'Opps Created'!$M:$M,">0",'Opps Created'!$G:$G,">="&EOMONTH($AB$3,-$AB$5)+1,'Opps Created'!$G:$G,"<="&$AB$3),0) -> 285376.3 | R18: =IFERROR(COUNTIFS('Opps Created'!$O:$O,"Events",'Opps Created'!$R:$R,0,'Opps Created'!$M:$M,">0",'Opps Created'!$G:$G,">="&EOMONTH($AB$3,-$AB$5)+1,'Opps Created'!$G:$G,"<="&$AB$3)/P18,0) -> 0.83333333 | S18: =IFERROR(AVERAGEIFS('Opps Created'!$P:$P,'Opps Created'!$O:$O,"Events",'Opps Created'!$R:$R,0,'Opps Created'!$G:$G,">="&EOMONTH($AB$3,-$AB$5)+1,'Opps Created'!$G:$G,"<="&$AB$3),0) -> 279.73333 | T18: =IFERROR(AVERAGEIFS('Opps Created'!$N:$N,'Opps Created'!$O:$O,"Events",'Opps Created'!$R:$R,0,'Opps Created'!$G:$G,">="&EOMONTH($AB$3,-$AB$5)+1,'Opps Created'!$G:$G,"<="&$AB$3),0) -> 164.03333 | U18: =IFERROR(COUNTIFS('Opps Created'!$O:$O,"Events",'Opps Created'!$R:$R,0,'Opps Created'!$Q:$Q,1,'Opps Created'!$G:$G,">="&EOMONTH($AB$3,-$AB$5)+1,'Opps Created'!$G:$G,"<="&$AB$3)/P18,0) -> 0.1
B19: =EOMONTH($AB$3,-9) -> 45961 | C19: =COUNTIFS('Opps Created'!$G:$G,">="&EOMONTH($B19,-1)+1,'Opps Created'!$G:$G,"<="&EOMONTH($B19,0),'Opps Created'!$O:$O,"<>",'Opps Created'!$O:$O,"<>0",'Opps Created'!$O:$O,"<>Exclude") -> 7 | D19: =SUM( SUMIFS('Opps Created'!$E:$E,'Opps Created'!$O:$O,"Digital",'Opps Created'!$G:$G,">="&EOMONTH($B19,-1)+1,'Opps Created'!$G:$G,"<="&EOMONTH($B19,0)), SUMIFS('Opps Created'!$E:$E,'Opps Created'!$O:$O,"Events",'Opps Created'!$G:$G,">="&EOMONTH($B19,-1)+1,'Opps Created'!$G:$G,"<="&EOMONTH($B19,0)), SUMIFS('Opps Created'!$E:$E,'Opps Created'!$O:$O,"Alliances",'Opps Created'!$G:$G,">="&EOMONTH($B19,-1)+1,'Opps Created'!$G:$G,"<="&EOMONTH($B19,0)), SUMIFS('Opps Created'!$E:$E,'Opps Created'!$O:$O,"Cold",'Opps Created'!$G:$G,">="&EOMONTH($B19,-1)+1,'Opps Created'!$G:$G,"<="&EOMONTH($B19,0)) ) -> 1241516.2 | E19: =SUMIFS('Digital Leads Raw'!$B:$B,'Digital Leads Raw'!$E:$E,">="&EOMONTH($B19,-1)+1,'Digital Leads Raw'!$E:$E,"<="&EOMONTH($B19,0)) +SUMIFS('Event Spend Raw'!$D:$D,'Event Spend Raw'!$G:$G,">="&EOMONTH($B19,-1)+1,'Event Spend Raw'!$G:$G,"<="&EOMONTH($B19,0)) +COUNTIFS('Cold outreach data'!$K:$K,"Cold",'Cold outreach data'!$C:$C,">="&EOMONTH($B19,-1)+1,'Cold outreach data'!$C:$C,"<="&EOMONTH($B19,0)) +COUNTIFS('Alliances Data Raw'!$Q:$Q,">="&EOMONTH($B19,-1)+1,'Alliances Data Raw'!$Q:$Q,"<="&EOMONTH($B19,0),'Alliances Data Raw'!$D:$D,"<>Disqualified",'Alliances Data Raw'!$D:$D,"<>Register Lead") -> 22 | F19: =COUNTIFS('Cold outreach data'!$G:$G,"Yes",'Cold outreach data'!$K:$K,"Digital",'Cold outreach data'!$C:$C,">="&EOMONTH($B19,-1)+1,'Cold outreach data'!$C:$C,"<="&EOMONTH($B19,0))+COUNTIFS('Cold outreach data'!$G:$G,"Yes",'Cold outreach data'!$K:$K,"Event",'Cold outreach data'!$C:$C,">="&EOMONTH($B19,-1)+1,'Cold outreach data'!$C:$C,"<="&EOMONTH($B19,0))+COUNTIFS('Cold outreach data'!$G:$G,"Yes",'Cold outreach data'!$K:$K,"Cold",'Cold outreach data'!$C:$C,">="&EOMONTH($B19,-1)+1,'Cold outreach data'!$C:$C,"<="&EOMONTH($B19,0))+COUNTIFS('Alliances Data Raw'!$W:$W,">="&EOMONTH($B19,-1)+1,'Alliances Data Raw'!$W:$W,"<="&EOMONTH($B19,0)) -> 18 | G19: =D19/C19 -> 177359.45 | H19: =SUMIFS( Table1[Total Net New ACV], Table1[LateStage_Unique_Monthly_Flag], 1, Table1[Change Date], ">="&EOMONTH('Marketing Dashboard'!B19,-1)+1, Table1[Change Date], "<="&EOMONTH('Marketing Dashboard'!B19,0) ) -> 2278803.3 | J19: Cold Outreach | K19: =SUMIFS( 'Cold Outreach Spend Raw'!$B:$B, 'Cold Outreach Spend Raw'!$A:$A,">="&EOMONTH($AB$3,-1)+1, 'Cold Outreach Spend Raw'!$A:$A,"<="&EOMONTH($AB$3,0) ) -> 32475 | L19: =SUMIFS( 'Cold Outreach Spend Raw'!$B:$B, 'Cold Outreach Spend Raw'!$A:$A,">="&EOMONTH($AB$3,-2)+1, 'Cold Outreach Spend Raw'!$A:$A,"<="&EOMONTH($AB$3,-1) ) -> 32475 | M19: =IF(L19=0,"", IF((K19-L19)/L19>0, "↑ "&TEXT((K19-L19)/L19,"0.0%"), IF((K19-L19)/L19<0, "↓ "&TEXT(ABS((K19-L19)/L19),"0.0%"), "→ 0.0%" ))) -> → 0.0% | O19: Cold Outreach | P19: =COUNTIFS('Opps Created'!$O:$O,"Cold",'Opps Created'!$R:$R,0,'Opps Created'!$G:$G,">="&EOMONTH($AB$3,-$AB$5)+1,'Opps Created'!$G:$G,"<="&$AB$3) -> 25 | Q19: =IFERROR(AVERAGEIFS('Opps Created'!$M:$M,'Opps Created'!$O:$O,"Cold",'Opps Created'!$R:$R,0,'Opps Created'!$M:$M,">0",'Opps Created'!$G:$G,">="&EOMONTH($AB$3,-$AB$5)+1,'Opps Created'!$G:$G,"<="&$AB$3),0) -> 324979.05 | R19: =IFERROR(COUNTIFS('Opps Created'!$O:$O,"Cold",'Opps Created'!$R:$R,0,'Opps Created'!$M:$M,">0",'Opps Created'!$G:$G,">="&EOMONTH($AB$3,-$AB$5)+1,'Opps Created'!$G:$G,"<="&$AB$3)/P19,0) -> 0.84 | S19: =IFERROR(AVERAGEIFS('Opps Created'!$P:$P,'Opps Created'!$O:$O,"Cold",'Opps Created'!$R:$R,0,'Opps Created'!$G:$G,">="&EOMONTH($AB$3,-$AB$5)+1,'Opps Created'!$G:$G,"<="&$AB$3),0) -> 320.52 | T19: =IFERROR(AVERAGEIFS('Opps Created'!$N:$N,'Opps Created'!$O:$O,"Cold",'Opps Created'!$R:$R,0,'Opps Created'!$G:$G,">="&EOMONTH($AB$3,-$AB$5)+1,'Opps Created'!$G:$G,"<="&$AB$3),0) -> 158.52 | U19: =IFERROR(COUNTIFS('Opps Created'!$O:$O,"Cold",'Opps Created'!$R:$R,0,'Opps Created'!$Q:$Q,1,'Opps Created'!$G:$G,">="&EOMONTH($AB$3,-$AB$5)+1,'Opps Created'!$G:$G,"<="&$AB$3)/P19,0) -> 0.08
B20: =EOMONTH($AB$3,-8) -> 45991 | C20: =COUNTIFS('Opps Created'!$G:$G,">="&EOMONTH($B20,-1)+1,'Opps Created'!$G:$G,"<="&EOMONTH($B20,0),'Opps Created'!$O:$O,"<>",'Opps Created'!$O:$O,"<>0",'Opps Created'!$O:$O,"<>Exclude") -> 6 | D20: =SUM( SUMIFS('Opps Created'!$E:$E,'Opps Created'!$O:$O,"Digital",'Opps Created'!$G:$G,">="&EOMONTH($B20,-1)+1,'Opps Created'!$G:$G,"<="&EOMONTH($B20,0)), SUMIFS('Opps Created'!$E:$E,'Opps Created'!$O:$O,"Events",'Opps Created'!$G:$G,">="&EOMONTH($B20,-1)+1,'Opps Created'!$G:$G,"<="&EOMONTH($B20,0)), SUMIFS('Opps Created'!$E:$E,'Opps Created'!$O:$O,"Alliances",'Opps Created'!$G:$G,">="&EOMONTH($B20,-1)+1,'Opps Created'!$G:$G,"<="&EOMONTH($B20,0)), SUMIFS('Opps Created'!$E:$E,'Opps Created'!$O:$O,"Cold",'Opps Created'!$G:$G,">="&EOMONTH($B20,-1)+1,'Opps Created'!$G:$G,"<="&EOMONTH($B20,0)) ) -> 1441015.6 | E20: =SUMIFS('Digital Leads Raw'!$B:$B,'Digital Leads Raw'!$E:$E,">="&EOMONTH($B20,-1)+1,'Digital Leads Raw'!$E:$E,"<="&EOMONTH($B20,0)) +SUMIFS('Event Spend Raw'!$D:$D,'Event Spend Raw'!$G:$G,">="&EOMONTH($B20,-1)+1,'Event Spend Raw'!$G:$G,"<="&EOMONTH($B20,0)) +COUNTIFS('Cold outreach data'!$K:$K,"Cold",'Cold outreach data'!$C:$C,">="&EOMONTH($B20,-1)+1,'Cold outreach data'!$C:$C,"<="&EOMONTH($B20,0)) +COUNTIFS('Alliances Data Raw'!$Q:$Q,">="&EOMONTH($B20,-1)+1,'Alliances Data Raw'!$Q:$Q,"<="&EOMONTH($B20,0),'Alliances Data Raw'!$D:$D,"<>Disqualified",'Alliances Data Raw'!$D:$D,"<>Register Lead") -> 78 | F20: =COUNTIFS('Cold outreach data'!$G:$G,"Yes",'Cold outreach data'!$K:$K,"Digital",'Cold outreach data'!$C:$C,">="&EOMONTH($B20,-1)+1,'Cold outreach data'!$C:$C,"<="&EOMONTH($B20,0))+COUNTIFS('Cold outreach data'!$G:$G,"Yes",'Cold outreach data'!$K:$K,"Event",'Cold outreach data'!$C:$C,">="&EOMONTH($B20,-1)+1,'Cold outreach data'!$C:$C,"<="&EOMONTH($B20,0))+COUNTIFS('Cold outreach data'!$G:$G,"Yes",'Cold outreach data'!$K:$K,"Cold",'Cold outreach data'!$C:$C,">="&EOMONTH($B20,-1)+1,'Cold outreach data'!$C:$C,"<="&EOMONTH($B20,0))+COUNTIFS('Alliances Data Raw'!$W:$W,">="&EOMONTH($B20,-1)+1,'Alliances Data Raw'!$W:$W,"<="&EOMONTH($B20,0)) -> 14 | G20: =D20/C20 -> 240169.27 | H20: =SUMIFS( Table1[Total Net New ACV], Table1[LateStage_Unique_Monthly_Flag], 1, Table1[Change Date], ">="&EOMONTH('Marketing Dashboard'!B20,-1)+1, Table1[Change Date], "<="&EOMONTH('Marketing Dashboard'!B20,0) ) -> 854808 | J20: Alliances | K20: =SUMIFS( 'Alliances Spend'!$B:$B, 'Alliances Spend'!$C:$C,">="&EOMONTH($AB$3,-1)+1, 'Alliances Spend'!$C:$C,"<="&EOMONTH($AB$3,0) ) -> 3454.56 | L20: =SUMIFS( 'Alliances Spend'!$B:$B, 'Alliances Spend'!$C:$C,">="&EOMONTH($AB$3,-2)+1, 'Alliances Spend'!$C:$C,"<="&EOMONTH($AB$3,-1) ) -> 92.75 | M20: =IF(L20=0,"", IF((K20-L20)/L20>0, "↑ "&TEXT((K20-L20)/L20,"0.0%"), IF((K20-L20)/L20<0, "↓ "&TEXT(ABS((K20-L20)/L20),"0.0%"), "→ 0.0%" ))) -> ↑ 3624.6% | O20: Alliances | P20: =COUNTIFS('Opps Created'!$O:$O,"Alliances",'Opps Created'!$R:$R,0,'Opps Created'!$G:$G,">="&EOMONTH($AB$3,-$AB$5)+1,'Opps Created'!$G:$G,"<="&$AB$3) -> 46 | Q20: =IFERROR(AVERAGEIFS('Opps Created'!$M:$M,'Opps Created'!$O:$O,"Alliances",'Opps Created'!$R:$R,0,'Opps Created'!$M:$M,">0",'Opps Created'!$G:$G,">="&EOMONTH($AB$3,-$AB$5)+1,'Opps Created'!$G:$G,"<="&$AB$3),0) -> 418501.26 | R20: =IFERROR(COUNTIFS('Opps Created'!$O:$O,"Alliances",'Opps Created'!$R:$R,0,'Opps Created'!$M:$M,">0",'Opps Created'!$G:$G,">="&EOMONTH($AB$3,-$AB$5)+1,'Opps Created'!$G:$G,"<="&$AB$3)/P20,0) -> 0.89130435 | S20: =IFERROR(AVERAGEIFS('Opps Created'!$P:$P,'Opps Created'!$O:$O,"Alliances",'Opps Created'!$R:$R,0,'Opps Created'!$G:$G,">="&EOMONTH($AB$3,-$AB$5)+1,'Opps Created'!$G:$G,"<="&$AB$3),0) -> 273.15217 | T20: =IFERROR(AVERAGEIFS('Opps Created'!$N:$N,'Opps Created'!$O:$O,"Alliances",'Opps Created'!$R:$R,0,'Opps Created'!$G:$G,">="&EOMONTH($AB$3,-$AB$5)+1,'Opps Created'!$G:$G,"<="&$AB$3),0) -> 189.26087 | U20: =IFERROR(COUNTIFS('Opps Created'!$O:$O,"Alliances",'Opps Created'!$R:$R,0,'Opps Created'!$Q:$Q,1,'Opps Created'!$G:$G,">="&EOMONTH($AB$3,-$AB$5)+1,'Opps Created'!$G:$G,"<="&$AB$3)/P20,0) -> 0.086956522
B21: =EOMONTH($AB$3,-7) -> 46022 | C21: =COUNTIFS('Opps Created'!$G:$G,">="&EOMONTH($B21,-1)+1,'Opps Created'!$G:$G,"<="&EOMONTH($B21,0),'Opps Created'!$O:$O,"<>",'Opps Created'!$O:$O,"<>0",'Opps Created'!$O:$O,"<>Exclude") -> 7 | D21: =SUM( SUMIFS('Opps Created'!$E:$E,'Opps Created'!$O:$O,"Digital",'Opps Created'!$G:$G,">="&EOMONTH($B21,-1)+1,'Opps Created'!$G:$G,"<="&EOMONTH($B21,0)), SUMIFS('Opps Created'!$E:$E,'Opps Created'!$O:$O,"Events",'Opps Created'!$G:$G,">="&EOMONTH($B21,-1)+1,'Opps Created'!$G:$G,"<="&EOMONTH($B21,0)), SUMIFS('Opps Created'!$E:$E,'Opps Created'!$O:$O,"Alliances",'Opps Created'!$G:$G,">="&EOMONTH($B21,-1)+1,'Opps Created'!$G:$G,"<="&EOMONTH($B21,0)), SUMIFS('Opps Created'!$E:$E,'Opps Created'!$O:$O,"Cold",'Opps Created'!$G:$G,">="&EOMONTH($B21,-1)+1,'Opps Created'!$G:$G,"<="&EOMONTH($B21,0)) ) -> 4904592 | E21: =SUMIFS('Digital Leads Raw'!$B:$B,'Digital Leads Raw'!$E:$E,">="&EOMONTH($B21,-1)+1,'Digital Leads Raw'!$E:$E,"<="&EOMONTH($B21,0)) +SUMIFS('Event Spend Raw'!$D:$D,'Event Spend Raw'!$G:$G,">="&EOMONTH($B21,-1)+1,'Event Spend Raw'!$G:$G,"<="&EOMONTH($B21,0)) +COUNTIFS('Cold outreach data'!$K:$K,"Cold",'Cold outreach data'!$C:$C,">="&EOMONTH($B21,-1)+1,'Cold outreach data'!$C:$C,"<="&EOMONTH($B21,0)) +COUNTIFS('Alliances Data Raw'!$Q:$Q,">="&EOMONTH($B21,-1)+1,'Alliances Data Raw'!$Q:$Q,"<="&EOMONTH($B21,0),'Alliances Data Raw'!$D:$D,"<>Disqualified",'Alliances Data Raw'!$D:$D,"<>Register Lead") -> 5 | F21: =COUNTIFS('Cold outreach data'!$G:$G,"Yes",'Cold outreach data'!$K:$K,"Digital",'Cold outreach data'!$C:$C,">="&EOMONTH($B21,-1)+1,'Cold outreach data'!$C:$C,"<="&EOMONTH($B21,0))+COUNTIFS('Cold outreach data'!$G:$G,"Yes",'Cold outreach data'!$K:$K,"Event",'Cold outreach data'!$C:$C,">="&EOMONTH($B21,-1)+1,'Cold outreach data'!$C:$C,"<="&EOMONTH($B21,0))+COUNTIFS('Cold outreach data'!$G:$G,"Yes",'Cold outreach data'!$K:$K,"Cold",'Cold outreach data'!$C:$C,">="&EOMONTH($B21,-1)+1,'Cold outreach data'!$C:$C,"<="&EOMONTH($B21,0))+COUNTIFS('Alliances Data Raw'!$W:$W,">="&EOMONTH($B21,-1)+1,'Alliances Data Raw'!$W:$W,"<="&EOMONTH($B21,0)) -> 7 | G21: =D21/C21 -> 700656 | H21: =SUMIFS( Table1[Total Net New ACV], Table1[LateStage_Unique_Monthly_Flag], 1, Table1[Change Date], ">="&EOMONTH('Marketing Dashboard'!B21,-1)+1, Table1[Change Date], "<="&EOMONTH('Marketing Dashboard'!B21,0) ) -> 433860 | J21: TOTAL | K21: =SUM(K17:K20) -> 75325.15 | L21: =SUM(L17:L20) -> 83937.21 | M21: =IF(L21=0,"", IF((K21-L21)/L21>0, "↑ "&TEXT((K21-L21)/L21,"0.0%"), IF((K21-L21)/L21<0, "↓ "&TEXT(ABS((K21-L21)/L21),"0.0%"), "→ 0.0%" ))) -> ↓ 10.3% | O21: TOTAL | P21: =SUM(P17:P20) -> 118 | Q21: =IFERROR((Q17*P17+Q18*P18+Q19*P19+Q20*P20)/P21,0) -> 375649.51 | R21: =IFERROR((R17*P17+R18*P18+R19*P19+R20*P20)/P21,0) -> 0.87288136 | S21: =IFERROR((S17*P17+S18*P18+S19*P19+S20*P20)/P21,0) -> 298.74576 | T21: =IFERROR((T17*P17+T18*P18+T19*P19+T20*P20)/P21,0) -> 176.05932 | U21: =IFERROR((U17*P17+U18*P18+U19*P19+U20*P20)/P21,0) -> 0.076271186
B22: =EOMONTH($AB$3,-6) -> 46053 | C22: =COUNTIFS('Opps Created'!$G:$G,">="&EOMONTH($B22,-1)+1,'Opps Created'!$G:$G,"<="&EOMONTH($B22,0),'Opps Created'!$O:$O,"<>",'Opps Created'!$O:$O,"<>0",'Opps Created'!$O:$O,"<>Exclude") -> 6 | D22: =SUM( SUMIFS('Opps Created'!$E:$E,'Opps Created'!$O:$O,"Digital",'Opps Created'!$G:$G,">="&EOMONTH($B22,-1)+1,'Opps Created'!$G:$G,"<="&EOMONTH($B22,0)), SUMIFS('Opps Created'!$E:$E,'Opps Created'!$O:$O,"Events",'Opps Created'!$G:$G,">="&EOMONTH($B22,-1)+1,'Opps Created'!$G:$G,"<="&EOMONTH($B22,0)), SUMIFS('Opps Created'!$E:$E,'Opps Created'!$O:$O,"Alliances",'Opps Created'!$G:$G,">="&EOMONTH($B22,-1)+1,'Opps Created'!$G:$G,"<="&EOMONTH($B22,0)), SUMIFS('Opps Created'!$E:$E,'Opps Created'!$O:$O,"Cold",'Opps Created'!$G:$G,">="&EOMONTH($B22,-1)+1,'Opps Created'!$G:$G,"<="&EOMONTH($B22,0)) ) -> 1915920 | E22: =SUMIFS('Digital Leads Raw'!$B:$B,'Digital Leads Raw'!$E:$E,">="&EOMONTH($B22,-1)+1,'Digital Leads Raw'!$E:$E,"<="&EOMONTH($B22,0)) +SUMIFS('Event Spend Raw'!$D:$D,'Event Spend Raw'!$G:$G,">="&EOMONTH($B22,-1)+1,'Event Spend Raw'!$G:$G,"<="&EOMONTH($B22,0)) +COUNTIFS('Cold outreach data'!$K:$K,"Cold",'Cold outreach data'!$C:$C,">="&EOMONTH($B22,-1)+1,'Cold outreach data'!$C:$C,"<="&EOMONTH($B22,0)) +COUNTIFS('Alliances Data Raw'!$Q:$Q,">="&EOMONTH($B22,-1)+1,'Alliances Data Raw'!$Q:$Q,"<="&EOMONTH($B22,0),'Alliances Data Raw'!$D:$D,"<>Disqualified",'Alliances Data Raw'!$D:$D,"<>Register Lead") -> 109 | F22: =COUNTIFS('Cold outreach data'!$G:$G,"Yes",'Cold outreach data'!$K:$K,"Digital",'Cold outreach data'!$C:$C,">="&EOMONTH($B22,-1)+1,'Cold outreach data'!$C:$C,"<="&EOMONTH($B22,0))+COUNTIFS('Cold outreach data'!$G:$G,"Yes",'Cold outreach data'!$K:$K,"Event",'Cold outreach data'!$C:$C,">="&EOMONTH($B22,-1)+1,'Cold outreach data'!$C:$C,"<="&EOMONTH($B22,0))+COUNTIFS('Cold outreach data'!$G:$G,"Yes",'Cold outreach data'!$K:$K,"Cold",'Cold outreach data'!$C:$C,">="&EOMONTH($B22,-1)+1,'Cold outreach data'!$C:$C,"<="&EOMONTH($B22,0))+COUNTIFS('Alliances Data Raw'!$W:$W,">="&EOMONTH($B22,-1)+1,'Alliances Data Raw'!$W:$W,"<="&EOMONTH($B22,0)) -> 28 | G22: =D22/C22 -> 319320 | H22: =SUMIFS( Table1[Total Net New ACV], Table1[LateStage_Unique_Monthly_Flag], 1, Table1[Change Date], ">="&EOMONTH('Marketing Dashboard'!B22,-1)+1, Table1[Change Date], "<="&EOMONTH('Marketing Dashboard'!B22,0) ) -> 317625
B23: =EOMONTH($AB$3,-5) -> 46081 | C23: =COUNTIFS('Opps Created'!$G:$G,">="&EOMONTH($B23,-1)+1,'Opps Created'!$G:$G,"<="&EOMONTH($B23,0),'Opps Created'!$O:$O,"<>",'Opps Created'!$O:$O,"<>0",'Opps Created'!$O:$O,"<>Exclude") -> 6 | D23: =SUM( SUMIFS('Opps Created'!$E:$E,'Opps Created'!$O:$O,"Digital",'Opps Created'!$G:$G,">="&EOMONTH($B23,-1)+1,'Opps Created'!$G:$G,"<="&EOMONTH($B23,0)), SUMIFS('Opps Created'!$E:$E,'Opps Created'!$O:$O,"Events",'Opps Created'!$G:$G,">="&EOMONTH($B23,-1)+1,'Opps Created'!$G:$G,"<="&EOMONTH($B23,0)), SUMIFS('Opps Created'!$E:$E,'Opps Created'!$O:$O,"Alliances",'Opps Created'!$G:$G,">="&EOMONTH($B23,-1)+1,'Opps Created'!$G:$G,"<="&EOMONTH($B23,0)), SUMIFS('Opps Created'!$E:$E,'Opps Created'!$O:$O,"Cold",'Opps Created'!$G:$G,">="&EOMONTH($B23,-1)+1,'Opps Created'!$G:$G,"<="&EOMONTH($B23,0)) ) -> 5621930 | E23: =SUMIFS('Digital Leads Raw'!$B:$B,'Digital Leads Raw'!$E:$E,">="&EOMONTH($B23,-1)+1,'Digital Leads Raw'!$E:$E,"<="&EOMONTH($B23,0)) +SUMIFS('Event Spend Raw'!$D:$D,'Event Spend Raw'!$G:$G,">="&EOMONTH($B23,-1)+1,'Event Spend Raw'!$G:$G,"<="&EOMONTH($B23,0)) +COUNTIFS('Cold outreach data'!$K:$K,"Cold",'Cold outreach data'!$C:$C,">="&EOMONTH($B23,-1)+1,'Cold outreach data'!$C:$C,"<="&EOMONTH($B23,0)) +COUNTIFS('Alliances Data Raw'!$Q:$Q,">="&EOMONTH($B23,-1)+1,'Alliances Data Raw'!$Q:$Q,"<="&EOMONTH($B23,0),'Alliances Data Raw'!$D:$D,"<>Disqualified",'Alliances Data Raw'!$D:$D,"<>Register Lead") -> 50 | F23: =COUNTIFS('Cold outreach data'!$G:$G,"Yes",'Cold outreach data'!$K:$K,"Digital",'Cold outreach data'!$C:$C,">="&EOMONTH($B23,-1)+1,'Cold outreach data'!$C:$C,"<="&EOMONTH($B23,0))+COUNTIFS('Cold outreach data'!$G:$G,"Yes",'Cold outreach data'!$K:$K,"Event",'Cold outreach data'!$C:$C,">="&EOMONTH($B23,-1)+1,'Cold outreach data'!$C:$C,"<="&EOMONTH($B23,0))+COUNTIFS('Cold outreach data'!$G:$G,"Yes",'Cold outreach data'!$K:$K,"Cold",'Cold outreach data'!$C:$C,">="&EOMONTH($B23,-1)+1,'Cold outreach data'!$C:$C,"<="&EOMONTH($B23,0))+COUNTIFS('Alliances Data Raw'!$W:$W,">="&EOMONTH($B23,-1)+1,'Alliances Data Raw'!$W:$W,"<="&EOMONTH($B23,0)) -> 28 | G23: =D23/C23 -> 936988.33 | H23: =SUMIFS( Table1[Total Net New ACV], Table1[LateStage_Unique_Monthly_Flag], 1, Table1[Change Date], ">="&EOMONTH('Marketing Dashboard'!B23,-1)+1, Table1[Change Date], "<="&EOMONTH('Marketing Dashboard'!B23,0) ) -> 2272163.4 | J23: Aging & Velocity by Channel | S23: Aging & Velocity — Median (Outlier-Resistant)
B24: =EOMONTH($AB$3,-4) -> 46112 | C24: =COUNTIFS('Opps Created'!$G:$G,">="&EOMONTH($B24,-1)+1,'Opps Created'!$G:$G,"<="&EOMONTH($B24,0),'Opps Created'!$O:$O,"<>",'Opps Created'!$O:$O,"<>0",'Opps Created'!$O:$O,"<>Exclude") -> 6 | D24: =SUM( SUMIFS('Opps Created'!$E:$E,'Opps Created'!$O:$O,"Digital",'Opps Created'!$G:$G,">="&EOMONTH($B24,-1)+1,'Opps Created'!$G:$G,"<="&EOMONTH($B24,0)), SUMIFS('Opps Created'!$E:$E,'Opps Created'!$O:$O,"Events",'Opps Created'!$G:$G,">="&EOMONTH($B24,-1)+1,'Opps Created'!$G:$G,"<="&EOMONTH($B24,0)), SUMIFS('Opps Created'!$E:$E,'Opps Created'!$O:$O,"Alliances",'Opps Created'!$G:$G,">="&EOMONTH($B24,-1)+1,'Opps Created'!$G:$G,"<="&EOMONTH($B24,0)), SUMIFS('Opps Created'!$E:$E,'Opps Created'!$O:$O,"Cold",'Opps Created'!$G:$G,">="&EOMONTH($B24,-1)+1,'Opps Created'!$G:$G,"<="&EOMONTH($B24,0)) ) -> 1187160 | E24: =SUMIFS('Digital Leads Raw'!$B:$B,'Digital Leads Raw'!$E:$E,">="&EOMONTH($B24,-1)+1,'Digital Leads Raw'!$E:$E,"<="&EOMONTH($B24,0)) +SUMIFS('Event Spend Raw'!$D:$D,'Event Spend Raw'!$G:$G,">="&EOMONTH($B24,-1)+1,'Event Spend Raw'!$G:$G,"<="&EOMONTH($B24,0)) +COUNTIFS('Cold outreach data'!$K:$K,"Cold",'Cold outreach data'!$C:$C,">="&EOMONTH($B24,-1)+1,'Cold outreach data'!$C:$C,"<="&EOMONTH($B24,0)) +COUNTIFS('Alliances Data Raw'!$Q:$Q,">="&EOMONTH($B24,-1)+1,'Alliances Data Raw'!$Q:$Q,"<="&EOMONTH($B24,0),'Alliances Data Raw'!$D:$D,"<>Disqualified",'Alliances Data Raw'!$D:$D,"<>Register Lead") -> 65 | F24: =COUNTIFS('Cold outreach data'!$G:$G,"Yes",'Cold outreach data'!$K:$K,"Digital",'Cold outreach data'!$C:$C,">="&EOMONTH($B24,-1)+1,'Cold outreach data'!$C:$C,"<="&EOMONTH($B24,0))+COUNTIFS('Cold outreach data'!$G:$G,"Yes",'Cold outreach data'!$K:$K,"Event",'Cold outreach data'!$C:$C,">="&EOMONTH($B24,-1)+1,'Cold outreach data'!$C:$C,"<="&EOMONTH($B24,0))+COUNTIFS('Cold outreach data'!$G:$G,"Yes",'Cold outreach data'!$K:$K,"Cold",'Cold outreach data'!$C:$C,">="&EOMONTH($B24,-1)+1,'Cold outreach data'!$C:$C,"<="&EOMONTH($B24,0))+COUNTIFS('Alliances Data Raw'!$W:$W,">="&EOMONTH($B24,-1)+1,'Alliances Data Raw'!$W:$W,"<="&EOMONTH($B24,0)) -> 26 | G24: =D24/C24 -> 197860 | H24: =SUMIFS( Table1[Total Net New ACV], Table1[LateStage_Unique_Monthly_Flag], 1, Table1[Change Date], ">="&EOMONTH('Marketing Dashboard'!B24,-1)+1, Table1[Change Date], "<="&EOMONTH('Marketing Dashboard'!B24,0) ) -> 2085754.8 | J24: Channel | K24: Days to Late Stage | L24: Late Stage to Won | M24: Days to Won | N24: Avg Open Opp Age | O24: Avg Open Late | P24: Late Stage Deals 30+ Days | Q24: Avg Stage Duration | S24: Channel | T24: Median Days to Late Stage | U24: Median Late Stage to Won | V24: Median Days to Won | W24: Median Open Opp Age | X24: Median Open Late
B25: =EOMONTH($AB$3,-3) -> 46142 | C25: =COUNTIFS('Opps Created'!$G:$G,">="&EOMONTH($B25,-1)+1,'Opps Created'!$G:$G,"<="&EOMONTH($B25,0),'Opps Created'!$O:$O,"<>",'Opps Created'!$O:$O,"<>0",'Opps Created'!$O:$O,"<>Exclude") -> 5 | D25: =SUM( SUMIFS('Opps Created'!$E:$E,'Opps Created'!$O:$O,"Digital",'Opps Created'!$G:$G,">="&EOMONTH($B25,-1)+1,'Opps Created'!$G:$G,"<="&EOMONTH($B25,0)), SUMIFS('Opps Created'!$E:$E,'Opps Created'!$O:$O,"Events",'Opps Created'!$G:$G,">="&EOMONTH($B25,-1)+1,'Opps Created'!$G:$G,"<="&EOMONTH($B25,0)), SUMIFS('Opps Created'!$E:$E,'Opps Created'!$O:$O,"Alliances",'Opps Created'!$G:$G,">="&EOMONTH($B25,-1)+1,'Opps Created'!$G:$G,"<="&EOMONTH($B25,0)), SUMIFS('Opps Created'!$E:$E,'Opps Created'!$O:$O,"Cold",'Opps Created'!$G:$G,">="&EOMONTH($B25,-1)+1,'Opps Created'!$G:$G,"<="&EOMONTH($B25,0)) ) -> 1314016 | E25: =SUMIFS('Digital Leads Raw'!$B:$B,'Digital Leads Raw'!$E:$E,">="&EOMONTH($B25,-1)+1,'Digital Leads Raw'!$E:$E,"<="&EOMONTH($B25,0)) +SUMIFS('Event Spend Raw'!$D:$D,'Event Spend Raw'!$G:$G,">="&EOMONTH($B25,-1)+1,'Event Spend Raw'!$G:$G,"<="&EOMONTH($B25,0)) +COUNTIFS('Cold outreach data'!$K:$K,"Cold",'Cold outreach data'!$C:$C,">="&EOMONTH($B25,-1)+1,'Cold outreach data'!$C:$C,"<="&EOMONTH($B25,0)) +COUNTIFS('Alliances Data Raw'!$Q:$Q,">="&EOMONTH($B25,-1)+1,'Alliances Data Raw'!$Q:$Q,"<="&EOMONTH($B25,0),'Alliances Data Raw'!$D:$D,"<>Disqualified",'Alliances Data Raw'!$D:$D,"<>Register Lead") -> 130 | F25: =COUNTIFS('Cold outreach data'!$G:$G,"Yes",'Cold outreach data'!$K:$K,"Digital",'Cold outreach data'!$C:$C,">="&EOMONTH($B25,-1)+1,'Cold outreach data'!$C:$C,"<="&EOMONTH($B25,0))+COUNTIFS('Cold outreach data'!$G:$G,"Yes",'Cold outreach data'!$K:$K,"Event",'Cold outreach data'!$C:$C,">="&EOMONTH($B25,-1)+1,'Cold outreach data'!$C:$C,"<="&EOMONTH($B25,0))+COUNTIFS('Cold outreach data'!$G:$G,"Yes",'Cold outreach data'!$K:$K,"Cold",'Cold outreach data'!$C:$C,">="&EOMONTH($B25,-1)+1,'Cold outreach data'!$C:$C,"<="&EOMONTH($B25,0))+COUNTIFS('Alliances Data Raw'!$W:$W,">="&EOMONTH($B25,-1)+1,'Alliances Data Raw'!$W:$W,"<="&EOMONTH($B25,0)) -> 28 | G25: =D25/C25 -> 262803.2 | H25: =SUMIFS( Table1[Total Net New ACV], Table1[LateStage_Unique_Monthly_Flag], 1, Table1[Change Date], ">="&EOMONTH('Marketing Dashboard'!B25,-1)+1, Table1[Change Date], "<="&EOMONTH('Marketing Dashboard'!B25,0) ) -> 720770 | J25: Digital | K25: =IFERROR(ROUND(AVERAGEIFS(Table1[Days Created to Late Stage],Table1[Channel],$J25,Table1[Current Stage Flag],1,Table1[Include in Aging Calc],TRUE,Table1[Days Created to Late Stage],">0"),0),"") -> 137 | L25: =IFERROR(ROUND(AVERAGEIFS(Table1[Days from Late Stage to Closed Won],Table1[Channel],$J25,Table1[Current Stage Flag],1,Table1[Include in Aging Calc],TRUE,Table1[Days from Late Stage to Closed Won],">0"),0),"") -> 122 | M25: =IFERROR(ROUND(AVERAGEIFS(Table1[Days Created to Won],Table1[Channel],$J25,Table1[Current Stage Flag],1,Table1[Include in Aging Calc],TRUE,Table1[Days Created to Won],">0"),0),"") -> 224 | N25: =IFERROR(ROUND(AVERAGEIFS(Table2[Opp Age (Total Age)],Table2[Channel],$J25,Table2[Closed Flag],0,Table2[Include in Aging Calc],TRUE,Table2[Opp Age (Total Age)],">0"),0),"") -> 534 | O25: =IFERROR(ROUND(AVERAGEIFS(Table2[Opp Age (Total Age)],Table2[Channel],$J25,Table2[Late Stage Flag],1,Table2[Closed Flag],0,Table2[Include in Aging Calc],TRUE,Table2[Opp Age (Total Age)],">0"),0),"") | P25: =COUNTIFS( 'Opps Created'!$O:$O,$J25, 'Opps Created'!$Q:$Q,1, 'Opps Created'!$R:$R,0, 'Opps Created'!$P:$P,">30" ) -> 1 | Q25: =IFERROR( ROUND( AVERAGEIFS( 'Opps Created'!$N:$N, 'Opps Created'!$O:$O,$J25, 'Opps Created'!$R:$R,0, 'Opps Created'!$N:$N,">0" ),0), "" ) -> 278 | S25: =$J25 -> Digital | T25: ='Aging Detail'!B6 -> 155 | U25: ='Aging Detail'!C6 -> 126 | V25: ='Aging Detail'!D6 -> 173 | W25: ='Aging Detail'!E6 -> 542 | X25: ='Aging Detail'!F6
B26: =EOMONTH($AB$3,-2) -> 46173 | C26: =COUNTIFS('Opps Created'!$G:$G,">="&EOMONTH($B26,-1)+1,'Opps Created'!$G:$G,"<="&EOMONTH($B26,0),'Opps Created'!$O:$O,"<>",'Opps Created'!$O:$O,"<>0",'Opps Created'!$O:$O,"<>Exclude") -> 7 | D26: =SUM( SUMIFS('Opps Created'!$E:$E,'Opps Created'!$O:$O,"Digital",'Opps Created'!$G:$G,">="&EOMONTH($B26,-1)+1,'Opps Created'!$G:$G,"<="&EOMONTH($B26,0)), SUMIFS('Opps Created'!$E:$E,'Opps Created'!$O:$O,"Events",'Opps Created'!$G:$G,">="&EOMONTH($B26,-1)+1,'Opps Created'!$G:$G,"<="&EOMONTH($B26,0)), SUMIFS('Opps Created'!$E:$E,'Opps Created'!$O:$O,"Alliances",'Opps Created'!$G:$G,">="&EOMONTH($B26,-1)+1,'Opps Created'!$G:$G,"<="&EOMONTH($B26,0)), SUMIFS('Opps Created'!$E:$E,'Opps Created'!$O:$O,"Cold",'Opps Created'!$G:$G,">="&EOMONTH($B26,-1)+1,'Opps Created'!$G:$G,"<="&EOMONTH($B26,0)) ) -> 2319060 | E26: =SUMIFS('Digital Leads Raw'!$B:$B,'Digital Leads Raw'!$E:$E,">="&EOMONTH($B26,-1)+1,'Digital Leads Raw'!$E:$E,"<="&EOMONTH($B26,0)) +SUMIFS('Event Spend Raw'!$D:$D,'Event Spend Raw'!$G:$G,">="&EOMONTH($B26,-1)+1,'Event Spend Raw'!$G:$G,"<="&EOMONTH($B26,0)) +COUNTIFS('Cold outreach data'!$K:$K,"Cold",'Cold outreach data'!$C:$C,">="&EOMONTH($B26,-1)+1,'Cold outreach data'!$C:$C,"<="&EOMONTH($B26,0)) +COUNTIFS('Alliances Data Raw'!$Q:$Q,">="&EOMONTH($B26,-1)+1,'Alliances Data Raw'!$Q:$Q,"<="&EOMONTH($B26,0),'Alliances Data Raw'!$D:$D,"<>Disqualified",'Alliances Data Raw'!$D:$D,"<>Register Lead") -> 36 | F26: =COUNTIFS('Cold outreach data'!$G:$G,"Yes",'Cold outreach data'!$K:$K,"Digital",'Cold outreach data'!$C:$C,">="&EOMONTH($B26,-1)+1,'Cold outreach data'!$C:$C,"<="&EOMONTH($B26,0))+COUNTIFS('Cold outreach data'!$G:$G,"Yes",'Cold outreach data'!$K:$K,"Event",'Cold outreach data'!$C:$C,">="&EOMONTH($B26,-1)+1,'Cold outreach data'!$C:$C,"<="&EOMONTH($B26,0))+COUNTIFS('Cold outreach data'!$G:$G,"Yes",'Cold outreach data'!$K:$K,"Cold",'Cold outreach data'!$C:$C,">="&EOMONTH($B26,-1)+1,'Cold outreach data'!$C:$C,"<="&EOMONTH($B26,0))+COUNTIFS('Alliances Data Raw'!$W:$W,">="&EOMONTH($B26,-1)+1,'Alliances Data Raw'!$W:$W,"<="&EOMONTH($B26,0)) -> 26 | G26: =D26/C26 -> 331294.29 | H26: =SUMIFS( Table1[Total Net New ACV], Table1[LateStage_Unique_Monthly_Flag], 1, Table1[Change Date], ">="&EOMONTH('Marketing Dashboard'!B26,-1)+1, Table1[Change Date], "<="&EOMONTH('Marketing Dashboard'!B26,0) ) -> 121585.47 | J26: Events | K26: =IFERROR(ROUND(AVERAGEIFS(Table1[Days Created to Late Stage],Table1[Channel],$J26,Table1[Current Stage Flag],1,Table1[Include in Aging Calc],TRUE,Table1[Days Created to Late Stage],">0"),0),"") -> 231 | L26: =IFERROR(ROUND(AVERAGEIFS(Table1[Days from Late Stage to Closed Won],Table1[Channel],$J26,Table1[Current Stage Flag],1,Table1[Include in Aging Calc],TRUE,Table1[Days from Late Stage to Closed Won],">0"),0),"") | M26: =IFERROR(ROUND(AVERAGEIFS(Table1[Days Created to Won],Table1[Channel],$J26,Table1[Current Stage Flag],1,Table1[Include in Aging Calc],TRUE,Table1[Days Created to Won],">0"),0),"") | N26: =IFERROR(ROUND(AVERAGEIFS(Table2[Opp Age (Total Age)],Table2[Channel],$J26,Table2[Closed Flag],0,Table2[Include in Aging Calc],TRUE,Table2[Opp Age (Total Age)],">0"),0),"") -> 514 | O26: =IFERROR(ROUND(AVERAGEIFS(Table2[Opp Age (Total Age)],Table2[Channel],$J26,Table2[Late Stage Flag],1,Table2[Closed Flag],0,Table2[Include in Aging Calc],TRUE,Table2[Opp Age (Total Age)],">0"),0),"") -> 318 | P26: =COUNTIFS( 'Opps Created'!$O:$O,$J26, 'Opps Created'!$Q:$Q,1, 'Opps Created'!$R:$R,0, 'Opps Created'!$P:$P,">30" ) -> 4 | Q26: =IFERROR( ROUND( AVERAGEIFS( 'Opps Created'!$N:$N, 'Opps Created'!$O:$O,$J26, 'Opps Created'!$R:$R,0, 'Opps Created'!$N:$N,">0" ),0), "" ) -> 286 | S26: =$J26 -> Events | T26: ='Aging Detail'!B7 -> 138 | U26: ='Aging Detail'!C7 | V26: ='Aging Detail'!D7 | W26: ='Aging Detail'!E7 -> 429 | X26: ='Aging Detail'!F7 -> 215
B27: =EOMONTH($AB$3,-1) -> 46203 | C27: =COUNTIFS('Opps Created'!$G:$G,">="&EOMONTH($B27,-1)+1,'Opps Created'!$G:$G,"<="&EOMONTH($B27,0),'Opps Created'!$O:$O,"<>",'Opps Created'!$O:$O,"<>0",'Opps Created'!$O:$O,"<>Exclude") -> 5 | D27: =SUM( SUMIFS('Opps Created'!$E:$E,'Opps Created'!$O:$O,"Digital",'Opps Created'!$G:$G,">="&EOMONTH($B27,-1)+1,'Opps Created'!$G:$G,"<="&EOMONTH($B27,0)), SUMIFS('Opps Created'!$E:$E,'Opps Created'!$O:$O,"Events",'Opps Created'!$G:$G,">="&EOMONTH($B27,-1)+1,'Opps Created'!$G:$G,"<="&EOMONTH($B27,0)), SUMIFS('Opps Created'!$E:$E,'Opps Created'!$O:$O,"Alliances",'Opps Created'!$G:$G,">="&EOMONTH($B27,-1)+1,'Opps Created'!$G:$G,"<="&EOMONTH($B27,0)), SUMIFS('Opps Created'!$E:$E,'Opps Created'!$O:$O,"Cold",'Opps Created'!$G:$G,">="&EOMONTH($B27,-1)+1,'Opps Created'!$G:$G,"<="&EOMONTH($B27,0)) ) -> 727080 | E27: =SUMIFS('Digital Leads Raw'!$B:$B,'Digital Leads Raw'!$E:$E,">="&EOMONTH($B27,-1)+1,'Digital Leads Raw'!$E:$E,"<="&EOMONTH($B27,0)) +SUMIFS('Event Spend Raw'!$D:$D,'Event Spend Raw'!$G:$G,">="&EOMONTH($B27,-1)+1,'Event Spend Raw'!$G:$G,"<="&EOMONTH($B27,0)) +COUNTIFS('Cold outreach data'!$K:$K,"Cold",'Cold outreach data'!$C:$C,">="&EOMONTH($B27,-1)+1,'Cold outreach data'!$C:$C,"<="&EOMONTH($B27,0)) +COUNTIFS('Alliances Data Raw'!$Q:$Q,">="&EOMONTH($B27,-1)+1,'Alliances Data Raw'!$Q:$Q,"<="&EOMONTH($B27,0),'Alliances Data Raw'!$D:$D,"<>Disqualified",'Alliances Data Raw'!$D:$D,"<>Register Lead") -> 16 | F27: =COUNTIFS('Cold outreach data'!$G:$G,"Yes",'Cold outreach data'!$K:$K,"Digital",'Cold outreach data'!$C:$C,">="&EOMONTH($B27,-1)+1,'Cold outreach data'!$C:$C,"<="&EOMONTH($B27,0))+COUNTIFS('Cold outreach data'!$G:$G,"Yes",'Cold outreach data'!$K:$K,"Event",'Cold outreach data'!$C:$C,">="&EOMONTH($B27,-1)+1,'Cold outreach data'!$C:$C,"<="&EOMONTH($B27,0))+COUNTIFS('Cold outreach data'!$G:$G,"Yes",'Cold outreach data'!$K:$K,"Cold",'Cold outreach data'!$C:$C,">="&EOMONTH($B27,-1)+1,'Cold outreach data'!$C:$C,"<="&EOMONTH($B27,0))+COUNTIFS('Alliances Data Raw'!$W:$W,">="&EOMONTH($B27,-1)+1,'Alliances Data Raw'!$W:$W,"<="&EOMONTH($B27,0)) -> 10 | G27: =D27/C27 -> 145416 | H27: =SUMIFS( Table1[Total Net New ACV], Table1[LateStage_Unique_Monthly_Flag], 1, Table1[Change Date], ">="&EOMONTH('Marketing Dashboard'!B27,-1)+1, Table1[Change Date], "<="&EOMONTH('Marketing Dashboard'!B27,0) ) -> 1270750 | J27: Cold | K27: =IFERROR(ROUND(AVERAGEIFS(Table1[Days Created to Late Stage],Table1[Channel],$J27,Table1[Current Stage Flag],1,Table1[Include in Aging Calc],TRUE,Table1[Days Created to Late Stage],">0"),0),"") -> 240 | L27: =IFERROR(ROUND(AVERAGEIFS(Table1[Days from Late Stage to Closed Won],Table1[Channel],$J27,Table1[Current Stage Flag],1,Table1[Include in Aging Calc],TRUE,Table1[Days from Late Stage to Closed Won],">0"),0),"") -> 28 | M27: =IFERROR(ROUND(AVERAGEIFS(Table1[Days Created to Won],Table1[Channel],$J27,Table1[Current Stage Flag],1,Table1[Include in Aging Calc],TRUE,Table1[Days Created to Won],">0"),0),"") -> 171 | N27: =IFERROR(ROUND(AVERAGEIFS(Table2[Opp Age (Total Age)],Table2[Channel],$J27,Table2[Closed Flag],0,Table2[Include in Aging Calc],TRUE,Table2[Opp Age (Total Age)],">0"),0),"") -> 792 | O27: =IFERROR(ROUND(AVERAGEIFS(Table2[Opp Age (Total Age)],Table2[Channel],$J27,Table2[Late Stage Flag],1,Table2[Closed Flag],0,Table2[Include in Aging Calc],TRUE,Table2[Opp Age (Total Age)],">0"),0),"") -> 360 | P27: =COUNTIFS( 'Opps Created'!$O:$O,$J27, 'Opps Created'!$Q:$Q,1, 'Opps Created'!$R:$R,0, 'Opps Created'!$P:$P,">30" ) -> 2 | Q27: =IFERROR( ROUND( AVERAGEIFS( 'Opps Created'!$N:$N, 'Opps Created'!$O:$O,$J27, 'Opps Created'!$R:$R,0, 'Opps Created'!$N:$N,">0" ),0), "" ) -> 434 | S27: =$J27 -> Cold | T27: ='Aging Detail'!B8 -> 191 | U27: ='Aging Detail'!C8 -> 19 | V27: ='Aging Detail'!D8 -> 82 | W27: ='Aging Detail'!E8 -> 790 | X27: ='Aging Detail'!F8 -> 360
B28: =$AB$3 -> 46234 | C28: =COUNTIFS('Opps Created'!$G:$G,">="&EOMONTH($B28,-1)+1,'Opps Created'!$G:$G,"<="&EOMONTH($B28,0),'Opps Created'!$O:$O,"<>",'Opps Created'!$O:$O,"<>0",'Opps Created'!$O:$O,"<>Exclude") -> 10 | D28: =SUM( SUMIFS('Opps Created'!$E:$E,'Opps Created'!$O:$O,"Digital",'Opps Created'!$G:$G,">="&EOMONTH($B28,-1)+1,'Opps Created'!$G:$G,"<="&EOMONTH($B28,0)), SUMIFS('Opps Created'!$E:$E,'Opps Created'!$O:$O,"Events",'Opps Created'!$G:$G,">="&EOMONTH($B28,-1)+1,'Opps Created'!$G:$G,"<="&EOMONTH($B28,0)), SUMIFS('Opps Created'!$E:$E,'Opps Created'!$O:$O,"Alliances",'Opps Created'!$G:$G,">="&EOMONTH($B28,-1)+1,'Opps Created'!$G:$G,"<="&EOMONTH($B28,0)), SUMIFS('Opps Created'!$E:$E,'Opps Created'!$O:$O,"Cold",'Opps Created'!$G:$G,">="&EOMONTH($B28,-1)+1,'Opps Created'!$G:$G,"<="&EOMONTH($B28,0)) ) -> 6517080 | E28: =SUMIFS('Digital Leads Raw'!$B:$B,'Digital Leads Raw'!$E:$E,">="&EOMONTH($B28,-1)+1,'Digital Leads Raw'!$E:$E,"<="&EOMONTH($B28,0)) +SUMIFS('Event Spend Raw'!$D:$D,'Event Spend Raw'!$G:$G,">="&EOMONTH($B28,-1)+1,'Event Spend Raw'!$G:$G,"<="&EOMONTH($B28,0)) +COUNTIFS('Cold outreach data'!$K:$K,"Cold",'Cold outreach data'!$C:$C,">="&EOMONTH($B28,-1)+1,'Cold outreach data'!$C:$C,"<="&EOMONTH($B28,0)) +COUNTIFS('Alliances Data Raw'!$Q:$Q,">="&EOMONTH($B28,-1)+1,'Alliances Data Raw'!$Q:$Q,"<="&EOMONTH($B28,0),'Alliances Data Raw'!$D:$D,"<>Disqualified",'Alliances Data Raw'!$D:$D,"<>Register Lead") -> 17 | F28: =COUNTIFS('Cold outreach data'!$G:$G,"Yes",'Cold outreach data'!$K:$K,"Digital",'Cold outreach data'!$C:$C,">="&EOMONTH($B28,-1)+1,'Cold outreach data'!$C:$C,"<="&EOMONTH($B28,0))+COUNTIFS('Cold outreach data'!$G:$G,"Yes",'Cold outreach data'!$K:$K,"Event",'Cold outreach data'!$C:$C,">="&EOMONTH($B28,-1)+1,'Cold outreach data'!$C:$C,"<="&EOMONTH($B28,0))+COUNTIFS('Cold outreach data'!$G:$G,"Yes",'Cold outreach data'!$K:$K,"Cold",'Cold outreach data'!$C:$C,">="&EOMONTH($B28,-1)+1,'Cold outreach data'!$C:$C,"<="&EOMONTH($B28,0))+COUNTIFS('Alliances Data Raw'!$W:$W,">="&EOMONTH($B28,-1)+1,'Alliances Data Raw'!$W:$W,"<="&EOMONTH($B28,0)) -> 13 | G28: =D28/C28 -> 651708 | H28: =SUMIFS( Table1[Total Net New ACV], Table1[LateStage_Unique_Monthly_Flag], 1, Table1[Change Date], ">="&EOMONTH('Marketing Dashboard'!B28,-1)+1, Table1[Change Date], "<="&EOMONTH('Marketing Dashboard'!B28,0) ) -> 2291910.6 | J28: Alliances | K28: =IFERROR(ROUND(AVERAGEIFS(Table1[Days Created to Late Stage],Table1[Channel],$J28,Table1[Current Stage Flag],1,Table1[Include in Aging Calc],TRUE,Table1[Days Created to Late Stage],">0"),0),"") -> 153 | L28: =IFERROR(ROUND(AVERAGEIFS(Table1[Days from Late Stage to Closed Won],Table1[Channel],$J28,Table1[Current Stage Flag],1,Table1[Include in Aging Calc],TRUE,Table1[Days from Late Stage to Closed Won],">0"),0),"") -> 61 | M28: =IFERROR(ROUND(AVERAGEIFS(Table1[Days Created to Won],Table1[Channel],$J28,Table1[Current Stage Flag],1,Table1[Include in Aging Calc],TRUE,Table1[Days Created to Won],">0"),0),"") -> 225 | N28: =IFERROR(ROUND(AVERAGEIFS(Table2[Opp Age (Total Age)],Table2[Channel],$J28,Table2[Closed Flag],0,Table2[Include in Aging Calc],TRUE,Table2[Opp Age (Total Age)],">0"),0),"") -> 663 | O28: =IFERROR(ROUND(AVERAGEIFS(Table2[Opp Age (Total Age)],Table2[Channel],$J28,Table2[Late Stage Flag],1,Table2[Closed Flag],0,Table2[Include in Aging Calc],TRUE,Table2[Opp Age (Total Age)],">0"),0),"") -> 217 | P28: =COUNTIFS( 'Opps Created'!$O:$O,$J28, 'Opps Created'!$Q:$Q,1, 'Opps Created'!$R:$R,0, 'Opps Created'!$P:$P,">30" ) -> 5 | Q28: =IFERROR( ROUND( AVERAGEIFS( 'Opps Created'!$N:$N, 'Opps Created'!$O:$O,$J28, 'Opps Created'!$R:$R,0, 'Opps Created'!$N:$N,">0" ),0), "" ) -> 320 | S28: =$J28 -> Alliances | T28: ='Aging Detail'!B9 -> 94 | U28: ='Aging Detail'!C9 -> 55 | V28: ='Aging Detail'!D9 -> 170 | W28: ='Aging Detail'!E9 -> 560 | X28: ='Aging Detail'!F9 -> 201
J29: TOTAL | K29: =IFERROR(ROUND(AVERAGEIFS(Table1[Days Created to Late Stage],Table1[Current Stage Flag],1,Table1[Include in Aging Calc],TRUE,Table1[Days Created to Late Stage],">0"),0),"") -> 139 | L29: =IFERROR(ROUND(AVERAGEIFS(Table1[Days from Late Stage to Closed Won],Table1[Current Stage Flag],1,Table1[Include in Aging Calc],TRUE,Table1[Days from Late Stage to Closed Won],">0"),0),"") -> 51 | M29: =IFERROR(ROUND(AVERAGEIFS(Table1[Days Created to Won],Table1[Current Stage Flag],1,Table1[Include in Aging Calc],TRUE,Table1[Days Created to Won],">0"),0),"") -> 184 | N29: =IFERROR(ROUND(AVERAGEIFS(Table2[Opp Age (Total Age)],Table2[Closed Flag],0,Table2[Include in Aging Calc],TRUE,Table2[Opp Age (Total Age)],">0"),0),"") -> 704 | O29: =IFERROR(ROUND(AVERAGEIFS(Table2[Opp Age (Total Age)],Table2[Late Stage Flag],1,Table2[Closed Flag],0,Table2[Include in Aging Calc],TRUE,Table2[Opp Age (Total Age)],">0"),0),"") -> 490 | P29: =SUM(P25:P28) -> 12 | Q29: =IFERROR(ROUND(AVERAGEIFS('Opps Created'!$N:$N,'Opps Created'!$R:$R,0,'Opps Created'!$N:$N,">0"),0),"") -> 371 | S29: =$J29 -> TOTAL | T29: ='Aging Detail'!B10 -> 66 | U29: ='Aging Detail'!C10 -> 31 | V29: ='Aging Detail'!D10 -> 128 | W29: ='Aging Detail'!E10 -> 574 | X29: ='Aging Detail'!F10 -> 297
J31: =COUNTIF('Aging Detail'!$F$14:$F$20,FALSE)&" stale/outlier deal(s) currently excluded from the averages above — see the Aging Detail tab to review or change." -> 4 stale/outlier deal(s) currently excluded from the averages above — see the Aging Detail tab to review or change. | Q31: Open tab → | S31: ="Median view of the same filtered deals (Include in Aging Calc = TRUE) as the Average table — shows the typical deal, since Average can still be pulled up by a few large but legitimate deals. See Aging Detail tab for the deal-level filter." -> Median view of the same filtered deals (Include in Aging Calc = TRUE) as the Average table — shows the typical deal, since Average can still be pulled up by a few large but legitimate deals. See Aging Detail tab for the deal-level filter.

Sheet Aging Detail
A1: Aging & Velocity — Outlier & Median Detail
A2: Backs the Aging & Velocity by Channel section on the Marketing Dashboard tab. Flip 'Include in Aging Calc?' below to include/exclude a flagged deal from the headline averages.
A4: Median (Outlier-Resistant View)
A5: Channel | B5: Median Days to Late Stage | C5: Median Late Stage to Won | D5: Median Days to Won | E5: Median Open Opp Age | F5: Median Open Late
A6: Digital | B6: {=IFERROR(ROUND(MEDIAN(IF((Table1[Channel]=$A6)*(Table1[Current Stage Flag]=1)*(Table1[Include in Aging Calc]=TRUE)*(Table1[Days Created to Late Stage]>0),Table1[Days Created to Late Stage])),0),"")} -> 155 | C6: {=IFERROR(ROUND(MEDIAN(IF((Table1[Channel]=$A6)*(Table1[Current Stage Flag]=1)*(Table1[Include in Aging Calc]=TRUE)*(Table1[Days from Late Stage to Closed Won]>0),Table1[Days from Late Stage to Closed Won])),0),"")} -> 126 | D6: {=IFERROR(ROUND(MEDIAN(IF((Table1[Channel]=$A6)*(Table1[Current Stage Flag]=1)*(Table1[Include in Aging Calc]=TRUE)*(Table1[Days Created to Won]>0),Table1[Days Created to Won])),0),"")} -> 173 | E6: {=IFERROR(ROUND(MEDIAN(IF((Table2[Channel]=$A6)*(Table2[Closed Flag]=0)*(Table2[Include in Aging Calc]=TRUE)*(Table2[Opp Age (Total Age)]>0),Table2[Opp Age (Total Age)])),0),"")} -> 542 | F6: {=IFERROR(ROUND(MEDIAN(IF((Table2[Channel]=$A6)*(Table2[Late Stage Flag]=1)*(Table2[Closed Flag]=0)*(Table2[Include in Aging Calc]=TRUE)*(Table2[Opp Age (Total Age)]>0),Table2[Opp Age (Total Age)])),0),"")}
A7: Events | B7: {=IFERROR(ROUND(MEDIAN(IF((Table1[Channel]=$A7)*(Table1[Current Stage Flag]=1)*(Table1[Include in Aging Calc]=TRUE)*(Table1[Days Created to Late Stage]>0),Table1[Days Created to Late Stage])),0),"")} -> 138 | C7: {=IFERROR(ROUND(MEDIAN(IF((Table1[Channel]=$A7)*(Table1[Current Stage Flag]=1)*(Table1[Include in Aging Calc]=TRUE)*(Table1[Days from Late Stage to Closed Won]>0),Table1[Days from Late Stage to Closed Won])),0),"")} | D7: {=IFERROR(ROUND(MEDIAN(IF((Table1[Channel]=$A7)*(Table1[Current Stage Flag]=1)*(Table1[Include in Aging Calc]=TRUE)*(Table1[Days Created to Won]>0),Table1[Days Created to Won])),0),"")} | E7: {=IFERROR(ROUND(MEDIAN(IF((Table2[Channel]=$A7)*(Table2[Closed Flag]=0)*(Table2[Include in Aging Calc]=TRUE)*(Table2[Opp Age (Total Age)]>0),Table2[Opp Age (Total Age)])),0),"")} -> 429 | F7: {=IFERROR(ROUND(MEDIAN(IF((Table2[Channel]=$A7)*(Table2[Late Stage Flag]=1)*(Table2[Closed Flag]=0)*(Table2[Include in Aging Calc]=TRUE)*(Table2[Opp Age (Total Age)]>0),Table2[Opp Age (Total Age)])),0),"")} -> 215
A8: Cold | B8: {=IFERROR(ROUND(MEDIAN(IF((Table1[Channel]=$A8)*(Table1[Current Stage Flag]=1)*(Table1[Include in Aging Calc]=TRUE)*(Table1[Days Created to Late Stage]>0),Table1[Days Created to Late Stage])),0),"")} -> 191 | C8: {=IFERROR(ROUND(MEDIAN(IF((Table1[Channel]=$A8)*(Table1[Current Stage Flag]=1)*(Table1[Include in Aging Calc]=TRUE)*(Table1[Days from Late Stage to Closed Won]>0),Table1[Days from Late Stage to Closed Won])),0),"")} -> 19 | D8: {=IFERROR(ROUND(MEDIAN(IF((Table1[Channel]=$A8)*(Table1[Current Stage Flag]=1)*(Table1[Include in Aging Calc]=TRUE)*(Table1[Days Created to Won]>0),Table1[Days Created to Won])),0),"")} -> 82 | E8: {=IFERROR(ROUND(MEDIAN(IF((Table2[Channel]=$A8)*(Table2[Closed Flag]=0)*(Table2[Include in Aging Calc]=TRUE)*(Table2[Opp Age (Total Age)]>0),Table2[Opp Age (Total Age)])),0),"")} -> 790 | F8: {=IFERROR(ROUND(MEDIAN(IF((Table2[Channel]=$A8)*(Table2[Late Stage Flag]=1)*(Table2[Closed Flag]=0)*(Table2[Include in Aging Calc]=TRUE)*(Table2[Opp Age (Total Age)]>0),Table2[Opp Age (Total Age)])),0),"")} -> 360
A9: Alliances | B9: {=IFERROR(ROUND(MEDIAN(IF((Table1[Channel]=$A9)*(Table1[Current Stage Flag]=1)*(Table1[Include in Aging Calc]=TRUE)*(Table1[Days Created to Late Stage]>0),Table1[Days Created to Late Stage])),0),"")} -> 94 | C9: {=IFERROR(ROUND(MEDIAN(IF((Table1[Channel]=$A9)*(Table1[Current Stage Flag]=1)*(Table1[Include in Aging Calc]=TRUE)*(Table1[Days from Late Stage to Closed Won]>0),Table1[Days from Late Stage to Closed Won])),0),"")} -> 55 | D9: {=IFERROR(ROUND(MEDIAN(IF((Table1[Channel]=$A9)*(Table1[Current Stage Flag]=1)*(Table1[Include in Aging Calc]=TRUE)*(Table1[Days Created to Won]>0),Table1[Days Created to Won])),0),"")} -> 170 | E9: {=IFERROR(ROUND(MEDIAN(IF((Table2[Channel]=$A9)*(Table2[Closed Flag]=0)*(Table2[Include in Aging Calc]=TRUE)*(Table2[Opp Age (Total Age)]>0),Table2[Opp Age (Total Age)])),0),"")} -> 560 | F9: {=IFERROR(ROUND(MEDIAN(IF((Table2[Channel]=$A9)*(Table2[Late Stage Flag]=1)*(Table2[Closed Flag]=0)*(Table2[Include in Aging Calc]=TRUE)*(Table2[Opp Age (Total Age)]>0),Table2[Opp Age (Total Age)])),0),"")} -> 201
A10: TOTAL | B10: {=IFERROR(ROUND(MEDIAN(IF((Table1[Current Stage Flag]=1)*(Table1[Include in Aging Calc]=TRUE)*(Table1[Days Created to Late Stage]>0),Table1[Days Created to Late Stage])),0),"")} -> 66 | C10: {=IFERROR(ROUND(MEDIAN(IF((Table1[Current Stage Flag]=1)*(Table1[Include in Aging Calc]=TRUE)*(Table1[Days from Late Stage to Closed Won]>0),Table1[Days from Late Stage to Closed Won])),0),"")} -> 31 | D10: {=IFERROR(ROUND(MEDIAN(IF((Table1[Current Stage Flag]=1)*(Table1[Include in Aging Calc]=TRUE)*(Table1[Days Created to Won]>0),Table1[Days Created to Won])),0),"")} -> 128 | E10: {=IFERROR(ROUND(MEDIAN(IF((Table2[Closed Flag]=0)*(Table2[Include in Aging Calc]=TRUE)*(Table2[Opp Age (Total Age)]>0),Table2[Opp Age (Total Age)])),0),"")} -> 574 | F10: {=IFERROR(ROUND(MEDIAN(IF((Table2[Late Stage Flag]=1)*(Table2[Closed Flag]=0)*(Table2[Include in Aging Calc]=TRUE)*(Table2[Opp Age (Total Age)]>0),Table2[Opp Age (Total Age)])),0),"")} -> 297
A12: Outlier Watch List — Aging & Velocity
A13: Channel | B13: Opportunity / Account | C13: Metric Flagged | D13: Days | E13: Why It's Flagged | F13: Include in Aging Calc? | G13: Recommendation | H13: Opp ID (lookup key)
A14: Digital | B14: TIAA-CREF - NCC - Post Pilot / TIAA-CREF | C14: Avg Open Opp Age & Avg Open Late | D14: =ROUND(AVERAGEIFS(Table2[Opp Age (Total Age)],Table2[Opportunity ID],$H14),0) -> 1384 | E14: ="Only open, late-stage Digital deal (n="&COUNTIFS(Table2[Channel],"Digital",Table2[Late Stage Flag],1,Table2[Closed Flag],0)&") — this single deal is the entire 'Avg Open Late' figure, not a true average." -> Only open, late-stage Digital deal (n=1) — this single deal is the entire 'Avg Open Late' figure, not a true average. | F14: FALSE | G14: Exclude — n=1, not a real average | H14: 006V50000052eDA
A15: Cold | B15: Toyota Financial / Toyota Financial Services Corporation | C15: Avg Open Opp Age | D15: =ROUND(AVERAGEIFS(Table2[Opp Age (Total Age)],Table2[Opportunity ID],$H15),0) -> 2551 | E15: ="Open "&D15&" days vs. Cold Outreach median of "&$E$8&" days (~"&ROUND(D15/$E$8,1)&"x)" -> Open 2551 days vs. Cold Outreach median of 790 days (~3.2x) | F15: FALSE | G15: Exclude — stale, recommend reviewing for close-out | H15: 006V50000052Y5D
A16: Cold | B16: Cardworks / CardWorks Inc | C16: Avg Open Opp Age | D16: =ROUND(AVERAGEIFS(Table2[Opp Age (Total Age)],Table2[Opportunity ID],$H16),0) -> 2464 | E16: ="Open "&D16&" days vs. Cold Outreach median of "&$E$8&" days (~"&ROUND(D16/$E$8,1)&"x)" -> Open 2464 days vs. Cold Outreach median of 790 days (~3.1x) | F16: FALSE | G16: Exclude — stale, recommend reviewing for close-out | H16: 006V50000052SJD
A17: Alliances | B17: Humana - BPO Post Pilot / Humana | C17: Avg Open Opp Age | D17: =ROUND(AVERAGEIFS(Table2[Opp Age (Total Age)],Table2[Opportunity ID],$H17),0) -> 2294 | E17: ="Open "&D17&" days vs. Alliances median of "&$E$9&" days (~"&ROUND(D17/$E$9,1)&"x)" -> Open 2294 days vs. Alliances median of 560 days (~4.1x) | F17: FALSE | G17: Exclude — stale, recommend reviewing for close-out | H17: 006V50000052Zud
A18: Alliances | B18: RACV-Insurance + Roadside - Post Pilot / RACV | C18: Days to Late Stage & Days to Won | D18: =ROUND(AVERAGEIFS(Table1[Days Created to Won],Table1[Opportunity ID],$H18,Table1[Current Stage Flag],1),0) -> 694 | E18: ="Closed-won in "&D18&" days vs. Alliances median of "&$D$9&" days (~"&ROUND(D18/$D$9,1)&"x)" -> Closed-won in 694 days vs. Alliances median of 170 days (~4.1x) | F18: TRUE | G18: Keep — real closed-won deal; flagged for visibility only | H18: 006V50000052bFG
A19: Alliances | B19: BSW Health - Phase 1 / Baylor Scott & White Health | C19: Days to Won | D19: =ROUND(AVERAGEIFS(Table1[Days Created to Won],Table1[Opportunity ID],$H19,Table1[Current Stage Flag],1),0) -> 773 | E19: ="Closed-won in "&D19&" days vs. Alliances median of "&$D$9&" days (~"&ROUND(D19/$D$9,1)&"x)" -> Closed-won in 773 days vs. Alliances median of 170 days (~4.5x) | F19: TRUE | G19: Keep — real closed-won deal; flagged for visibility only | H19: 006V50000052Obr
A20: Alliances | B20: SCAN Health / SCAN Health Plan | C20: Late Stage to Won | D20: =ROUND(AVERAGEIFS(Table1[Days from Late Stage to Closed Won],Table1[Opportunity ID],$H20,Table1[Current Stage Flag],1),0) -> 227 | E20: ="Closed-won "&D20&" days after reaching late stage vs. Alliances median of "&$C$9&" days (~"&ROUND(D20/$C$9,1)&"x)" -> Closed-won 227 days after reaching late stage vs. Alliances median of 55 days (~4.1x) | F20: TRUE | G20: Keep — real closed-won deal; flagged for visibility only | H20: 006V500000DoExx

Sheet TOTAL
B2: Pipeline Council - BIG PICTURE | K2: Running Cohort | N2: 18 | O2: Months
B3: Month | C3: 46234
B4: MQL / MQA | F4: MEETINGS | J4: OPPORTUNITIES | N4: LATE STAGE | R4: CLOSED WON
B5: Last Month | F5: Last Month | J5: Last Month | N5: Last Month | R5: Last Month
B6: MQL | C6: =SUM(Digital!C6,Events!C6,'Cold Outreach'!C6,Alliances!C6) -> 17 | F6: Meetings | G6: =SUM(Digital!G6,Events!G6,'Cold Outreach'!G6,Alliances!G6) -> 13 | J6: Created | K6: =SUM(Digital!K6,Events!K6,'Cold Outreach'!K6,Alliances!K6) -> 10 | N6: Moved | O6: =SUM(Digital!O6,Events!O6,'Cold Outreach'!O6,Alliances!O6) -> 7 | R6: Won | S6: =SUM(Digital!S6,Events!S6,'Cold Outreach'!S6,Alliances!S6) -> 1
B7: MQA | C7: =SUM(Digital!C7,Events!C7,'Cold Outreach'!C7,Alliances!C7) -> 17 | F7: MQL to Meeting | G7: =IFERROR(G6/C6,0) -> 0.76470588 | J7: ACV $ | K7: =SUM(Digital!K7,Events!K7,'Cold Outreach'!K7,Alliances!K7) -> 6517080 | N7: ACV $ | O7: =SUM(Digital!O7,Events!O7,'Cold Outreach'!O7,Alliances!O7) -> 1218856 | R7: ACV $ | S7: =SUM(Digital!S7,Events!S7,'Cold Outreach'!S7,Alliances!S7) -> 60000
J8: Meeting to Opp | K8: =IFERROR(K6/G6,0) -> 0.76923077
B9: Running Total | F9: Running Total | J9: Running Total | N9: Running Total | R9: Running Total
B10: MQL | C10: =SUM(Digital!C10,Events!C10,'Cold Outreach'!C10,Alliances!C10) -> 822 | F10: Meetings | G10: =SUM(Digital!G10,Events!G10,'Cold Outreach'!G10,Alliances!G10) -> 269 | J10: Created | K10: =SUM(Digital!K10,Events!K10,'Cold Outreach'!K10,Alliances!K10) -> 133 | N10: Moved | O10: =SUM(Digital!O10,Events!O10,'Cold Outreach'!O10,Alliances!O10) -> 12 | R10: Won | S10: =SUM(Digital!S10,Events!S10,'Cold Outreach'!S10,Alliances!S10) -> 31
B11: MQA | C11: =SUM(Digital!C11,Events!C11,'Cold Outreach'!C11,Alliances!C11) -> 628 | F11: MQL to Meeting | G11: =IFERROR(G10/C10,0) -> 0.32725061 | J11: ACV $ | K11: =SUM(Digital!K11,Events!K11,'Cold Outreach'!K11,Alliances!K11) -> 60630001 | N11: ACV $ | O11: =SUM(Digital!O11,Events!O11,'Cold Outreach'!O11,Alliances!O11) -> 3889357.8 | R11: ACV $ | S11: =SUM(Digital!S11,Events!S11,'Cold Outreach'!S11,Alliances!S11) -> 3037724.1
J12: Meeting to Opp | K12: =IFERROR(K10/G10,0) -> 0.49442379 | N12: % in Late | O12: =O10/K10 -> 0.090225564 | R12: % in Closed | S12: =S10/K10 -> 0.23308271
B14: Last Month Spend | F14: =SUM(IFERROR(Digital!F14,0),IFERROR(Events!F14,0),IFERROR('Cold Outreach'!F14,0),IFERROR(Alliances!F14,0)) -> 75325.15 | I14: $1 Spend drives | O14: =IFERROR(K7/F14,"") -> 86.51931 | P14: In new ACV Pipeline
B15: Running Spend | F15: =SUM(IFERROR(Digital!F15,0),IFERROR(Events!F15,0),IFERROR('Cold Outreach'!F15,0),IFERROR(Alliances!F15,0)) -> 1967771.7 | I15: $1 Spend drives | O15: =K11/F15 -> 30.811502 | P15: In new ACV Pipeline
O16: =ROUND(O11/F15,1) -> 2 | P16: In Late Stage ACV Pipeline
N17: $1 Spend Drives | O17: =((O11*0.55)+S11)/F15 -> 2.630829 | P17: In new ACV
B18: Includes all spend, activities and results from Alliances, Digital, Events and Cold Outreach

Sheet Digital
B1: Digital
B2: Pipeline Council - BIG PICTURE | K2: Running Cohort | N2: =TOTAL!N2 -> 18 | O2: Months
B3: Month | C3: =TOTAL!C3 -> 46234
B4: MQL / MQA | F4: MEETINGS | J4: OPPORTUNITIES | N4: LATE STAGE | R4: CLOSED WON
B5: Last Month | F5: Last Month | J5: Last Month | N5: Last Month | R5: Last Month
B6: MQL | C6: =SUMIFS('Digital Leads Raw'!$B1:$B933,'Digital Leads Raw'!$E1:$E933,">="&EOMONTH($C$3,-1)+1,'Digital Leads Raw'!$E1:$E933,"<="&EOMONTH($C$3,0)) -> 6 | F6: Meetings | G6: =COUNTIFS('Cold outreach data'!$K$2:$K$251,"Digital",'Cold outreach data'!$G$2:$G$251,"Yes",'Cold outreach data'!$C$2:$C$251,">="&DATE(YEAR($C$3),MONTH($C$3),1),'Cold outreach data'!$C$2:$C$251,"<="&EOMONTH($C$3,0)) -> 2 | J6: Created | K6: =COUNTIFS('Opps Created'!$O:$O,$B$1,'Opps Created'!$G:$G,">="&EOMONTH($C$3,-1)+1,'Opps Created'!$G:$G,"<="&EOMONTH($C$3,0)) -> 2 | N6: Moved | O6: =SUMIFS( 'Stage History'!$S:$S, 'Stage History'!$O:$O,$B$1, 'Stage History'!$P:$P,">="&EOMONTH($C$3,-1)+1, 'Stage History'!$P:$P,"<"&EOMONTH($C$3,0)+1 ) -> 1 | R6: Won | S6: =SUMIFS( 'Stage History'!$T:$T, 'Stage History'!$O:$O,"Digital", 'Stage History'!$P:$P,">="&EOMONTH($C$3,-1)+1, 'Stage History'!$P:$P,"<"&EOMONTH($C$3,0)+1 ) -> 1
B7: MQA | C7: =SUMIFS('Digital Leads Raw'!$C1:$C933,'Digital Leads Raw'!$E1:$E933,">="&EOMONTH($C$3,-1)+1,'Digital Leads Raw'!$E1:$E933,"<="&EOMONTH($C$3,0)) -> 6 | F7: MQL to Meeting | G7: =IFERROR(G6/C6,0) -> 0.33333333 | J7: Total Amount | K7: =SUMIFS('Opps Created'!$E:$E,'Opps Created'!$O:$O,$B$1,'Opps Created'!$G:$G,">="&EOMONTH($C$3,-1)+1,'Opps Created'!$G:$G,"<="&EOMONTH($C$3,0)) -> 2680000 | N7: Total Amount | O7: =SUMIFS('Stage History'!$K:$K,'Stage History'!$O:$O,$B$1,'Stage History'!$S:$S,1,'Stage History'!$P:$P,">="&EOMONTH($C$3,-1)+1, 'Stage History'!$P:$P,"<"&EOMONTH($C$3,0)+1 ) -> 119448 | R7: ACV $ | S7: =SUMIFS('Stage History'!$L:$L,'Stage History'!$O:$O,"Digital",'Stage History'!$T:$T,1,'Stage History'!$P:$P,">="&EOMONTH($C$3,-1)+1,'Stage History'!$P:$P,"<"&EOMONTH($C$3,0)+1) -> 60000
J8: ACV $ | K8: =SUMIFS('Opps Created'!$M:$M,'Opps Created'!$O:$O,$B$1,'Opps Created'!$G:$G,">="&EOMONTH($C$3,-1)+1,'Opps Created'!$G:$G,"<="&EOMONTH($C$3,0)) -> 2400000 | N8: ACV $ | O8: =SUMIFS('Stage History'!$L:$L,'Stage History'!$O:$O,$B$1,'Stage History'!$S:$S,1,'Stage History'!$P:$P,">="&EOMONTH($C$3,-1)+1, 'Stage History'!$P:$P,"<"&EOMONTH($C$3,0)+1 ) -> 119448
B9: Running Total | F9: Running Total | J9: Running Total | N9: Running Total | R9: Running Total
B10: MQL | C10: =SUMIFS('Digital Leads Raw'!$B1:$B933,'Digital Leads Raw'!$E1:$E933,">="&EDATE(EOMONTH($C$3,-1)+1,-($N$2-1)),'Digital Leads Raw'!$E1:$E933,"<="&EOMONTH($C$3,0)) -> 59 | F10: Meetings | G10: =COUNTIFS('Cold outreach data'!$K$2:$K$251,"Digital",'Cold outreach data'!$G$2:$G$251,"Yes",'Cold outreach data'!$C$2:$C$251,">="&EDATE(DATE(YEAR($C$3),MONTH($C$3),1),-($N$2-1)),'Cold outreach data'!$C$2:$C$251,"<="&EOMONTH($C$3,0)) -> 23 | J10: Created | K10: =COUNTIFS('Opps Created'!$O:$O,$B$1,'Opps Created'!$G:$G,">="&EDATE(EOMONTH($C$3,-1)+1,-($N$2-1)),'Opps Created'!$G:$G,"<="&EOMONTH($C$3,0)) -> 20 | N10: Total Count | O10: =COUNTIFS( 'Opps Created'!$O:$O,$B$1, 'Opps Created'!$Q:$Q,1 ) -> 1 | R10: Won | S10: =SUMIFS('Stage History'!$T:$T,'Stage History'!$O:$O,"Digital",'Stage History'!$P:$P,">="&EOMONTH($C$3,-$N$2)+1, 'Stage History'!$P:$P,"<"&EOMONTH($C$3,0)+1 ) -> 8
B11: MQA | C11: =SUMIFS('Digital Leads Raw'!$C1:$C933,'Digital Leads Raw'!$E1:$E933,">="&EDATE(EOMONTH($C$3,-1)+1,-($N$2-1)),'Digital Leads Raw'!$E1:$E933,"<="&EOMONTH($C$3,0)) -> 52 | F11: MQL to Meeting | G11: =IFERROR(G10/C10,0) -> 0.38983051 | J11: Total Amount | K11: =SUMIFS('Opps Created'!$E:$E,'Opps Created'!$O:$O,$B$1,'Opps Created'!$G:$G,">="&EDATE(EOMONTH($C$3,-1)+1,-($N$2-1)),'Opps Created'!$G:$G,"<="&EOMONTH($C$3,0)) -> 10457055 | N11: Total Amount | O11: =SUMIFS( 'Opps Created'!$E:$E, 'Opps Created'!$O:$O,$B$1, 'Opps Created'!$Q:$Q,1, 'Opps Created'!$R:$R,0 ) -> 596510 | R11: ACV $ | S11: =SUMIFS('Stage History'!$L:$L,'Stage History'!$O:$O,"Digital",'Stage History'!$T:$T,1,'Stage History'!$P:$P,">="&EOMONTH($C$3,-$N$2)+1, 'Stage History'!$P:$P,"<"&EOMONTH($C$3,0)+1 ) -> 963185
J12: ACV $ | K12: =SUMIFS('Opps Created'!$M:$M,'Opps Created'!$O:$O,$B$1,'Opps Created'!$G:$G,">="&EDATE(EOMONTH($C$3,-1)+1,-($N$2-1)),'Opps Created'!$G:$G,"<="&EOMONTH($C$3,0)) -> 8126285 | N12: ACV $ | O12: =SUMIFS( 'Opps Created'!$M:$M, 'Opps Created'!$O:$O,$B$1, 'Opps Created'!$Q:$Q,1, 'Opps Created'!$R:$R,0 ) -> 374010 | R12: % in Closed | S12: =S10/K10 -> 0.4
B14: =TEXT(C3,"mmmm-yy")&" Spend" -> July-26 Spend | F14: =SUMIFS( 'Digital Spend Data'!$C$26:$C$212, 'Digital Spend Data'!$B$26:$B$212,">="&EOMONTH($C$3,-1)+1, 'Digital Spend Data'!$B$26:$B$212,"<="&EOMONTH($C$3,0) ) -> 34395.59 | I14: $1 Spend drives | O14: =IFERROR(K8/F14,"") -> 69.776387 | P14: In new ACV Pipeline
B15: Running Spend | F15: =SUMIFS('Digital Spend Data'!$C$26:$C$212,'Digital Spend Data'!$B$26:$B$212,">="&EDATE(DATE(YEAR($C$3),MONTH($C$3),1),-($N$2-1)),'Digital Spend Data'!$B$26:$B$212,"<="&EOMONTH($C$3,0)) -> 470640.59 | I15: $1 Spend drives | O15: =K12/F15 -> 17.266435 | P15: In new ACV Pipeline
O16: =ROUND(O12/F15,1) -> 0.8 | P16: In Late Stage ACV Pipeline
N17: $1 Spend drives | O17: =(S11+(O11*0.55))/F15 -> 2.7436339 | P17: In new ACV
B18: Includes all spend, activities and results from Digital ONLY
B20: MQLs: | F20: Meetings: | J20: Created: | N20: Late Stage: | R20: Closed Won:
B21: Hubspot | F21: Instructure | J21: Alorica - Front Office tranche 2 | N21: Blue Cross Blue Shield of NC - 553 BPO | R21: TIAA-CREF - NCC - Pilot
B22: Instructure | F22: InDrive | J22: Alorica - Front Office tranche 3
B23: Principal Financial Group
B24: Indrive
B25: Verity Credit Union
B26: Verizon

Sheet Events
B1: Events
B2: Pipeline Council - BIG PICTURE | K2: Running Cohort | N2: =TOTAL!N2 -> 18 | O2: Months
B3: Month | C3: =TOTAL!C3 -> 46234
B4: MQL / MQA | F4: MEETINGS | J4: OPPORTUNITIES | N4: LATE STAGE | R4: CLOSED WON
B5: Last Month | F5: Last Month | J5: Last Month | N5: Last Month | R5: Last Month
B6: MQL | C6: =SUMIFS('Event Spend Raw'!$D$2:$D$995,'Event Spend Raw'!$G$2:$G$995,">="&DATE(YEAR($C$3),MONTH($C$3),1),'Event Spend Raw'!$G$2:$G$995,"<="&EOMONTH($C$3,0)) -> 0 | F6: Meetings | G6: =COUNTIFS('Cold outreach data'!$K$2:$K$251,"Event",'Cold outreach data'!$G$2:$G$251,"Yes",'Cold outreach data'!$C$2:$C$251,">="&DATE(YEAR($C$3),MONTH($C$3),1),'Cold outreach data'!$C$2:$C$251,"<="&EOMONTH($C$3,0)) -> 0 | J6: Created | K6: =COUNTIFS('Opps Created'!$O:$O,$B$1,'Opps Created'!$G:$G,">="&EOMONTH($C$3,-1)+1,'Opps Created'!$G:$G,"<="&EOMONTH($C$3,0)) -> 2 | N6: Moved | O6: =SUMIFS( 'Stage History'!$S:$S, 'Stage History'!$O:$O,$B$1, 'Stage History'!$P:$P,">="&EOMONTH($C$3,-1)+1, 'Stage History'!$P:$P,"<"&EOMONTH($C$3,0)+1 ) -> 1 | R6: Won | S6: =SUMIFS('Stage History'!$T:$T,'Stage History'!$O:$O,"Events",'Stage History'!$P:$P,">="&EOMONTH($C$3,-1)+1,'Stage History'!$P:$P,"<"&EOMONTH($C$3,0)+1) -> 0
B7: MQA | C7: =SUMIFS('Event Spend Raw'!$E$2:$E$995,'Event Spend Raw'!$G$2:$G$995,">="&DATE(YEAR($C$3),MONTH($C$3),1),'Event Spend Raw'!$G$2:$G$995,"<="&EOMONTH($C$3,0)) -> 0 | F7: MQL to Meeting | G7: =IFERROR(G6/C6,0) -> 0 | J7: Total Amount | K7: =SUMIFS('Opps Created'!$E:$E,'Opps Created'!$O:$O,$B$1,'Opps Created'!$G:$G,">="&EOMONTH($C$3,-1)+1,'Opps Created'!$G:$G,"<="&EOMONTH($C$3,0)) -> 2234880 | N7: Total Amount | O7: =SUMIFS('Stage History'!$K:$K,'Stage History'!$O:$O,$B$1,'Stage History'!$S:$S,1,'Stage History'!$P:$P,">="&EOMONTH($C$3,-1)+1, 'Stage History'!$P:$P,"<"&EOMONTH($C$3,0)+1 ) -> 0 | R7: ACV $ | S7: =SUMIFS('Stage History'!$L:$L,'Stage History'!$O:$O,"Events",'Stage History'!$T:$T,1,'Stage History'!$P:$P,">="&EOMONTH($C$3,-1)+1,'Stage History'!$P:$P,"<"&EOMONTH($C$3,0)+1) -> 0
J8: ACV $ | K8: =SUMIFS('Opps Created'!$M:$M,'Opps Created'!$O:$O,$B$1,'Opps Created'!$G:$G,">="&EOMONTH($C$3,-1)+1,'Opps Created'!$G:$G,"<="&EOMONTH($C$3,0)) -> 2234880 | N8: ACV $ | O8: =SUMIFS('Stage History'!$L:$L,'Stage History'!$O:$O,$B$1,'Stage History'!$S:$S,1,'Stage History'!$P:$P,">="&EOMONTH($C$3,-1)+1, 'Stage History'!$P:$P,"<"&EOMONTH($C$3,0)+1 ) -> 0
B9: Running Total | F9: Running Total | J9: Running Total | N9: Running Total | R9: Running Total
B10: MQL | C10: =SUMIFS('Event Spend Raw'!$D$2:$D$995,'Event Spend Raw'!$G$2:$G$995,">="&EDATE(DATE(YEAR($C$3),MONTH($C$3),1),-($N$2-1)),'Event Spend Raw'!$G$2:$G$995,"<="&EOMONTH($C$3,0)) -> 471 | F10: Meetings | G10: =COUNTIFS('Cold outreach data'!$K$2:$K$251,"Event",'Cold outreach data'!$G$2:$G$251,"Yes",'Cold outreach data'!$C$2:$C$251,">="&EDATE(DATE(YEAR($C$3),MONTH($C$3),1),-($N$2-1)),'Cold outreach data'!$C$2:$C$251,"<="&EOMONTH($C$3,0)) -> 34 | J10: Created | K10: =COUNTIFS('Opps Created'!$O:$O,$B$1,'Opps Created'!$G:$G,">="&EDATE(EOMONTH($C$3,-1)+1,-($N$2-1)),'Opps Created'!$G:$G,"<="&EOMONTH($C$3,0)) -> 30 | N10: Total Opps | O10: =COUNTIFS( 'Opps Created'!$O:$O,$B$1, 'Opps Created'!$Q:$Q,1 ) -> 4 | R10: Won | S10: =SUMIFS('Stage History'!$T:$T,'Stage History'!$O:$O,"Events",'Stage History'!$P:$P,">="&EOMONTH($C$3,-$N$2)+1, 'Stage History'!$P:$P,"<"&EOMONTH($C$3,0)+1 ) -> 0
B11: MQA | C11: =SUMIFS('Event Spend Raw'!$E$2:$E$995,'Event Spend Raw'!$G$2:$G$995,">="&EDATE(DATE(YEAR($C$3),MONTH($C$3),1),-($N$2-1)),'Event Spend Raw'!$G$2:$G$995,"<="&EOMONTH($C$3,0)) -> 331 | F11: MQL to Meeting | G11: =IFERROR(G10/C10,0) -> 0.072186837 | J11: Total Amount | K11: =SUMIFS('Opps Created'!$E:$E,'Opps Created'!$O:$O,$B$1,'Opps Created'!$G:$G,">="&EDATE(EOMONTH($C$3,-1)+1,-($N$2-1)),'Opps Created'!$G:$G,"<="&EOMONTH($C$3,0)) -> 9920447.6 | N11: Total Amount | O11: =SUMIFS( 'Opps Created'!$E:$E, 'Opps Created'!$O:$O,$B$1, 'Opps Created'!$Q:$Q,1, 'Opps Created'!$R:$R,0 ) -> 1118283.8 | R11: ACV $ | S11: =SUMIFS('Stage History'!$L:$L,'Stage History'!$O:$O,"Events",'Stage History'!$T:$T,1,'Stage History'!$P:$P,">="&EOMONTH($C$3,-$N$2)+1, 'Stage History'!$P:$P,"<"&EOMONTH($C$3,0)+1 ) -> 0
J12: ACV $ | K12: =SUMIFS('Opps Created'!$M:$M,'Opps Created'!$O:$O,$B$1,'Opps Created'!$G:$G,">="&EDATE(EOMONTH($C$3,-1)+1,-($N$2-1)),'Opps Created'!$G:$G,"<="&EOMONTH($C$3,0)) -> 7134407.6 | N12: ACV $ | O12: =SUMIFS( 'Opps Created'!$M:$M, 'Opps Created'!$O:$O,$B$1, 'Opps Created'!$Q:$Q,1, 'Opps Created'!$R:$R,0 ) -> 720622.8 | R12: % in Closed | S12: =S10/K10 -> 0
B14: =TEXT(C3,"mmmm-yy")&" Spend" -> July-26 Spend | F14: =SUMIFS('Event Spend Raw'!$C:$C,'Event Spend Raw'!$G:$G,">="&EOMONTH($C$3,-1)+1,'Event Spend Raw'!$G:$G,"<"&EOMONTH($C$3,0)+1) -> 5000 | I14: $1 Spend drives | O14: =IFERROR(K8/F14,"") -> 446.976 | P14: In new ACV Pipeline
B15: Running Spend | F15: =SUMIFS( 'Event Spend Raw'!$C:$C, 'Event Spend Raw'!$G:$G,">="&EDATE(EOMONTH($C$3,-1)+1,-($N$2-1)), 'Event Spend Raw'!$G:$G,"<"&EOMONTH($C$3,0)+1 ) -> 829384 | I15: $1 Spend drives | O15: =K12/F15 -> 8.602056 | P15: In new ACV Pipeline
O16: =ROUND(O12/F15,1) -> 0.9 | P16: In Late Stage ACV Pipeline
B17: Includes all spend, activities and results from Events ONLY
O18: =(S11+(O11*0.55))/F15 -> 0.74158181

Sheet Cold Outreach
B1: Cold
B2: Pipeline Council - BIG PICTURE | K2: Running Cohort | N2: =TOTAL!N2 -> 18 | O2: Months
B3: Month | C3: =TOTAL!C3 -> 46234
B4: MQL / MQA | F4: MEETINGS | J4: OPPORTUNITIES | N4: LATE STAGE | R4: CLOSED WON
B5: Last Month | F5: Last Month | J5: Last Month | N5: Last Month | R5: Last Month
B6: MQL | C6: =COUNTIFS('Cold outreach data'!$K$2:$K$251,"Cold",'Cold outreach data'!$C$2:$C$251,">="&DATE(YEAR($C$3),MONTH($C$3),1),'Cold outreach data'!$C$2:$C$251,"<="&EOMONTH($C$3,0)) -> 6 | F6: Meetings | G6: =COUNTIFS('Cold outreach data'!$K$2:$K$251,"Cold",'Cold outreach data'!$G$2:$G$251,"Yes",'Cold outreach data'!$C$2:$C$251,">="&DATE(YEAR($C$3),MONTH($C$3),1),'Cold outreach data'!$C$2:$C$251,"<="&EOMONTH($C$3,0)) -> 6 | J6: Created | K6: =COUNTIFS('Opps Created'!$O:$O,$B$1,'Opps Created'!$G:$G,">="&EOMONTH($C$3,-1)+1,'Opps Created'!$G:$G,"<="&EOMONTH($C$3,0)) -> 1 | N6: Moved | O6: =SUMIFS( 'Stage History'!$S:$S, 'Stage History'!$O:$O,$B$1, 'Stage History'!$P:$P,">="&EOMONTH($C$3,-1)+1, 'Stage History'!$P:$P,"<"&EOMONTH($C$3,0)+1 ) -> 1 | R6: Won | S6: =SUMIFS('Stage History'!$T:$T,'Stage History'!$O:$O,"Cold",'Stage History'!$P:$P,">="&EOMONTH($C$3,-1)+1,'Stage History'!$P:$P,"<"&EOMONTH($C$3,0)+1) -> 0
B7: MQA | C7: =SUMIFS('Cold outreach data'!$L$2:$L$251,'Cold outreach data'!$K$2:$K$251,"Cold",'Cold outreach data'!$C$2:$C$251,">="&DATE(YEAR($C$3),MONTH($C$3),1),'Cold outreach data'!$C$2:$C$251,"<="&EOMONTH($C$3,0)) -> 6 | F7: MQL to Meeting | G7: =IFERROR(G6/C6,0) -> 1 | J7: Total Amount | K7: =SUMIFS('Opps Created'!$E:$E,'Opps Created'!$O:$O,$B$1,'Opps Created'!$G:$G,">="&EOMONTH($C$3,-1)+1,'Opps Created'!$G:$G,"<="&EOMONTH($C$3,0)) -> 240800 | N7: Total Amount | O7: =SUMIFS('Stage History'!$K:$K,'Stage History'!$O:$O,$B$1,'Stage History'!$S:$S,1,'Stage History'!$P:$P,">="&EOMONTH($C$3,-1)+1, 'Stage History'!$P:$P,"<"&EOMONTH($C$3,0)+1 ) -> 757200 | R7: ACV $ | S7: =SUMIFS('Stage History'!$L:$L,'Stage History'!$O:$O,"Cold",'Stage History'!$T:$T,1,'Stage History'!$P:$P,">="&EOMONTH($C$3,-1)+1,'Stage History'!$P:$P,"<"&EOMONTH($C$3,0)+1) -> 0
J8: ACV $ | K8: =SUMIFS('Opps Created'!$M:$M,'Opps Created'!$O:$O,$B$1,'Opps Created'!$G:$G,">="&EOMONTH($C$3,-1)+1,'Opps Created'!$G:$G,"<="&EOMONTH($C$3,0)) -> 100800 | N8: ACV $ | O8: =SUMIFS('Stage History'!$L:$L,'Stage History'!$O:$O,$B$1,'Stage History'!$S:$S,1,'Stage History'!$P:$P,">="&EOMONTH($C$3,-1)+1, 'Stage History'!$P:$P,"<"&EOMONTH($C$3,0)+1 ) -> 607200 | R8: % in Closed
B9: Running Total | F9: Running Total | J9: Running Total | N9: Running Total | R9: Running Total
B10: MQL | C10: =COUNTIFS('Cold outreach data'!$K$2:$K$251,"Cold",'Cold outreach data'!$C$2:$C$251,">="&EDATE(DATE(YEAR($C$3),MONTH($C$3),1),-($N$2-1)),'Cold outreach data'!$C$2:$C$251,"<="&EOMONTH($C$3,0)) -> 178 | F10: Meetings | G10: =COUNTIFS('Cold outreach data'!$K$2:$K$251,"Cold",'Cold outreach data'!$G$2:$G$251,"Yes",'Cold outreach data'!$C$2:$C$251,">="&EDATE(DATE(YEAR($C$3),MONTH($C$3),1),-($N$2-1)),'Cold outreach data'!$C$2:$C$251,"<="&EOMONTH($C$3,0)) -> 141 | J10: Created | K10: =COUNTIFS('Opps Created'!$O:$O,$B$1,'Opps Created'!$G:$G,">="&EDATE(EOMONTH($C$3,-1)+1,-($N$2-1)),'Opps Created'!$G:$G,"<="&EOMONTH($C$3,0)) -> 27 | N10: Moved | O10: =COUNTIFS( 'Opps Created'!$O:$O,$B$1, 'Opps Created'!$Q:$Q,1 ) -> 2 | R10: Won | S10: =SUMIFS('Stage History'!$T:$T,'Stage History'!$O:$O,"Cold",'Stage History'!$P:$P,">="&EDATE(EOMONTH($C$3,-1)+1,-($N$2-1)),'Stage History'!$P:$P,"<="&EOMONTH($C$3,0)) -> 4
B11: MQA | C11: =SUMIFS('Cold outreach data'!$M$2:$M$251,'Cold outreach data'!$K$2:$K$251,"Cold",'Cold outreach data'!$C$2:$C$251,">="&EDATE(DATE(YEAR($C$3),MONTH($C$3),1),-($N$2-1)),'Cold outreach data'!$C$2:$C$251,"<="&EOMONTH($C$3,0)) -> 138 | F11: MQL to Meeting | G11: =IFERROR(G10/C10,0) -> 0.79213483 | J11: Total Amount | K11: =SUMIFS('Opps Created'!$E:$E,'Opps Created'!$O:$O,$B$1,'Opps Created'!$G:$G,">="&EDATE(EOMONTH($C$3,-1)+1,-($N$2-1)),'Opps Created'!$G:$G,"<="&EOMONTH($C$3,0)) -> 10098778 | N11: Total Amount | O11: =SUMIFS( 'Opps Created'!$E:$E, 'Opps Created'!$O:$O,$B$1, 'Opps Created'!$Q:$Q,1, 'Opps Created'!$R:$R,0 ) -> 1267200 | R11: ACV $ | S11: =SUMIFS('Stage History'!$L:$L,'Stage History'!$O:$O,"Cold",'Stage History'!$T:$T,1,'Stage History'!$P:$P,">="&EDATE(EOMONTH($C$3,-1)+1,-($N$2-1)),'Stage History'!$P:$P,"<="&EOMONTH($C$3,0)) -> 219385.5
J12: ACV $ | K12: =SUMIFS('Opps Created'!$M:$M,'Opps Created'!$O:$O,$B$1,'Opps Created'!$G:$G,">="&EDATE(EOMONTH($C$3,-1)+1,-($N$2-1)),'Opps Created'!$G:$G,"<="&EOMONTH($C$3,0)) -> 6961560 | N12: ACV $ | O12: =SUMIFS( 'Opps Created'!$M:$M, 'Opps Created'!$O:$O,$B$1, 'Opps Created'!$Q:$Q,1, 'Opps Created'!$R:$R,0 ) -> 1057200 | R12: % in Closed | S12: =S10/K10 -> 0.14814815
B14: =TEXT(C3,"mmmm-yy")&" Spend" -> July-26 Spend | F14: =SUMIFS( 'Cold Outreach Spend Raw'!$B:$B, 'Cold Outreach Spend Raw'!$A:$A,">="&EOMONTH($C$3,-1)+1, 'Cold Outreach Spend Raw'!$A:$A,"<="&EOMONTH($C$3,0) ) -> 32475 | I14: $1 Spend drives | O14: =IFERROR(K8/F14,"") -> 3.1039261 | P14: In new ACV Pipeline
B15: Running Spend | F15: =SUMIFS('Cold Outreach Spend Raw'!$B:$B,'Cold Outreach Spend Raw'!$A:$A,">="&EDATE(EOMONTH($C$3,-1)+1,-($N$2-1)),'Cold Outreach Spend Raw'!$A:$A,"<="&EOMONTH($C$3,0)) -> 479675 | I15: $1 Spend drives | O15: =K12/F15 -> 14.513077 | P15: In new ACV Pipeline
O16: =ROUND(O12/F15,1) -> 2.2 | P16: In Late Stage ACV Pipeline
B17: Includes all spend, activities and results from Cold Outreach ONLY (MemoryBlue / Nathan)
O18: =(S11+(O11*0.55))/F15 -> 1.9103466

Sheet Alliances
B1: Alliances
B2: Pipeline Council - BIG PICTURE | K2: Running Cohort | N2: =TOTAL!N2 -> 18 | O2: Months
B3: Month | C3: =TOTAL!C3 -> 46234
B4: MQL / MQA | F4: MEETINGS | J4: OPPORTUNITIES | N4: LATE STAGE | R4: CLOSED WON
B5: Last Month | F5: Last Month | J5: Last Month | N5: Last Month | R5: Last Month
B6: MQL | C6: =COUNTIFS('Alliances Data Raw'!$V$3:$V$100029,">="&DATE(YEAR($C$3),MONTH($C$3),1),'Alliances Data Raw'!$V$3:$V$100029,"<="&EOMONTH($C$3,0),'Alliances Data Raw'!$D$3:$D$100029,"<>Disqualified",'Alliances Data Raw'!$D$3:$D$100029,"<>Register Lead") -> 5 | F6: Meetings | G6: =COUNTIFS( 'Alliances Data Raw'!$W$3:$W$1029,">="&DATE(YEAR($C$3),MONTH($C$3),1), 'Alliances Data Raw'!$W$3:$W$1029,"<="&EOMONTH($C$3,0) ) -> 5 | J6: Created | K6: =COUNTIFS('Opps Created'!$O:$O,$B$1,'Opps Created'!$G:$G,">="&EOMONTH($C$3,-1)+1,'Opps Created'!$G:$G,"<="&EOMONTH($C$3,0)) -> 5 | N6: Moved | O6: =SUMIFS( 'Stage History'!$S:$S, 'Stage History'!$O:$O,$B$1, 'Stage History'!$P:$P,">="&EOMONTH($C$3,-1)+1, 'Stage History'!$P:$P,"<"&EOMONTH($C$3,0)+1 ) -> 4 | R6: Won | S6: =SUMIFS('Stage History'!$T:$T,'Stage History'!$O:$O,"Alliances",'Stage History'!$P:$P,">="&EOMONTH($C$3,-1)+1, 'Stage History'!$P:$P,"<"&EOMONTH($C$3,0)+1 ) -> 0
B7: MQA | C7: {=IFERROR( COUNTA( _xlfn.UNIQUE( _xlfn._xlws.FILTER( 'Alliances Data Raw'!$C$3:$C$1029, ('Alliances Data Raw'!$C$3:$C$1029<>"")* ('Alliances Data Raw'!$V$3:$V$1029>=DATE(YEAR($C$3),MONTH($C$3),1))* ('Alliances Data Raw'!$V$3:$V$1029<=EOMONTH($C$3,0))* ('Alliances Data Raw'!$D$3:$D$1029<>"Disqualified")* ('Alliances Data Raw'!$D$3:$D$1029<>"Register Lead") ) ) ), 0)} -> 5 | F7: MQL to Meeting | G7: =IF(C6=0,"",G6/C6) -> 1 | J7: Total Amount | K7: =SUMIFS('Opps Created'!$E:$E,'Opps Created'!$O:$O,$B$1,'Opps Created'!$G:$G,">="&EOMONTH($C$3,-1)+1,'Opps Created'!$G:$G,"<="&EOMONTH($C$3,0)) -> 1361400 | N7: Total Amount | O7: =SUMIFS('Stage History'!$K:$K,'Stage History'!$O:$O,$B$1,'Stage History'!$S:$S,1,'Stage History'!$P:$P,">="&EOMONTH($C$3,-1)+1, 'Stage History'!$P:$P,"<"&EOMONTH($C$3,0)+1 ) -> 342208 | R7: ACV $ | S7: =SUMIFS('Stage History'!$L:$L,'Stage History'!$O:$O,"Alliances",'Stage History'!$T:$T,1,'Stage History'!$P:$P,">="&EOMONTH($C$3,-1)+1,'Stage History'!$P:$P,"<"&EOMONTH($C$3,0)+1) -> 0
J8: ACV $ | K8: =SUMIFS('Opps Created'!$M:$M,'Opps Created'!$O:$O,$B$1,'Opps Created'!$G:$G,">="&EOMONTH($C$3,-1)+1,'Opps Created'!$G:$G,"<="&EOMONTH($C$3,0)) -> 732400 | N8: ACV $ | O8: =SUMIFS('Stage History'!$L:$L,'Stage History'!$O:$O,$B$1,'Stage History'!$S:$S,1,'Stage History'!$P:$P,">="&EOMONTH($C$3,-1)+1, 'Stage History'!$P:$P,"<"&EOMONTH($C$3,0)+1 ) -> 272208
B9: Running Total | F9: Running Total | J9: Running Total | N9: Running Total | R9: Running Total
B10: MQL | C10: =COUNTIFS('Alliances Data Raw'!$V$3:$V$100029,">="&EDATE(DATE(YEAR($C$3),MONTH($C$3),1),-($N$2-1)),'Alliances Data Raw'!$V$3:$V$100029,"<="&EOMONTH($C$3,0),'Alliances Data Raw'!$D$3:$D$100029,"<>Disqualified",'Alliances Data Raw'!$D$3:$D$100029,"<>Register Lead") -> 114 | F10: Meetings | G10: =COUNTIFS( 'Alliances Data Raw'!$W$3:$W$1029,">="&EDATE(DATE(YEAR($C$3),MONTH($C$3),1),-($N$2-1)), 'Alliances Data Raw'!$W$3:$W$1029,"<="&EOMONTH($C$3,0) ) -> 71 | J10: Created | K10: =COUNTIFS('Opps Created'!$O:$O,$B$1,'Opps Created'!$G:$G,">="&EDATE(EOMONTH($C$3,-1)+1,-($N$2-1)),'Opps Created'!$G:$G,"<="&EOMONTH($C$3,0)) -> 56 | N10: Moved | O10: =COUNTIFS( 'Opps Created'!$O:$O,$B$1, 'Opps Created'!$Q:$Q,1 ) -> 5 | R10: Won | S10: =SUMIFS('Stage History'!$T:$T,'Stage History'!$O:$O,"Alliances",'Stage History'!$P:$P,">="&EOMONTH($C$3,-$N$2)+1, 'Stage History'!$P:$P,"<"&EOMONTH($C$3,0)+1 ) -> 19
B11: MQA | C11: {=IFERROR( COUNTA( _xlfn.UNIQUE( _xlfn._xlws.FILTER( 'Alliances Data Raw'!$C$3:$C$100029, ('Alliances Data Raw'!$C$3:$C$100029<>"")* ('Alliances Data Raw'!$V$3:$V$100029>=EDATE(DATE(YEAR($C$3),MONTH($C$3),1),-($N$2-1)))* ('Alliances Data Raw'!$V$3:$V$100029<=EOMONTH($C$3,0))* ('Alliances Data Raw'!$D$3:$D$100029<>"Disqualified")* ('Alliances Data Raw'!$D$3:$D$100029<>"Register Lead") ) ) ), 0)} -> 107 | F11: MQL to Meeting | G11: =IFERROR(G10/C10,0) -> 0.62280702 | J11: Total Amount | K11: =SUMIFS('Opps Created'!$E:$E,'Opps Created'!$O:$O,$B$1,'Opps Created'!$G:$G,">="&EDATE(EOMONTH($C$3,-1)+1,-($N$2-1)),'Opps Created'!$G:$G,"<="&EOMONTH($C$3,0)) -> 30153720 | N11: Total Amount | O11: =SUMIFS( 'Opps Created'!$E:$E, 'Opps Created'!$O:$O,$B$1, 'Opps Created'!$Q:$Q,1, 'Opps Created'!$R:$R,0 ) -> 907364 | R11: ACV $ | S11: =SUMIFS('Stage History'!$L:$L,'Stage History'!$O:$O,"Alliances",'Stage History'!$T:$T,1,'Stage History'!$P:$P,">="&EOMONTH($C$3,-$N$2)+1, 'Stage History'!$P:$P,"<"&EOMONTH($C$3,0)+1 ) -> 1855153.6
J12: ACV $ | K12: =SUMIFS('Opps Created'!$M:$M,'Opps Created'!$O:$O,$B$1,'Opps Created'!$G:$G,">="&EDATE(EOMONTH($C$3,-1)+1,-($N$2-1)),'Opps Created'!$G:$G,"<="&EOMONTH($C$3,0)) -> 18115520 | N12: ACV $ | O12: =SUMIFS( 'Opps Created'!$M:$M, 'Opps Created'!$O:$O,$B$1, 'Opps Created'!$Q:$Q,1, 'Opps Created'!$R:$R,0 ) -> 626364 | R12: % in Closed | S12: =S10/K10 -> 0.33928571
B14: =TEXT(C3,"mmmm-yy")&" Spend" -> July-26 Spend | F14: =SUMIFS( 'Alliances Spend'!$B:$B, 'Alliances Spend'!$C:$C,">="&EOMONTH($C$3,-1)+1, 'Alliances Spend'!$C:$C,"<="&EOMONTH($C$3,0) ) -> 3454.56 | I14: $1 Spend drives | O14: =IFERROR(K8/F14,"") -> 212.00963 | P14: In new ACV Pipeline
B15: Running Spend | F15: =SUMIFS( 'Alliances Spend'!$B:$B, 'Alliances Spend'!$C:$C,">="&EDATE(DATE(YEAR($C$3),MONTH($C$3),1),-($N$2-1)), 'Alliances Spend'!$C:$C,"<="&EOMONTH($C$3,0) ) -> 188072.1 | I15: $1 Spend drives | O15: =K12/F15 -> 96.322209 | P15: In new ACV Pipeline
O16: =ROUND(O12/F15,1) -> 3.3 | P16: In Late Stage ACV Pipeline
B17: Includes all spend, activities and results from Alliances ONLY
O18: {=(J8:L10S11+(O11*0.55))/F15} -> #NAME?
O19: =(S11+(O11*0.55))/F15 -> 12.51756

Sheet Alliances Spend
A1: Partner | B1: Spend | C1: Date | D1: Type
A2: Five9/SKO | B2: 1919.37 | C2: 45658 | D2: Travel
A3: Partner | B3: 0 | C3: 45658 | D3: Travel
A4: Connex | B4: 0 | C4: 45658 | D4: Travel
A5: Avaya | B5: -88.07 | C5: 45658 | D5: Travel
A6: Alvaria | B6: 0 | C6: 45658 | D6: Travel
A7: Call Design | B7: 0 | C7: 45658 | D7: Travel
A8: Genesys | B8: 0 | C8: 45658 | D8: Travel
A9: Five 9 | B9: 8500 | C9: 45688 | D9: 3 Silver Sponsorship passes
A10: Five9/SKO | B10: 5984.7 | C10: 45689 | D10: Travel
A11: Partner | B11: 1142.44 | C11: 45689 | D11: Travel
A12: Connex | B12: 0 | C12: 45689 | D12: Travel
A13: Avaya | B13: 0 | C13: 45689 | D13: Travel
... A59: Genesys | B59: 1464.28 | C59: 45870 | D59: Travel
A60: SagesS3 | C60: 45870 | D60: Retainer
A61: Five9/SKO | B61: 0 | C61: 45901 | D61: Travel
A62: Partner | B62: 3893.37 | C62: 45901 | D62: Travel
A63: Connex | B63: 0 | C63: 45901 | D63: Travel
A64: Avaya | B64: 0 | C64: 45901 | D64: Travel
A65: Alvaria | B65: 0 | C65: 45901 | D65: Travel
A66: Call Design | B66: 0 | C66: 45901 | D66: Travel
A67: Genesys | B67: 2829.34 | C67: 45901 | D67: Travel
A68: SagesS3 | C68: 45901 | D68: Retainer
A69: Five9/SKO | B69: 1120.42 | C69: 45931 | D69: Travel
A70: Partner | B70: 78.84 | C70: 45931 | D70: Travel
A71: Connex | B71: 0 | C71: 45931 | D71: Travel
A72: Avaya | B72: 0 | C72: 45931 | D72: Travel
A73: Alvaria | B73: 0 | C73: 45931 | D73: Travel
A74: Call Design | B74: 0 | C74: 45931 | D74: Travel
A75: Genesys | B75: 6793.37 | C75: 45931 | D75: Travel
A76: SagesS3 | C76: 45931 | D76: Retainer
A77: Call Design | B77: 15000 | C77: 45961 | D77: Gold Sponsorship
A78: Five9/SKO | B78: 6574.65 | C78: 45962 | D78: Travel
A79: Partner | B79: 3174.32 | C79: 45962 | D79: Travel
A80: Connex | B80: 0 | C80: 45962 | D80: Travel
A81: Avaya | B81: 0 | C81: 45962 | D81: Travel
A82: Alvaria | B82: 0 | C82: 45962 | D82: Travel
A83: Call Design | B83: 43.34 | C83: 45962 | D83: Travel
A84: Genesys | B84: 278.02 | C84: 45962 | D84: Travel
A85: SagesS3 | C85: 45962 | D85: Retainer
A86: Alvaria | B86: 10892 | C86: 45991 | D86: Exhibit Buildout for Contact Center Expo in London Co-located with Alvaria
A87: Five9/SKO | B87: 10273.73 | C87: 45992 | D87: Travel
A88: Partner | B88: 0 | C88: 45992 | D88: Travel
A89: Connex | B89: 0 | C89: 45992 | D89: Travel
A90: Avaya | B90: 0 | C90: 45992 | D90: Travel
A91: Alvaria | B91: 0 | C91: 45992 | D91: Travel
A92: Call Design | B92: 0 | C92: 45992 | D92: Travel
A93: Genesys | B93: 269.54 | C93: 45992 | D93: Travel
A94: SagesS3 | C94: 45992 | D94: Retainer
A95: Five 9 | B95: 21250 | C95: 46022 | D95: Gold CX Summit Sponsorship
A96: Five9/SKO | B96: 1418.31 | C96: 46023 | D96: Travel
A97: Partner | B97: 1116.21 | C97: 46023 | D97: Travel
A98: Connex | B98: 764.76 | C98: 46023 | D98: Travel
A99: Avaya | B99: 0 | C99: 46023 | D99: Travel
A100: Alvaria | B100: 0 | C100: 46023 | D100: Travel
A101: Call Design | B101: 0 | C101: 46023 | D101: Travel
A102: Genesys | B102: 0 | C102: 46023 | D102: Travel
A103: SagesS3 | C103: 46023 | D103: Retainer
A104: Five 9 | B104: 10000 | C104: 46053 | D104: Silver SKO Sponsorship
A105: Five9/SKO | B105: 14854.34 | C105: 46054 | D105: Travel
A106: Partner | B106: 1756.39 | C106: 46054 | D106: Travel
A107: Connex | B107: 0 | C107: 46054 | D107: Travel
A108: Avaya | B108: 0 | C108: 46054 | D108: Travel
A109: Alvaria | B109: 0 | C109: 46054 | D109: Travel
A110: Call Design | B110: 0 | C110: 46054 | D110: Travel
A111: Genesys | B111: 0 | C111: 46054 | D111: Travel
A112: SagesS3 | C112: 46054 | D112: Retainer
A113: SagesS3 | C113: 46082 | D113: Retainer
A114: SagesS3 | C114: 46113 | D114: Retainer
A115: Genesys | B115: 1500 | C115: 46113 | D115: Genesys London Travel
A116: Travel | C116: 46113 | D116: Enterprise Connect Partner Program
A117: Five9 | B117: 3729.81 | C117: 46143 | D117: Five9 Partner Powered Reception travel and event spend
A118: Genesys | B118: 2200 | C118: 46143 | D118: Genesys Dallas
A119: Genesys | B119: 46.375 | C119: 46196 | D119: Allan Taxi/Public Transportation/Ride Sharing April Claim Taxi to airport for Genesys event in London
A120: Genesys | B120: 46.375 | C120: 46196 | D120: Allan Taxi/Public Transportation/Ride Sharing April Claim Taxi from airport for Genesys event in London
A121: Genesys | B121: 575.82 | C121: 46204 | D121: Genesys Xperience Travel
A122: Alvaria | B122: 605.52 | C122: 46204 | D122: Alvaria CCW Business Meal
A123: Partner | B123: 2273.22 | C123: 46204 | D123: CCW Partner Conference Travel

Sheet Digital Leads Raw
A1: Company | B1: MQL | C1: MQA | D1: Week End | E1: Date Converted | F1: Notes | G1: Job Title | H1: First Name | I1: Last Name | J1: Form | K1: Assigned To? | L1: Status | M1: Meeting Scheduled? | N1: Email | O1: Source | P1: Source Referrer / comments | Q1: Outcome? | R1: Oppty | S1: Stage | T1: Amount | U1: SFDC Record | V1: Form Comments
A2: Altice | B2: 1 | D2: 45293 | E2: 45293 | H2: Julia | I2: Fagan | J2: Form Submission: Website - Get In Touch Form 2020 - USE | N2: Julfaga@alticeusa.com | O2: Website
A3: EE | B3: 1 | D3: 45302 | E3: 45302 | H3: Lee | I3: Waller | J3: Form: SWPP Webinar 5.2.23 - Watch On-Demand Form US | N3: lee.2.waller@ee.co.uk | O3: Website | P3: Webinar on Demand
A4: Bank of Scotland | B4: 1 | D4: 45323 | E4: 45323 | H4: Antony | I4: McCarthy | J4: Form: TEI Report | N4: antonymccarthy@bankofscotland.co.uk | O4: Website
A5: TD Bank | B5: 1 | D5: 45324 | E5: 45324 | G5: Genesys WFO Product Owner | H5: Bruno | I5: Menses | J5: Form UK Resource Increase Agent Engagement | O5: Website
A6: WorldPay | B6: 1 | D6: 45336 | E6: 45336 | G6: Enterprise Solution Architect | H6: Jim | I6: Ritter | J6: Website Lead - contact us | N6: james.ritter@worldpay.com | O6: Website
A7: Convey Health Solutions | B7: 1 | D7: 45343 | E7: 45343 | G7: Vice President, Product & Service Delivery | H7: Ameerah | I7: Murray | J7: Form: Healthcare Customer Story (lander) - WebEx Modal Confirmation w/ button | N7: amurray1@conveyhs.com | O7: Website | P7: Web Personalization
A8: Nexon Asia Pacific | B8: 1 | D8: 45349 | E8: 45349 | H8: Malcolm | I8: Thompson | J8: Website - Contact Us - USE | O8: Website
A9: TD Bank | B9: 1 | D9: 45350 | E9: 45350 | G9: Intraday Manager | H9: Dawn | I9: Squires | J9: Form Webinar The Human Side of AI | N9: dawn.squires@td.com | O9: Website | P9: Webinar on Demand
A10: Verizon | B10: 1 | D10: 45358 | E10: 45358 | G10: Cslt-WkForce Plng&Anlys | H10: Eric | I10: McCreery | J10: Form: Website - Contact Us - USE | N10: eric.mccreery@verizonwireless.com | O10: Website | Q10: Meeting Scheduled | S10: Current Opp | U10: Meeting scheduled
A11: NZ Airlines | B11: 1 | D11: 45361 | E11: 45361 | H11: Nick | I11: Baldock | J11: Form Handler: ROI Calc USE (handler) | N11: nick.baldock@airnz.co.nz | O11: Website
A12: Wayfair | B12: 1 | D12: 45366 | E12: 45366 | H12: Jason | I12: Landis-Spuur | J12: Form: Website - Forrester TEI Report 2022 | N12: jlandisspuur@wayfair.com | O12: Website
A13: Sutherland Global | B13: 1 | D13: 45380 | E13: 45380 | H13: Allen | I13: Larsen | J13: Form: Website - Get In Touch Form 2020 - USE | N13: allen.larsen@sutherlandglobal.com | O13: Website
A14: 1-800 Got Junk | B14: 1 | D14: 45392 | E14: 45392 | H14: Greg | I14: Brown | J14: Form: Website - Attrition Calculator | N14: greg.brown@1800gotjunk.com | O14: Website
A15: Achmea | B15: 1 | D15: 45406 | E15: 45406 | G15: Sr Business Innovation Manager | H15: Jeroen | I15: Bartelse | J15: Form: Website - Forrester TEI Report 2022 | N15: jeroen.bartelse@achmea.nl | O15: Website | P15: TEI Report, Attrition Calc, Contact Us (Apr 24-25, 2024) | Q15: Christian Foumboua | U15: Associated with Burnout Oppty 5/2 | V15: https://intradiem2023.lightning.force.com/lightning/r/Contact/003V5000008gSwFIAU/view
A16: TTEC | B16: 1 | D16: 45409 | E16: 45409 | H16: Maurilo | I16: Borges | J16: Form Submission: Website Download - WP - How AI May Help with Contact Center Operations - 2023 update (form) | N16: maurilo.borges@ttec.com | O16: Website
A17: Verizon | B17: 1 | D17: 45436 | E17: 45436 | G17: Program Manager/Engagement Executive - Professional Services | H17: Ryan | I17: Ballew | J17: Form: Website - Forrester TEI Report 2022 - new site | N17: ryan.ballew@verizon.com | O17: Website | Q17: Nick assigned to Verizon. confirm if MQL
A18: US Cellular | B18: 1 | D18: 45440 | E18: 45440 | G18: Workforce Forcasting Analyst | H18: Caitlan | I18: Johnston | J18: Form: SWPP Cigna Webinar 4.4.24 - Watch On-Demand Form US | N18: caitlan.johnston@uscellular.com | O18: Website
A19: AIA Austraila | B19: 1 | D19: 45449 | E19: 45449 | F19: Senior Manager Workforce Planning | G19: Senior Manager Workforce Planning | H19: Scott | I19: Cumming | J19: Form: SWPP Cigna Webinar 4.4.24 - Watch On-Demand Form US | N19: scott.cumming@aia.com | O19: Website | P19: https://www.google.com/ Google Google Natural Search https://go.intradiem.com/
A20: Covetrus | B20: 1 | D20: 45468 | E20: 45468 | H20: Anna | I20: Sanders | J20: Form Submission: Website US - Demo Requested | N20: anna.sanders@covetrus.com | O20: Website
A21: TTEC | B21: 1 | D21: 45468 | E21: 45468 | H21: Steve | I21: Miles | J21: Form Submission: Website Download - WP - How AI May Help with Contact Center Operations - 2023 update (form) | N21: steve.miles@ttec.com | O21: Website | P21: https://www.google.com/ Google Google Natural Search *searched for "architecture - intradiem"
A22: MailChimp | B22: 1 | E22: 45493 | G22: Senior Manager Product Support/ BPO Vendor management; https://www.linkedin.com/in/estela-turqui-28104643 | H22: Estela | I22: Turqui | J22: Linkedin Ad: ops-ebook | L22: Re-MQL July'25 | N22: eturqui@rsglab.com | O22: LinkedIn Ad | Q22: Nurture | U22: https://intradiem2023.lightning.force.com/lightning/r/Lead/00QV5000007XSb0MAG/view
A23: Beyond Financial | B23: 1 | E23: 45499 | G23: Senior Manager Strategic Workforce Planning | H23: Ana | I23: Hughey | J23: Form Handler: Intradiem_TEI-Forrester-Report_US | L23: unconfirmed - likely organic. Came from unbounce lander | N23: ahughey@beyondfinance.com | O23: Website | U23: https://intradiem2023.lightning.force.com/lightning/r/Lead/00QV5000008I4LsMAK/view
A24: HomeServe USA | B24: 1 | E24: 45522 | G24: VP Total Rewards & People Operations; https://www.linkedin.com/in/ktobrien; in progress from Vic | H24: Kevin | I24: O'Brien | J24: Linkedin Ad: ops-ebook | K24: Brady | L24: Nurture | N24: kevin.obrien@homeserveusa.com | O24: LinkedIn Ad | Q24: Oppty (created Jan'25) this contact not associated | R24: HomeServe USA | S24: Qualification | T24: 577600 | U24: https://intradiem2023.lightning.force.com/lightning/r/Lead/00QV5000008Rr6rMAC/view
A25: Cardinal Health | B25: 1 | E25: 45526 | G25: Manager; Quality Performance | H25: Connie | I25: Brock | J25: Linkedin Ad: ops-ebook | N25: constance.brock@rollins.com | O25: LinkedIn Ad | Q25: Nurture | U25: https://intradiem2023.lightning.force.com/lightning/r/Lead/00QV5000008oH2fMAE/view
A26: TTEC | B26: 1 | E26: 45536 | G26: Vice President, Delivery Transformation | H26: Michelle | I26: Fox | J26: Organic Search | K26: Form: Website - Demo Form | L26: Organic (duckduckgo.com) | M26: Mike Reagan | N26: michelle.fox@ttec.com | O26: Working
A27: Hyatt Hotel Companies | B27: 1 | E27: 45537 | G27: SVP Contact Centers & Operations | H27: Anderson | I27: Hernandez, MBA | J27: Linkedin Ad: ops-ebook | L27: preexisting contact. not created as lead via LI ad submission due to this? intially sales invited to access online demo (2022) | N27: Anhernandez@algvacations.com | O27: LinkedIn Ad | Q27: Nurture | U27: https://intradiem2023.lightning.force.com/lightning/r/Contact/003V500000682J5IAI/view
A28: Cambia Health Solutions | B28: 1 | E28: 45538 | G28: Director Medicare Operations | H28: Dana | I28: Franke | J28: Linkedin Ad: ops-ebook | N28: dana.franke@regence.com | O28: LinkedIn Ad | Q28: Nurture | U28: https://intradiem2023.lightning.force.com/lightning/r/Lead/00QV5000009KFCEMA4/view
A29: TTEC | B29: 1 | E29: 45541 | G29: Vice President, Delivery Transformation | H29: Michelle | I29: Fox | J29: Form: Website Lead - Demo Form | N29: michelle.fox@ttec.com | O29: Organic Search | P29: duckduckgo.com
A30: Towergate Insurance Brokers | B30: 1 | E30: 45544 | G30: Contact Center Operations Director | H30: Paul | I30: Roberts | J30: urn:li:sponsoredCreative:457243374 | O30: LinkedIn Ad | U30: https://intradiem2023.lightning.force.com/lightning/r/Lead/00QV500000AdM2wMAF/view
A31: Domestic and General | B31: 1 | E31: 45556 | G31: Director of Contact Centre Operations - European Union | H31: Alison | I31: Comins | J31: Linkedin Ad: ops-ebook | K31: Christian Foumboua | N31: alison.jones@domesticandgeneral.com | O31: LinkedIn Ad | U31: https://intradiem2023.lightning.force.com/lightning/r/Lead/00QV5000006N85wMAC/view
A32: Highmark Health | B32: 1 | E32: 45561 | G32: FEP Plan Executive and Commercial Customer Experience Leader | H32: Christina | I32: Palughi | J32: urn:li:sponsoredCreative:457243374 | O32: LinkedIn Ad
A33: Towergate insurance brokers | B33: 1 | E33: 45564 | G33: Contact Center Operations Director | H33: Paul | I33: Roberts | J33: Linkedin Ad: ops-ebook | K33: Christian Foumboua | O33: LinkedIn Ad
A34: G4S | B34: 1 | E34: 45567 | F34: Director of Operations | G34: Director of Operations | H34: Alexander | I34: Barr | J34: urn:li:sponsoredCreative:457243374 | K34: Christian | N34: alexander.barr@uk.g4s.com | O34: LinkedIn Ad | Q34: 2 Oppty's on acct (unqualified)
A35: Qualfon | B35: 1 | E35: 45573 | G35: VP Data Management and Analytics | H35: Galina | I35: Petrenko | J35: Website Lead - Demo Form | K35: Nate | L35: Qualified | M35: 1 | N35: galina.petrenko@qualfon.com | O35: Bing Natural Search | P35: https://www.youtube.com/, https://chatgpt.com/, https://www.bing.com/ | Q35: OPPTY | R35: Qualfon - NL | S35: Discovery | T35: 1140000 | U35: https://intradiem2023.lightning.force.com/lightning/r/Contact/003V500000FaktVIAR/view
A36: Mercy | B36: 1 | E36: 45573 | G36: Director of Operations | H36: Autumn | I36: Frazier | J36: LinkedIn Ad | K36: Nathan Belfield | N36: Autumn.frazier@mercy.net | O36: LinkedIn Ad | Q36: Nurture
A37: Thompson Reuters | B37: 1 | E37: 45577 | G37: Senior Global Workforce Manager | H37: Jonathan | I37: Lim | J37: Form: Webinar 9.5.22 LB - Erlang-O Files Downloaded | K37: N/A | L37: Not assigned (prospect, not TAM) | N37: jonathan.lim@thomsonreuters.com | O37: Website | Q37: Nurture | R37: Queued for wfm nurture | U37: https://intradiem2023.lightning.force.com/lightning/r/Lead/00QV500000B4wALMAZ/view
A38: Gainwell Technologies | B38: 1 | E38: 45582 | G38: Director Workforce Management | H38: Dwight | I38: Simpson | J38: Website Lead - Demo Form | K38: Vic passed to Haresh/Frank | L38: Nurture | N38: dwight.simpson@gainwelltechnologies.com | O38: Google Natural Search | Q38: Nurture | R38: Queued for wfm nurture | U38: https://intradiem2023.lightning.force.com/lightning/r/Lead/00QV500000BI9eRMAT/view | V38: I have vetted this tool with another organization but interested in seeing fit in Gainwell. We leverage IEX for voice agents and Verint OM for non-voice agents. Looking for a demo to show team and possible R.O.I. to include for C Suite.
A39: HHA Hospital Medicine | B39: 1 | C39: 1 | E39: 45601 | G39: Director of Information Technology | H39: Akhil | I39: Danda | J39: Website Lead - Demo Form | K39: Nate | L39: Nurture | M39: 0 | N39: areddy@hhamedicine.com | O39: Google Ad | P39: Promoted to Dir. IT | Q39: Not Responsive | R39: confirm whether to add to ops nurture or circle back w/ nate | U39: https://intradiem2023.lightning.force.com/lightning/r/Lead/00QV500000BWtkbMAD/view | V39: 2024-10-23 09:04:31 (PDT) I'm lookin g to auto9mate Front desk for my hospital clinic
A40: REI | B40: 1 | C40: 1 | E40: 45603 | G40: Assistant Manager of Operations | H40: Walter | I40: Rowland | J40: Contact Us | K40: Nick | L40: Nurture | M40: 0 | N40: wrowlan@rei.com | O40: Website | Q40: no connect? | R40: Queued for ops nurture | U40: https://intradiem2023.lightning.force.com/lightning/r/Lead/00QV500000CBCRyMAP/view
A41: TIAA | B41: 1 | C41: 0 | E41: 45604 | G41: Director Channel Delivery & Innovation | H41: Oscar | I41: Barnes | J41: Website Lead - Demo Form | K41: Nick | L41: Qualified - preexisting oppty | M41: 1 | N41: obarnes@tiaa.org | O41: Google Ad | Q41: preexisting oppty | R41: TIAA-CREF - NCC | S41: Propose | T41: 451980 | U41: https://intradiem2023.lightning.force.com/lightning/r/Contact/003V500000ErlFHIAZ/view
A42: belairdirect | B42: 1 | C42: 1 | E42: 45607 | G42: Director Workforce Management | H42: Gary | I42: Ersan | J42: Website Lead - Demo Form | K42: Nate | L42: SQL | M42: 1 | N42: gary.ersan@belairdirect.com | O42: Google Natural Search | Q42: OPPTY | R42: Belair Direct - NL | S42: Qualification | T42: N/A | U42: https://intradiem2023.lightning.force.com/lightning/r/Contact/003V500000675FHIAY/view
A43: Marshmallow | B43: 1 | C43: 1 | E43: 45625 | G43: Senior Workforce Manager | H43: Chris | I43: Bateson | J43: Website Lead - Demo Form | K43: Christian | L43: DQ | M43: 1 | N43: chris.bateson@marshmallow.co | O43: Google Natural Search | Q43: Size | U43: https://intradiem2023.lightning.force.com/lightning/r/Lead/00QV500000D6vgsMAB/view
A44: BetMGM | B44: 1 | C44: 1 | E44: 45638 | G44: Sr. Manager, Workforce Management | H44: Ryan | I44: Phillabaum | J44: Website Lead - Demo Form | K44: Nick | L44: Qualified | M44: 1 | N44: ryan.phillabaum@betmgm.com | O44: Bing Natural Search | Q44: OPPTY (2) | R44: BetMGM | S44: BetMGM - Entain LOB | T44: =211200+172800 -> 384000 | U44: https://intradiem2023.lightning.force.com/lightning/r/Contact/003V500000I7JtCIAV/view
A45: GE Appliances, a Haier company | B45: 1 | C45: 1 | E45: 45668 | G45: VP Director of Operation | H45: Jenifer | I45: Spurgeon | J45: LinkedIn Ad ebook- 5 charactersistc | K45: Nick | L45: Nurture | M45: 0 | N45: jenifer.spurgeon@geappliances.com | O45: LinkedIn Ad | Q45: no connect? | R45: Queued for ops nurture | U45: https://intradiem2023.lightning.force.com/lightning/r/Contact/003V50000067VW1IAM/view
A46: Disney | B46: 1 | C46: 1 | E46: 45662 | G46: Global Workforce Management Sr. Consultant | H46: Ameer | I46: Salam | J46: Form: Webinar 9.5.22 LB - Erlang-O Files Downloaded | K46: Nate | L46: Nurture | M46: 0 | N46: ameer.salam@workforcemanagement101.com | O46: Website | Q46: no connect | R46: Queued for wfm nurture | U46: https://intradiem2023.my.salesforce.com/00QV500000EE0U1MAL
A47: Cole Electric | B47: 1 | C47: 1 | E47: 45685 | G47: Director, fulfillment and support | H47: Chloe | I47: Batts | J47: Website Lead - Demo Form | K47: Nick | L47: DQ | M47: 1 | N47: chloe.batts@bannerhealth.com | O47: Website | Q47: Size | U47: https://intradiem2023.lightning.force.com/lightning/r/Lead/00QV500000FdUqTMAV/view
A48: TechStyle | B48: 1 | C48: 1 | E48: 45688 | G48: Director, WFM | H48: Damon | I48: Spurlock | J48: Website - Contact Us | K48: Nate | L48: Qualified | M48: 1 | N48: dspurlock@techstyle.com | O48: Google Natural Search | Q48: OPPTY | R48: TechStyle Fashion Group - NL | S48: Discovery | T48: 597400 | U48: https://intradiem2023.lightning.force.com/lightning/r/Lead/00QV5000009xIOtMAM/view
A49: Capital Group | B49: 0 | C49: 0 | E49: 45694 | G49: Senior Solution Engineer | H49: Jason | I49: Neuman | J49: Form Handler Submission: Intradiem_TEI-Forrester-Report_US | K49: Mike | L49: preexisting oppty | M49: 0 | N49: jsnn@capgroup.com | O49: Bing Natural Search | P49: http://pages.intradiem.com/boost-employee-engagement-reduce-costly-attrition/ (unbounce lander) | Q49: preexisting. re-MQL'd on 3/18 - reached out to Nate/Mike asking if associated with open oppty | R49: Capital Group - NL | S49: Procure | T49: 821839.67 | U49: https://intradiem2023.lightning.force.com/lightning/r/Contact/003V500000L3ryBIAR/view | V49: per Mike 3/18: Yes. Actively engaged. This is The Capital Group opp. Jason is part of CapGroup’s IT/Architecture team. We’re also heavily engaged with the Business & Procurement groups. In flight. Thanks for sharing!
A50: Banner Health | B50: 1 | C50: 1 | E50: 45698 | G50: Director, fulfillment and support | H50: Chloe | I50: Batt | J50: Website Lead - Demo Form | K50: Nick | L50: DQ | M50: 1 | N50: chloe.batts@bannerhealth.com | O50: Google Natural Search | Q50: Size
A51: Wellcare (Centene) | B51: 1 | C51: 1 | E51: 45706 | G51: Director, Workforce | H51: Mark | I51: Thomas | J51: Website - downloaded 4.4.24 Webinar on Demand (Cigna/SWPP) | K51: Nate | L51: MQL | M51: 0 | N51: mark.thomas@wellcare.com | O51: Google Natural Search | Q51: Not assoc. with open opptys. scheduled a meeting with intradiem in 2022 (SJ sent info to RD, NB 6/13)
A52: Flagship Credit Union | B52: 1 | C52: 1 | E52: 45702 | G52: Vice President, Loan Servicing | H52: Chuck | I52: Blommaert | J52: Website Lead - Demo Form | K52: Nick | L52: Nurture | M52: 0 | N52: chuck.blommaert@flagshipcredit.com | O52: LinkedIn Ad | Q52: no activity logged on record | R52: Queued for ops nurture | U52: https://intradiem2023.lightning.force.com/lightning/r/Contact/003V500000671jPIAQ/view
A53: Manulife | B53: 1 | C53: 1 | E53: 45721 | G53: Contact Center Director | H53: Jake | I53: Turner | J53: LinkedIn Ad ebook- 5 characteristics | K53: Nate | L53: Nurture | M53: 0 | N53: Jake_turner@manulife.ca | O53: LinkedIn Ad | Q53: Open Opp but contact not associated. SE logged - No connect (2 emails opened) | R53: Manulife Back Office | S53: Manulife Backoffice Expansion | T53: 232400 | U53: https://intradiem2023.lightning.force.com/lightning/r/Contact/003V500000KLqePIAT/view
A54: Royal Automobile Club Victoria (RACV) | B54: 0 | C54: 0 | E54: 45721 | G54: General Manager - Member Service Delivery | H54: Michelle | I54: Scott | J54: Website- downloaded SWPP Webinar Empowering Supervisors 2.25.25 | K54: Larry? (contact owner - no account team assoc. w acct. | L54: Qualified- preexisting opportunity | M54: 0 | N54: michelle_scott@racv.com.au | O54: Google Natural Search | Q54: preexisting oppty - no meeting | R54: RACV-Insurance + Roadside - 60 60 POV | S54: Closed Won | T54: 30000 | U54: https://intradiem2023.lightning.force.com/lightning/r/Contact/003V500000MBSHVIA5/view | V54: correspondence from larry linked
A55: Dominion Energy | B55: 1 | C55: 1 | E55: 45723 | G55: Manager, Contact Center Support Group | H55: Kevin | I55: Monaghan | J55: Form Handler Submission: Request Demo - G2 Lead (handler) | K55: Nate | L55: Qualified | M55: 1 | N55: kevin.monaghan@dominionenergy.com | O55: G2 | Q55: OPPTY | R55: Dominion Energy | S55: Closed Won | T55: 279200 | U55: https://intradiem2023.lightning.force.com/lightning/r/Contact/003V500000680fcIAA/view
A56: Wawanesa Insurance | B56: 1 | C56: 1 | E56: 45723 | G56: Manager of Workforce Management | H56: Shane | I56: Tankoy | J56: Website- downloaded SWPP Webinar Empowering Supervisors 2.25.25 | K56: Nate lead owner but Nick assigned to account | L56: SQL | M56: 1 | N56: stankoy@wawanesa.com | O56: Website | Q56: Oppty | R56: Wawanesa Insurance | S56: Qualification | T56: 437600 | U56: https://intradiem2023.lightning.force.com/lightning/r/Contact/003V50000067dxLIAQ/view | V56: dup record (prospect linked to contact record
A57: Progressive Leasing | B57: 0 | C57: 0 | E57: 45729 | G57: Senior Information Security Analyst | H57: Tanner | I57: Porter | J57: Form: Website - Frost & Sullivan 2024 Report | K57: Steve | L57: preexisting oppty | M57: 0 | N57: tanner.porter@progleasing.com | O57: Google Natural Search | Q57: preexisting (closed won)- Steve confirmed part of convos. SJ converted 6/17 | R57: Renewal - Progressive Leasing - 60 60 POV | S57: Prove | T57: N/A
A58: CAA Club Group | B58: 1 | C58: 0 | E58: 45731 | G58: Director, Operational Efficiency, Reporting & Insight | H58: Chris | I58: Jaaic | J58: Marketing Qualified Lead - CRM Status Change | K58: Keegan | L58: SQL | M58: 1 | N58: cjai@caasco.ca | O58: Google Ad | Q58: Oppty - confirm | R58: Renewal - CAA Club Group (Avaya) - Post Pilot | T58: 73000 | U58: https://intradiem2023.lightning.force.com/lightning/r/Contact/003V50000067lVEIAY/view
A59: Covertrus | B59: 1 | C59: 1 | E59: 45751 | G59: Sr. Director Customer Experience Operations | H59: Silvia | I59: Glowka | J59: Form: Website - Contact Us - new site | K59: Nate | L59: SQL | M59: 1 | N59: silvia.glowka@covetrus.com | O59: Google Natural Search | Q59: OPPTY (was not assoc. SJ converted 6/17) | R59: Covetrus | S59: Qualification | T59: 100000 | U59: https://intradiem2023.lightning.force.com/lightning/r/Lead/00QV500000Hi2QxMAJ/view
A60: Capital One | B60: 1 | C60: 1 | E60: 45759 | G60: Director of Workforce, Reporting, & Analytics and Process Excellence | H60: Charlie | I60: Canela | J60: Form: Website - Webinar 9.5.24 - SWPP Erlang-O Download on Demand | K60: Nate | L60: MQL | N60: charlemagne.canela@capitalone.com | O60: Google Natural Search | Q60: no activity logged on record? SJ marked nurture 6/17 + queue WFM nurtu | R60: Queued for wfm nurture
A61: Hilton | B61: 1 | C61: 1 | E61: 45799 | G61: Director of Operations | H61: Hayden | I61: Bowman | J61: LinkedIn Ad Lead Gen Form ops-ebook-2025 | K61: Nick | L61: MQL | N61: hayden.bowman@hilton.com | O61: LinkedIn Ad | Q61: no connect | U61: https://intradiem2023.lightning.force.com/lightning/r/Lead/00QV500000JgBKNMA3/view
A62: Hummingbird Healthcare | B62: 1 | C62: 1 | E62: 45811 | G62: Performance Programs Leader | H62: Morgan | I62: Minogue | J62: Form: Website Lead - Demo Form | K62: Nick | L62: SQL | M62: 1 | N62: morgan.minogue@hummingbird.healthcare | O62: Bing Natural Search | Q62: Oppty | R62: Hummingbird Healthcare | S62: Qualification | T62: 193200 | U62: https://intradiem2023.lightning.force.com/lightning/r/Lead/00QV500000KASKUMA5/view | V62: 2025-06-03 14:58:53 (PDT) Healthcare BPO interested in this capability
A63: MCI BPO LC | B63: 1 | C63: 1 | E63: 45818 | G63: Sr Director | H63: Jared | I63: Myers | J63: Form: Website Lead - Demo Form | K63: Nick | L63: Nurture | M63: 1 | N63: jared.myers@bpoaas.com | O63: Google Ad | P63: https://www.google.com/ | Q63: Nurture (Not a Fit: Product Gap) | U63: https://intradiem2023.lightning.force.com/lightning/r/Lead/00QV500000KTD82MAH/view | V63: 2025-06-10 11:54:11 (PDT) Looking for a WFM solution that will allow me to project staffing needs for a variety of current clients as well as potential clients. Would like to discuss pricing.
A64: Think Forward | B64: 0 | C64: 0 | E64: 45826 | G64: Executive Assistant (on behalf of Sabrina Gibson) | H64: Sabrina | I64: Garcia | J64: Form: Website Lead - Demo Form | K64: Nate | L64: SAL | M64: 1 | N64: sabrina@thnkforward.com | O64: Google Ad | Q64: SAL(partner lead) | U64: https://intradiem2023.lightning.force.com/lightning/r/Lead/00QV500000KqTiOMAV/view | V64: I’m reaching out on behalf of Gina Gibson, who has contacted you previously. Gina is an agent representing a customer interested in seeing a demonstration of your product.| *Gina submitted inbound partner form fill 6/6/25https://intradiem2023.lightning.force.com/lightning/r/Lead/00QV500000KIkNRMA1/view Could you please arrange a demo at your earliest convenience? Let us know your availability and any details we should prepare in advance.
A65: Blue Cross Blue Shield of North Carolina | B65: 1 | C65: 1 | E65: 45828 | G65: Command Center Manager | H65: Ken | I65: Hessing | J65: Form: Website Lead - Demo Form | K65: Nate | L65: SQL | M65: 1 | N65: ken.hessing@bcbsnc.com | O65: Google Natural Search | P65: https://www.google.com/ | Q65: Oppty | R65: Blue Cross Blue Shield of NC | S65: Discovery | T65: 506800 | U65: https://intradiem2023.lightning.force.com/lightning/r/Contact/003V50000067k9IIAQ/view | V65: 2025-06-20 08:42:06 (PDT) It has been several years since I last saw a demo and I am interested in what you have available and building a business case for using Intradiem for use in our Contact Center/Back Office.
A66: Concentrix | B66: 1 | C66: 0 | E66: 45831 | G66: WFM Manager | H66: Niraj | I66: Sehgal | J66: Form: Website Lead - Demo Form | K66: Nate | L66: MQL | N66: niraj.sehgal@concentrix.com | O66: Website | P66: https://de3e40908ca541d2b66fa733cfd37e0b.pages.ubembed.com/ | Q66: MQL | U66: https://intradiem2023.lightning.force.com/lightning/r/Lead/00QV500000L10I1MAJ/view | V66: per Nate 6/25: Got Mike in contact with Niraj. They are discussing via e-mail. No meeting set. Will let you know if Mike books one.
A67: NHS Business Services Authority | B67: 1 | C67: 1 | E67: 45835 | G67: Service Delivery Manager | H67: Sian | I67: Pedder | J67: Form: Website - Frost & Sullivan 2024 Report | K67: Simon | L67: MQL (pending conf. # agents) | N67: sian.pedder@nhsbsa.nhs.uk | O67: Google Natural Search | P67: https://www.ecosia.org/ | Q67: MQL(?) | U67: https://intradiem2023.lightning.force.com/lightning/r/Lead/00QV500000LH6mUMAT/view
A68: Qualfon | B68: 1 | C68: 1 | E68: 45834 | G68: Vice President, Customer Experience Transformation | H68: Chris | I68: Serafini | J68: Form: Webinar 6.26.25 - AI Won’t Save Your Agents from Burnout - Registration Form | L68: MQL | N68: chris.serafini@qualfon.com | O68: Bing Natural Search | P68: https://www.bing.com/ | Q68: MQL | U68: https://intradiem2023.lightning.force.com/lightning/r/Contact/003V50000067xBgIAI/view
A69: G4S | B69: 0 | C69: 0 | E69: 45841 | G69: Comms & Engagement Manager | H69: Julie | I69: Owens | J69: Form: Webinar 6.26.25 - Actionary SWPP Fixing Attrition Key to AI Success - Watch On-Demand (form) | K69: Simon? | L69: MQL | N69: julie.owens@uk.g4s.com | O69: Google Ad | Q69: MQL | U69: https://intradiem2023.lightning.force.com/lightning/r/Lead/00QV500000KW6BoMAL/view
A70: Datavant | B70: 1 | C70: 1 | E70: 45841 | G70: Workforce Planning Manager | H70: Kyle | I70: Baker | J70: Form: Webinar 6.26.25 - Actionary SWPP Fixing Attrition Key to AI Success - Watch On-Demand (form) | K70: Jean-Ann/Nate | L70: SQL | M70: 1 | N70: kyle.baker@datavant.com | O70: Social Media - Organic | P70: https://www.linkedin.com/ | Q70: SAL | U70: https://intradiem2023.lightning.force.com/lightning/r/Lead/00QV500000JwxXuMAJ/view
A71: TeKnowledge | B71: 0 | C71: 0 | E71: 45841 | G71: WFM Global Client Leader | H71: Aizel | I71: McGarry | J71: (Score Automation) Form: Webinar 6.26.25 - Actionary SWPP Fixing Attrition Key to AI Success - Watch On-Demand (form) | K71: Nate | L71: Partner | N71: aizel.mcgarry@teknowledge.com | O71: Website | Q71: MQL (partner lead) | U71: https://intradiem2023.lightning.force.com/lightning/r/Lead/00QV500000LUIQIMA5/view
A72: Sistemas MER | B72: 0 | C72: 0 | D72: 45846 | E72: 45846 | F72: Partner | G72: unknown | H72: Victor | I72: Delgado | J72: Form: Webinar 6.18.24 - Thrive - Watch On-Demand Form | L72: SQL: Partner | N72: vdelgado@sistemasmer.com | O72: Google Natural Search | Q72: SAL (partner lead) | U72: https://intradiem2023.lightning.force.com/lightning/r/Lead/00QV500000LjhazMAB/view
A73: Crash Champions | B73: 1 | C73: 0 | E73: 45852 | G73: Manager WFM | H73: Arthur | I73: Lance | J73: Demo Form (LP: SEO Blog Calculating Call Center Shrinkage) | L73: DQ - Size / product fit | N73: arthur.springer@crashchampions.com | O73: Google Natural Search | P73: https://www.google.com/ https://urlwatch.com/ | Q73: DQ - Too Small 100 Agents and no WFM | U73: https://intradiem2023.lightning.force.com/lightning/r/Lead/00QV500000LyxCRMAZ/view
A74: T-Mobile | B74: 1 | C74: 1 | D74: 45854 | E74: 45854 | G74: Director, Solutions Engineering | H74: Craig | I74: Ward | J74: Form: Webinar - SWPP Empower Supervisors 02.27.25 - Watch On-Demand Form US | K74: Nolan | L74: MQL | N74: craig.ward19@t-mobile.com | O74: Google Ad | Q74: MQL - Working - Reached out to Nolan. He is working T-Mobile very heavily. | U74: https://intradiem2023.lightning.force.com/lightning/r/Lead/00QV500000M6l9HMAR/view
A75: Independence Pet Group | B75: 0 | C75: 0 | D75: 45862 | E75: 45862 | G75: President | H75: Chad | I75: Bellin | J75: Form: Website - Partner Lead Registration | L75: SQL: Partner | N75: cbellin@independenceamerican.com | O75: Partner | Q75: SAL - meeting booked | U75: https://intradiem2023.lightning.force.com/lightning/r/Lead/00QV500000MRpt0MAD/view
A76: Invesco | B76: 1 | C76: 1 | D76: 45869 | E76: 45869 | G76: Associate Director | H76: Karen | I76: Chin | J76: Form: Website - Contact Us | L76: Qualified | M76: 1 | N76: karen.chin@invesco.com | O76: Google Ad | Q76: SAL | R76: Invesco | S76: Discovery | T76: 458800 | U76: https://intradiem2023.lightning.force.com/lightning/r/Lead/00QV500000MjLTVMA3/view
A77: The Standard Insurance Company | B77: 1 | C77: 1 | D77: 45869 | E77: 45869 | G77: Workforce Planning Manager | H77: Scott | I77: Boyd | J77: Form: Website - Demo - new site | L77: MQL | N77: robert.boyd@standard.com | O77: Bing Natural Search - Blog - https://intradiem.com/resources/blog/how-to-calculate-call-center-shrinkage/ | Q77: MQL | U77: https://intradiem2023.lightning.force.com/lightning/r/Lead/00QV500000Mjnw2MAB/view
A78: C.H. Robinson Worldwide, Inc. | B78: 1 | C78: 1 | E78: 45876 | G78: Senior Capacity Manager | H78: Mike | I78: Reid | J78: LI Ad: 5 Critial Questions to Ask When Updating Your Contact Center Tech Stack (ad converted: https://www.linkedin.com/feed/update/urn:li:sponsoredContentV2:(urn:li:share:7319060524791459842,urn:li:sponsoredCreative:653315034)/?actorCompanyId=20184&viewContext=REVIEWER). | L78: Open - working | N78: mike.reid@chrobinson.com | O78: LinkedIn Ad (VITO campaign) | Q78: Open - Working | U78: https://intradiem2023.lightning.force.com/lightning/r/Lead/00QV500000N0Pu2MAF/view
A79: Teleperformance | B79: 1 | C79: 0 | E79: 45881 | G79: VP Workforce Management | H79: Raj | I79: Gupta | J79: Filled Out Contact Us Form on Website | L79: Qualified | M79: 1 | N79: raj.gupta2@teleperformance.com | O79: Google Natural Search | Q79: Oppty | R79: Teleperformance | S79: Qualification | T79: 50000 | U79: https://intradiem2023.my.salesforce.com/00QV500000N9N3P
A80: (JCPenny) Catalyst Brands | B80: 1 | C80: 1 | E80: 45881 | G80: Manager, Ivr & Technology | H80: John | I80: DiNapoli | J80: Filled Out Contact Us Form on Website | L80: SAL | M80: 1 | N80: jdinapo1@jcp.com | O80: Google Natural Search | Q80: SAL(meeting secured 8/13) | U80: https://intradiem2023.lightning.force.com/lightning/r/Lead/00QV500000NApP0MAL/view | V80: https://pi.pardot.com/prospect/read?id=39782317
A81: Headway | B81: 1 | C81: 1 | E81: 45883 | G81: Manager, CX Systems | H81: Tessa | I81: Loftus | J81: Form: Website - Demo - new site | L81: SAL | M81: 1 | N81: tessa.loftus@findheadway.com | O81: Google Natural Search | Q81: SAL | U81: https://intradiem2023.my.salesforce.com/00QV500000NHCh3
A82: Fresenius Medical Care | B82: 1 | C82: 1 | E82: 45896 | G82: Director, People Analytics | H82: Gunter | I82: Hartmann | J82: Form: Website - Demo - new site | K82: Nate | L82: SAL : Meeting Booked | M82: 1 | N82: gunter.hartmann@fmc-na.com | O82: Google Natural Search | Q82: SAL | U82: https://intradiem2023.lightning.force.com/lightning/r/Lead/00QV5000006N5nYMAS/view
A83: AwesomeCX (BPO for TechStyle) | B83: 1 | C83: 0 | E83: 45903 | G83: Scheduler | H83: Geleez | I83: Usop | J83: Form: ...LB - Erlang-O Files Downloaded | K83: Nate | L83: MQL - Working | N83: geleez.usop@awesomecx.com | O83: Website (no referrer info available) | P83: Email sent and opened 9/3 | Q83: MQL - Working | email sent & opened 9/3 | U83: https://intradiem2023.lightning.force.com/lightning/r/Lead/00QV5000006N7myMAC/view
A84: Global Fidelis (BPO for TechStyle) | B84: 1 | C84: 0 | E84: 45903 | G84: Adherence Analyst | H84: Rodrigo | I84: Coronel | J84: Form: ...LB - Erlang-O Files Downloaded | K84: Nate | L84: MQL - Working | N84: rcoronel@globalfidelis.com | O84: Website (no referrer info available) | Q84: MQL - Working | email sent & opened 9/3 | U84: https://intradiem2023.lightning.force.com/lightning/r/Lead/00QV5000006N7lmMAC/view
A85: BINA | B85: 0 | C85: 0 | E85: 45901 | G85: Head of International Operations | H85: Ekansh | I85: Barthwal | J85: Filled Out Contact Us Form on Website | K85: Nate | L85: DQ - no contact center | N85: ekansh.barthwal@binaconf.com | O85: Website (no referrer info available) | Q85: no response - Nate sent eml 9/2 to determine partner fit (opened 9/8) | U85: https://intradiem2023.lightning.force.com/lightning/_classic/%2F00QV500000NuyAjMAJ
A86: NUSD | B86: 0 | C86: 0 | E86: 45907 | G86: Legal Assistant | H86: Amelia | I86: Hall | J86: Website Lead - demo form | K86: Nate | L86: DQ - bad data | N86: mcmaster@net.bandai.co | O86: Google Ad - Display remarketing | Q86: Working | email bounced 9/11 | U86: https://intradiem2023.lightning.force.com/lightning/r/Lead/00QV500000OADEHMA5/view
A87: DPR Constructions | B87: 0 | C87: 0 | E87: 45908 | G87: Corporate Procurement Manager | H87: Mark | I87: O-Brien | J87: mark.obrien@dpr-grp.com | K87: Nate | L87: DQ - bad data | O87: Website (no referrer info available) | P87: Likely organic - entered via about us page (no referrer info). left comment. Nate reached out on email and LI. | Q87: DQ 9/12: Mark O'Brien confirmed that the "contact us" demo request was not from them and that this is SPAM. Disqualifying the lead. | U87: https://intradiem2023.lightning.force.com/lightning/r/Lead/00QV500000OCFDaMAP/view | V87: Dear Sir/Madam, I am writing to express our interest in your services. After reviewing your company brochure online, we are eager to learn more about specific offerings that may suit our needs. Could you kindly connect me with the appropriate contact person to facilitate further communication? I would like to share our specifications and requirements in detail and request a quote at your earliest convenience. I look forward to your response. Kind regards, Mark O'Brien
A88: Virtual Help Partner | B88: 0 | C88: 0 | E88: 45910 | G88: Executive Assistant | H88: Brenda | I88: Cruz | J88: Contact Us | K88: ? | L88: DQ - Size / product fit | N88: b.cruz@virtualhelppartner.com | O88: Website (no referrer info available) | Q88: Email sent & opened 9/11 (sent to Larry 9/24 for outreach support week nate was out) | U88: https://intradiem2023.lightning.force.com/lightning/r/Lead/00QV500000OKBj5MAH/view
A89: Supply House | B89: 0 | C89: 0 | E89: 45917 | F89: error syncing acct to sfdc | G89: Customer Service Manager | H89: Nicole | I89: Lewis | J89: Customer Service Manager | K89: Nate | L89: Events | N89: nicolelew@supplyhouse.com | O89: Google Natural Search | Q89: no activity or notes | U89: https://intradiem2023.lightning.force.com/lightning/r/Lead/00QV500000Obt7oMAB/view
A90: Rycon Construction | B90: 0 | C90: 0 | E90: 45918 | G90: CEO | H90: John | I90: Sabatos | J90: Contact Us | K90: Nate/Larry | L90: DQ - no contact center | N90: jsabatos@ryconic.com | O90: Website (no referrer info available) | Q90: Disqualified (sent to Larry 9/24 for outreach support) | U90: https://intradiem2023.lightning.force.com/lightning/r/Lead/00QV500000OdupMMAR/view
A91: Kids Help Phone | B91: 1 | C91: 1 | D91: y | E91: 45920 | G91: Director of Clinical Service Operations | H91: Sara | I91: Smith | J91: SWPP Busting Burnout Webinar 9.14 - Watch On-Demand Form US | K91: Nate | L91: Nurture | N91: sara.smith@kidshelpphone.ca | O91: Website (no referrer info available) | Q91: Sent to Larry 9/24 for outreach support | U91: https://intradiem2023.lightning.force.com/lightning/r/Lead/00QV500000OjdIjMAJ/view
A92: Global Atlantic Financial Group | B92: 0 | C92: 0 | E92: 45936 | G92: Senior Analyst Workforce Management | H92: Tiffany | I92: Kelderhouse-Tucker | J92: Watched Webinar On Demand - From Plan to Performance: How WFM Leaders Are Orchestrating the AI-Powered Contact Center | K92: Nate | L92: DQ - Role | N92: tiffany.tucker@gafg.com | O92: Social Media - Organic (SocialHP) | U92: https://intradiem2023.lightning.force.com/lightning/r/Lead/00QV5000009uLofMAE/view
A93: TTEC | B93: 1 | C93: 0 | E93: 45944 | G93: WFM Trainer | H93: Wenzel | I93: Buaquina | J93: Webinar on Demand: Webinar 3.19.20 - What is Workforce Automation (form) | Video: Adherence Management | L93: MQL - ? | N93: wenzel.s.buaquina@ttec.com | O93: Website (no referrer info available) | U93: https://intradiem2023.lightning.force.com/lightning/r/Lead/00QV5000009uLTXMA2/view
A94: Bank of America | B94: 1 | C94: 1 | E94: 45945 | G94: Assistant Manager - TMT Sector Specialist | H94: Mohammed | I94: Hussein | J94: Website - Frost & Sullivan 2024 Report | K94: Nate | L94: MQL - Working | N94: mohammed.n.hussain@bofa.com | O94: Google Natural Search | U94: https://intradiem2023.lightning.force.com/lightning/r/Lead/00QV500000PtSOiMAN/view
A95: Onepoint | B95: 1 | C95: 1 | E95: 45951 | F95: consulting/partner? | G95: Change Management & Training Consultant | H95: Ninon | I95: Ribreau | J95: Demo Form | K95: Nate | L95: SAL : Meeting Booked | M95: 1 | N95: n.ribreau@groupeonepoint.com | O95: Website (no referrer info available) | Q95: SAL | U95: https://intradiem2023.lightning.force.com/lightning/r/Lead/00QV500000QBfyXMAT/view
A96: Gusto | B96: 0 | C96: 0 | E96: 45952 | G96: WFM Scheduling & Planning Analyst | H96: Bunny | I96: Bates | J96: Form: ...LB - Erlang-O Files Downloaded | K96: Nate | L96: Nurture | N96: bunny.bates@gusto.com | O96: Website (no referrer info available) | U96: https://intradiem2023.lightning.force.com/lightning/r/Lead/00QV5000009uMVzMAM/view
A97: iOPEX | B97: 0 | C97: 0 | E97: 45955 | F97: possible partner play | G97: VP Business Development | H97: Susan | I97: Cohen | J97: Demo Form | K97: Nate lead owner but Nick assigned to account | L97: DQ - Size | N97: susan.cohen@iopex.com | O97: Google Ad | U97: https://intradiem2023.lightning.force.com/lightning/r/Lead/00QV500000QTzvZMAT/view
A98: SOL Systems | B98: 1 | C98: 1 | E98: 45955 | G98: Co-Founder and Managing Partner | H98: Sameer | I98: Hasan | J98: Contact Us Form on Website | K98: Nate | L98: MQL - Working | N98: sameer.hasan@solgulf.com | O98: Google Ad (referrer: https://amamgame.com/)- display remarketing | U98: https://intradiem2023.lightning.force.com/lightning/r/Lead/00QV500000QT6BAMA1/view
A99: Teva Pharmaceuticals | B99: 1 | C99: 1 | E99: 45956 | G99: n/a | H99: Keithe | I99: Naoetter | J99: Contact Us Form on Website | K99: Nate | L99: MQL - Working | N99: tonyamoney@ccast.net | O99: Google Ad | U99: https://intradiem2023.lightning.force.com/lightning/r/Lead/00QV500000QBfyXMAT/view
A100: Execviva | B100: 1 | C100: 0 | E100: 45959 | G100: Senior Executive Assistant | H100: Fabiana | I100: Heredia | J100: Form: Webinar 09.30.25 - From Plan to Performance: How WFM Leaders Are Orchestrating (Watch On Demand form) | K100: Nate | L100: MQL - Working | N100: fabiana.heredia@execviva.com | O100: Website | U100: https://intradiem2023.lightning.force.com/lightning/r/Lead/00QV500000QdHTRMA3/view
...

Sheet Digital Spend Data
B1: Month | C1: # of MQL's | D1: Source
B2: Nov | C2: 5 | D2: Google Ad - 2, Website - 1, Google Natural Search - 2 | G2: 45597 | I2: 45627 | K2: 45658 | M2: 45689 | O2: 45717 | Q2: 45748 | S2: 45778 | U2: 45809 | W2: 45839 | Y2: 45870 | AA2: 45901 | AC2: 45931 | AE2: 45962 | AG2: 45992 | AI2: 46023 | AK2: 46054 | AM2: 46082
B3: Dec | C3: 1 | D3: Bing Natural Search -1 | G3: MQL | H3: SAL | I3: MQL | J3: SAL | K3: MQL | L3: SAL | M3: MQL | N3: SAL | O3: MQL | P3: SAL | Q3: MQL | R3: SAL | S3: MQL | T3: SAL | U3: MQL | V3: SAL | W3: MQL | X3: SAL | Y3: MQL | Z3: SAL | AA3: MQL | AB3: SAL | AC3: MQL | AD3: SAL | AE3: MQL | AF3: SAL | AG3: MQL | AH3: SAL | AI3: MQL | AJ3: SAL | AK3: MQL | AL3: SAL | AM3: MQL | AN3: SAL | AO3: RUNNING TOTALS:
B4: Jan | C4: 4 | D4: LI Ad -1, Website - 1, Bing natural search - 2 | F4: 6sense | G4: 0 | I4: 0 | K4: 0 | M4: 0 | O4: 0 | AO4: =SUM(G4,I4,K4,M4,W4,Q4,S4,U4,Y4,AA4,AC4,AE4,AG4,O4,AI4,AM4) -> 0 | AP4: 6sense ads attributed MQLs
B5: Feb | C5: 3 | D5: LinkedIn Ad - 1, Google Natural Search - 2 | F5: LinkedIn Ads | G5: 0 | I5: 0 | K5: 1 | M5: 1 | N5: 0 | O5: 1 | S5: 1 | T5: 0 | Y5: 1 | AE5: 1 | AO5: =SUM(G5,I5,K5,M5,W5,Q5,S5,U5,Y5,AA5,AC5,AE5,AG5,O5,AI5,AM5) -> 6 | AP5: LinkedIn ads attributed MQLs
B6: Mar | C6: 3 | D6: LinkedIn Ad - 1, G2 - 1, Website - 1 | F6: Google Ads | G6: 2 | H6: 1 | I6: 0 | K6: 0 | M6: 0 | O6: 0 | U6: 1 | W6: 1 | AE6: 1 | AG6: 1 | AI6: 1 | AJ6: 1 | AO6: =SUM(G6,I6,K6,M6,W6,Q6,S6,U6,Y6,AA6,AC6,AE6,AG6,O6,AI6,AM6,AK6) -> 7 | AP6: Google Ads attributed MQLs
B7: Apr | C7: 2 | D7: Google Natural Search - 2 | F7: Organic Search | G7: 2 | H7: 2 | I7: 1 | J7: 1 | K7: 1 | L7: 1 | M7: 2 | O7: 1 | P7: 1 | Q7: 2 | R7: 1 | U7: 4 | V7: 2 | W7: 2 | Y7: 4 | Z7: 4 | AC7: 1 | AE7: 2 | AG7: 1 | AH7: 1 | AI7: 1 | AJ7: 1 | AO7: =SUM(G7,I7,K7,M7,W7,Q7,S7,U7,Y7,AA7,AC7,AE7,AG7,O7,AI7,AM7) -> 24 | AP7: Organic Search MQLs
B8: May | C8: 1 | D8: LinkedIn Ad - 1 | F8: Website (source NA/other) | G8: 1 | I8: 0 | K8: 2 | L8: 1 | M8: 0 | N8: 2 | O8: 1 | P8: 1 | Q8: 0 | U8: 1 | W8: 2 | Y8: 0 | AA8: 3 | AC8: 2 | AD8: 1 | AO8: =SUM(G8,I8,K8,M8,W8,Q8,S8,U8,Y8,AA8,AC8,AE8,AG8,O8,AI8,AK8,AM8) -> 12 | AP8: Website MQLs (source N/A)
B9: June | C9: 6 | D9: Bing Natural Search - 2, Google Natural Search - 2, Google Ad - 1, Website - 1 | F9: TOTAL INBOUND | G9: =SUM(G4:G8) -> 5 | H9: 3 | I9: =SUM(I4:I8) -> 1 | J9: 1 | K9: =SUM(K4:K8) -> 4 | L9: 2 | M9: =SUM(M4:M8) -> 3 | N9: 2 | O9: 3 | P9: 2 | Q9: =SUM(Q4:Q8) -> 2 | R9: 1 | S9: 1 | T9: 0 | U9: =SUM(U4:U8) -> 6 | V9: 2 | W9: 5 | X9: 1 | Y9: =SUM(Y4:Y8) -> 5 | Z9: =SUM(Z4:Z8) -> 4 | AA9: 3 | AB9: =SUM(AB4:AB8) -> 0 | AC9: 5 | AD9: =SUM(AD4:AD8) -> 1 | AE9: 4 | AF9: 0 | AG9: 2 | AH9: 1 | AI9: 2 | AK9: 0 | AL9: 0 | AO9: =SUM(G9,I9,K9,M9,Q9,S9,U9,W9,Y9,AA9,AC9,AE9,AG9,O9,AI9,AK9,AM9) -> 51 | AP9: Digital MQLs (all sources)
B10: July | C10: 5 | D10: Google Natural Search - 2, Google Ad- 1, Organic Social - 1, Website - 1 | F10: Paid Media Only | G10: =SUM(G4:G6) -> 2 | H10: 1 | I10: =SUM(I4:I6) -> 0 | J10: 1 | K10: =SUM(K4:K6) -> 1 | L10: 0 | M10: =SUM(M4:M6) -> 1 | N10: 0 | O10: 1 | P10: 2 | Q10: 0 | R10: 0 | S10: =SUM(S3:S5) -> 1 | T10: 0 | U10: =SUM(U4:U6) -> 1 | V10: =SUM(V4:V6) -> 0 | W10: =SUM(W4:W6) -> 1 | X10: =SUM(X4:X6) -> 0 | Y10: =SUM(Y4:Y6) -> 1 | Z10: =SUM(Z4:Z6) -> 0 | AA10: =SUM(AA4:AA6) -> 0 | AB10: =SUM(AB4:AB6) -> 0 | AC10: 2 | AD10: 2 | AE10: 2 | AF10: 0 | AG10: 1 | AK10: 0 | AL10: 0 | AO10: =SUM($G$10,$I$10,K10,M10,W10,Q10,S10,U10,Y10,AA10,AC10,AE10,AG10,O10,AI10) -> 14 | AP10: inbound MQLs from Paid Media
B11: August | C11: 5 | D11: Google Natural Search - 4, LinkedIn Ad - 1
B12: September | C12: 4 | D12: Google Natural Search - 1, Website - 4
B13: October | C13: 5 | D13: Google Ad - 2, Google Natural Search - 1, Website - 2
B14: November | C14: 4 | D14: LinkedIn Ad - 1, Google Ad - 1, Google Natural Search - 2
B15: December | C15: 2 | D15: Google Natural Search - 1, Google Ad - 1
B16: 46023 | C16: 2 | D16: Bing Natural Search - 1, Google Ad - 1
B17: 46054 | C17: 0
B18: 46082 | C18: 5 | D18: LinkedIn Ads - 2, Google Natural Search - 2, Email Nurture - 1
B19: 46113
B20: 46143
B21: 46174
B22: 46204
B24: Paid Media Overview by Month 2025 | H24: Google Ads 2025 By Month | N24: 6sense Ads 2025 By Month | U24: LinkedIn Ads 2025 by Month | AC24: Reddit Ads 2025 by Month | AJ24: Microsoft Ads 2025 by Month
B25: Month | C25: Total Spend | D25: Impressions | E25: Total Clicks | F25: CTR | H25: Month | I25: Clicks | J25: Impressions | K25: Conv. Rate | L25: Cost | N25: Month | O25: Clicks | P25: Impressions | Q25: CTR | R25: Cost | S25: Accounts Reached | T25: eCPM | U25: Month | V25: Clicks | W25: Impressions | X25: Avg CTR | Y25: Cost | Z25: Leads | AA25: Conversions | AB25: Conversion Rate | AC25: Month | AD25: Clicks | AE25: Impressions | AF25: Avg CTR | AG25: Cost | AJ25: Month | AK25: Clicks | AL25: Impressions | AM25: Avg CTR | AN25: Cost | AP25: Next steps: | AZ25: Inbound Leads by Source
B26: 45597 | C26: =SUM(L26,R26,Y26) -> 12795.82 | D26: =SUM(P26,J26,W26) -> 1390330 | E26: =SUM(I26,O26,V26) -> 5566 | F26: =E26/D26 -> 0.0040033661 | H26: 45621 | I26: 1421 | J26: 40099 | K26: =I26/J26 -> 0.035437293 | L26: 2482.98 | M26: 2 leads | N26: 45621 | O26: 307 | P26: 555800 | Q26: 0.0006 | R26: 5870.61 | S26: 1071 | T26: 10.64 | U26: 45621 | V26: 3838 | W26: 794431 | X26: 0.0048 | Y26: 4442.23 | Z26: 0 leads | AA26: 6 conversions | AC26: 45621 | AJ26: 45621 | AP26: future state goal: report on touches per account across channels. need to define touch - tech stack currently unable to report on for multiple ad channels. | AZ26: https://intradiem.sharepoint.com/:x:/s/Marketing/EYnefu445hBJsEDhO4OTbNEBOmW6jvB5oEHbdAm4aLe3IQ?e=DtvzHP
B27: 45627 | C27: =SUM(L27,R27,Y27) -> 10042.78 | D27: =SUM(P27,J27,W27) -> 872982 | E27: =SUM(I27,O27,V27) -> 2616 | F27: =E27/D27 -> 0.0029966254 | H27: 45651 | I27: 746 | J27: 25415 | K27: =I27/J27 -> 0.029352744 | L27: 1315.64 | N27: 45651 | O27: 351 | P27: 585440 | Q27: 0.0006 | R27: 5917.82 | S27: 1038 | T27: 10.21 | U27: 45651 | V27: 1519 | W27: 262127 | X27: 0.0058 | Y27: 2809.32 | Z27: 0 leads | AA27: 0 conversions | AC27: 45651 | AJ27: 45651 | AP27: MQA and SAL stage coverage - automate marketing emails to the area where "leads go to die"
B28: 45658 | C28: =SUM(L28,R28,Y28) -> 10121.93 | D28: =SUM(P28,J28,W28) -> 923059 | E28: =SUM(I28,O28,V28) -> 2566 | F28: =E28/D28 -> 0.0027798873 | H28: 45682 | I28: 561 | J28: 27869 | K28: =I28/J28 -> 0.020129893 | L28: 1233.06 | N28: 45682 | O28: 313 | P28: 611159 | Q28: 0.0006 | R28: 5734.74 | S28: 1090 | T28: 9.54 | U28: 45682 | V28: 1692 | W28: 284031 | X28: 0.006 | Y28: 3154.13 | Z28: 1 lead | AA28: 0 conversions | AC28: 45682 | AJ28: 45682 | AP28: shine a light on stage 1-2 (sits there a long time and some go back to nurture)
B29: 45689 | C29: =SUM(L29,R29,Y29) -> 11589.4 | D29: =SUM(P29,J29,W29) -> 969667 | E29: =SUM(I29,O29,V29) -> 3030 | F29: =E29/D29 -> 0.0031247841 | H29: 45713 | I29: 447 | J29: 58467 | K29: =I29/J29 -> 0.0076453384 | L29: 2241.65 | N29: 45713 | O29: 174 | P29: 453615 | Q29: 0.0004 | R29: 4587.53 | S29: 1129 | T29: 10.19 | U29: 45713 | V29: 2409 | W29: 457585 | X29: =V29/W29 -> 0.0052645956 | Y29: 4760.22 | Z29: 0 leads | AA29: 0 conversions | AC29: 45713 | AJ29: 45713 | AP29: how does marketing help sales get higher in an account? | AZ29: Paid Media Overview by Channel
B30: 45717 | C30: =SUM(L30,R30,Y30) -> 23022.89 | D30: =SUM(P30,J30,W30) -> 1219456 | E30: =SUM(I30,O30,V30) -> 5028 | F30: =E30/D30 -> 0.00412315 | H30: 45741 | I30: 1523 | J30: 76517 | K30: =I30/J30 -> 0.019904074 | L30: 4244.79 | N30: 45741 | O30: 323 | P30: 720377 | Q30: 0.0004 | R30: 7955.82 | S30: 1199 | T30: 11.13 | U30: 45741 | V30: 3182 | W30: 422562 | X30: =V30/W30 -> 0.0075302559 | Y30: 10822.28 | Z30: 2 leads | AA30: 0 conversions | AC30: 45741 | AJ30: 45741 | AZ30: https://intradiem.sharepoint.com/:x:/s/Marketing/EWAVQhBPQd1IqXPP3e6_D4wBBZ_9wxxk5RaSakyG4hJAYQ?e=KDs8s6
B31: 45748 | C31: =SUM(L31,R31,Y31) -> 22527.66 | D31: =SUM(P31,J31,W31) -> 1271009 | E31: =SUM(I31,O31,V31) -> 4053 | F31: =E31/D31 -> 0.0031888051 | H31: 45748 | I31: 1206 | J31: 84360 | K31: =I31/J31 -> 0.014295875 | L31: 1838.19 | N31: 45748 | O31: 479 | P31: 835475 | Q31: =O31/P31 -> 0.00057332655 | R31: 8671.48 | S31: 1540 | T31: 10.44 | U31: 45748 | V31: 2368 | W31: 351174 | X31: =V31/W31 -> 0.006743096 | Y31: 12017.99 | Z31: 4 leads (0 MQLs) | AA31: 0 conversions | AC31: 45748 | AJ31: 45748 | AP31: engagement campaign for SWPP webinar registrants, attendees to generate SALs
B32: 45778 | C32: =SUM(L32,R32,Y32,AG32) -> 20398.95 | D32: =SUM(P32,J32,W32,AE32) -> 827720 | E32: =SUM(I32,O32,V32,AD32) -> 1511 | F32: =E32/D32 -> 0.0018254965 | H32: 45778 | I32: 303 | J32: 5907 | K32: 0.0513 | L32: 1226.12 | M32: 1 lead (G4S), 12 conversions | N32: 45778 | O32: 360 | P32: 608435 | Q32: 0.0006 | R32: 6381.88 | S32: 1805 | T32: 10.54 | U32: 45778 | V32: 237 | W32: 46595 | X32: 0.0051 | Y32: 11845.24 | Z32: 1 lead (1 MQL) | AA32: 0 conversions | AC32: 45778 | AD32: 611 | AE32: 166783 | AF32: 0.0037 | AG32: 945.71 | AJ32: 45778 | AZ32: Spend vs. Budget Tracker
B33: 45809 | C33: =SUM(L33,R33,Y33,AG33) -> 14967.103 | D33: =SUM(P33,J33,W33,AE33) -> 621650 | E33: =SUM(I33,O33,V33,AD33) -> 1907 | F33: =E33/D33 -> 0.0030676426 | H33: 45809 | I33: 412 | J33: 9396 | K33: =I33/J33 -> 0.043848446 | L33: 1193.69 | M33: 1 lead | N33: 45809 | O33: 228 | P33: 444986 | Q33: 0.0005 | R33: 4682.7 | S33: 1953 | T33: 10.54 | U33: 45809 | V33: 1134 | W33: 138847 | X33: =V33/W33 -> 0.0081672632 | Y33: 8850.39 | Z33: 0 leads | AA33: 0 conversions | AC33: 45809 | AD33: 133 | AE33: 28421 | AF33: 0.004679638 | AG33: 240.3233 | AJ33: 45809 | AZ33: https://intradiem.sharepoint.com/:x:/s/Marketing/EblifdWqOG9EnHC7GKBI0lABXYWAP1WFbbyt5mvWk6htaA?e=2CexqB
B34: 45839 | C34: =SUM(L34,R34,Y34,AG34,AN34) -> 13702.02 | D34: =SUM(P34,J34,W34,AE34,AL34) -> 609488 | E34: =SUM(I34,O34,V34,AD34,AK34) -> 3447 | F34: =E34/D34 -> 0.0056555666 | H34: 45839 | I34: 625 | J34: 13682 | K34: 0.0457 | L34: 3280.08 | M34: 1 lead | N34: 45839 | O34: 169 | P34: 236803 | Q34: 0.0007 | R34: 2639.13 | S34: 1981 | T34: 11.14 | U34: 45839 | V34: 1498 | W34: 145556 | X34: =V34/W34 -> 0.010291572 | Y34: 5768.37 | Z34: 0 leads | AA34: 0 conversions | AC34: 45839 | AD34: 610 | AE34: 149676 | AF34: 0.00408 | AG34: 1098.25 | AJ34: 45839 | AK34: 545 | AL34: 63771 | AM34: =AK34/AL34 -> 0.0085462044 | AN34: 916.19
B35: 45870 | C35: =SUM(L35,R35,Y35,AG35,AN35) -> 15211.83 | D35: =SUM(P35,J35,W35,AE35,AL35) -> 743971 | E35: =SUM(I35,O35,V35,AD35,AK35) -> 7127 | F35: =E35/D35 -> 0.0095796745 | H35: 45870 | I35: 861 | J35: 17743 | K35: =I35/J35 -> 0.048526179 | L35: 2860.18 | N35: 45870 | O35: 234 | P35: 301664 | Q35: =O35/P35 -> 0.00077569746 | R35: 2700.15 | S35: 2212 | T35: 8.95 | U35: 45870 | V35: 3769 | W35: 264254 | X35: =V35/W35 -> 0.014262793 | Y35: 6748.21 | Z35: 1 lead | AA35: 0 conversions | AC35: 45870 | AD35: 405 | AE35: 73280 | AF35: =AD35/AE35 -> 0.0055267467 | AG35: 892.66 | AJ35: 45870 | AK35: 1858 | AL35: 87030 | AM35: =AK35/AL35 -> 0.02134896 | AN35: 2010.63
B36: 45901 | C36: =SUM(L36,R36,Y36,AG36,AN36) -> 14287.68 | D36: =SUM(P36,J36,W36,AE36,AL36) -> 840953 | E36: =SUM(I36,O36,V36,AD36,AK36) -> 8208 | F36: =E36/D36 -> 0.0097603552 | H36: 45901 | I36: 919 | J36: 19535 | K36: =I36/J36 -> 0.047043768 | L36: 1582.33 | N36: 45901 | O36: 312 | P36: 409410 | Q36: =O36/P36 -> 0.00076207225 | R36: 3272.47 | S36: 2385 | T36: 7.99 | U36: 45901 | V36: 3130 | W36: 292258 | X36: 0.0107 | Y36: 6657.81 | Z36: 0 leads | AA36: 0 conversions | AC36: 45901 | AD36: 21 | AE36: 2879 | AF36: =AD36/AE36 -> 0.0072941994 | AG36: 50.85 | AJ36: 45901 | AK36: 3826 | AL36: 116871 | AM36: =AK36/AL36 -> 0.032736949 | AN36: 2724.22 | AO36: 0 conversions
B37: 45931 | C37: =SUM(L37,R37,Y37,AG37,AN37) -> 24129.37 | D37: =SUM(P37,J37,W37,AE37,AL37) -> 1151744 | E37: =SUM(I37,O37,V37,AD37,AK37) -> 6278 | F37: =E37/D37 -> 0.0054508641 | H37: 45931 | I37: 1791 | J37: 73169 | K37: =I37/J37 -> 0.024477579 | L37: 6174.97 | N37: 45931 | O37: 622 | P37: 845758 | Q37: =O37/P37 -> 0.00073543496 | R37: 7244.43 | S37: 2582 | T37: 8.57 | U37: 45931 | V37: 2927 | W37: 205784 | X37: 0.0142 | Y37: 9410.27 | Z37: 0 leads | AA37: 0 conversions | AC37: 45931 | AJ37: 45931 | AK37: 938 | AL37: 27033 | AM37: =AK37/AL37 -> 0.034698332 | AN37: 1299.7 | AO37: 0 conversions
B38: 45962 | C38: =SUM(L38,R38,Y38,AG38,AN38) -> 33841.02 | D38: =SUM(P38,J38,W38,AE38,AL38) -> 1546142 | E38: =SUM(I38,O38,V38,AD38,AK38) -> 9367 | F38: =E38/D38 -> 0.0060583051 | H38: 45962 | I38: 2593 | J38: 56620 | K38: 0.0458 | L38: 8886.97 | N38: 45962 | O38: 733 | P38: 1086444 | Q38: 0.0007 | R38: 9420.77 | S38: 2576 | T38: 8.67 | U38: 45962 | V38: 4642 | W38: 367052 | X38: =V38/W38 -> 0.012646709 | Y38: 13566.52 | Z38: 1 lead (1 MQL) | AA38: 1 conversion | AC38: 45962 | AJ38: 45962 | AK38: 1399 | AL38: 36026 | AM38: =AK38/AL38 -> 0.038833065 | AN38: 1966.76
B39: 45992 | C39: =SUM(L39,R39,Y39,AG39,AN39) -> 54388.65 | D39: =SUM(P39,J39,W39,AE39,AL39) -> 2624983 | E39: =SUM(I39,O39,V39,AD39,AK39) -> 18364 | F39: =E39/D39 -> 0.0069958548 | H39: 45992 | I39: 4669 | J39: 505904 | K39: =I39/J39 -> 0.0092290237 | L39: 14217.45 | N39: 45992 | O39: 656 | P39: 1183380 | Q39: =O39/P39 -> 0.00055434434 | R39: 9944.12 | S39: 2388 | T39: 8.4 | U39: 45992 | V39: 11718 | W39: 890282 | X39: =V39/W39 -> 0.013162122 | Y39: 28156.41 | Z39: 7 leads (0 MQL) | AA39: 5 conversions | AB39: 0.0023 | AC39: 45992 | AJ39: 45992 | AK39: 1321 | AL39: 45417 | AM39: =AK39/AL39 -> 0.029086025 | AN39: 2070.67
B40: 46023 | C40: =SUM(L40,R40,Y40,AG40,AN40) -> 33454.83 | D40: =SUM(P40,J40,W40,AE40,AL40) -> 2301702 | E40: =SUM(I40,O40,V40,AD40,AK40) -> 9534 | F40: =E40/D40 -> 0.0041421522 | H40: 46023 | I40: 1696 | J40: 249239 | K40: =I40/J40 -> 0.0068047135 | L40: 8499.34 | N40: 46023 | O40: 820 | P40: 1437045 | Q40: =O40/P40 -> 0.00057061539 | R40: 10384.92 | S40: 3178 | T40: 7.23 | U40: 46023 | V40: 6073 | W40: 557154 | X40: =V40/W40 -> 0.010900038 | Y40: 11772.91 | Z40: 2 leads (1 MQL) - VITO RT | AA40: 0 conversions | AC40: 46023 | AJ40: 46023 | AK40: 945 | AL40: 58264 | AM40: =AK40/AL40 -> 0.016219278 | AN40: 2797.66
B41: 46054 | C41: =SUM(L41,R41,Y41,AG41,AN41) -> 29363.53 | D41: =SUM(P41,J41,W41,AE41,AL41) -> 1801654 | E41: =SUM(I41,O41,V41,AD41,AK41) -> 9740 | F41: =E41/D41 -> 0.0054061435 | H41: 46054 | I41: 1409 | J41: 62914 | K41: =I41/J41 -> 0.022395651 | L41: 6762.26 | N41: 46054 | O41: 542 | P41: 1026438 | Q41: =O41/P41 -> 0.00052803969 | R41: 8489.47 | S41: 3287 | T41: 8.27 | U41: 46054 | V41: 6607 | W41: 676188 | X41: =V41/W41 -> 0.0097709513 | Y41: 12286.86 | Z41: 2 leads | AA41: 1 conversion | AC41: 46054 | AJ41: 46054 | AK41: 1182 | AL41: 36114 | AM41: =AK41/AL41 -> 0.032729689 | AN41: 1824.94
B42: 46082 | C42: 31298.72 | D42: 1757377 | E42: 13081 | F42: 0.0074 | H42: 46082 | I42: 1922 | J42: 97187 | K42: 0.0198 | L42: 7551.61 | N42: 46107 | O42: 468 | P42: 962617 | Q42: 0.0005 | R42: 8134.09 | S42: 2660 | T42: 8.45 | U42: 46082 | V42: 9260 | W42: 648937 | X42: 0.0143 | Y42: 13803.93 | Z42: 3 leads | AA42: 6 conversions | AC42: 46082 | AJ42: 46082 | AK42: 1431 | AL42: 48636 | AM42: 0.0294 | AN42: 1809.09
B43: 46113 | C43: =SUM(L43,R43,Y43,AG43,AN43) -> 30962.79 | D43: =SUM(P43,J43,W43,AE43,AL43) -> 1577060 | E43: =SUM(I43,O43,V43,AD43,AK43) -> 11636 | F43: =E43/D43 -> 0.0073782862 | H43: 46113 | I43: 1967 | J43: 42481 | K43: =I43/J43 -> 0.046303053 | L43: 8084.47 | N43: 46113 | O43: 520 | P43: 1002078 | Q43: =O43/P43 -> 0.00051892168 | R43: 7753.34 | S43: 2796 | T43: 7.93 | U43: 46113 | V43: 8369 | W43: 485484 | X43: =V43/W43 -> 0.017238467 | Y43: 14027.67 | AC43: 46113 | AJ43: 46113 | AK43: 780 | AL43: 47017 | AM43: =AK43/AL43 -> 0.016589744 | AN43: 1097.31
B44: 46143 | C44: 31329.1 | D44: 1506053 | E44: 12190 | F44: 0.0081 | H44: 46143 | I44: 1267 | J44: 54225 | K44: 0.0234 | L44: 8541.81 | N44: 46143 | O44: 530 | P44: 1039413 | Q44: 0.0005 | R44: 7776.77 | S44: 2826 | U44: 46143 | V44: 9622 | W44: 382964 | X44: 0.0251 | Y44: 13245.49 | Z44: 0 leads | AA44: 7 conversions | AC44: 46143 | AJ44: 46143 | AK44: 771 | AL44: 29451 | AM44: 0.0262 | AN44: 1765.03 | AO44: 2 conversions
B45: 46174 | C45: 31769.46 | D45: 1354314 | E45: 12982 | F45: 0.0096 | H45: 46174 | I45: 1686 | J45: 59755 | K45: 0.0282 | L45: 8550.71 | N45: 46174 | O45: 407 | P45: 948075 | Q45: 0.0004 | R45: 7849.59 | S45: 3099 | T45: 8.28 | U45: 46174 | V45: 10125 | W45: 325937 | X45: 0.0311 | Y45: 13553.12 | Z45: 0 leads | AA45: 0 conversions | AC45: 46174 | AJ45: 46174 | AK45: 764 | AL45: 20547 | AM45: 0.0372 | AN45: 1816.04 | AO45: 1 conversion | AQ45: 46190
B46: 46204 | C46: 34395.59 | D46: 2234994 | E46: 20500 | F46: 0.0092 | H46: 46204 | I46: 1153 | J46: 48171 | K46: =I46/J46 -> 0.023935563 | L46: 7874.09 | N46: 46204 | O46: 535 | P46: 1007310 | Q46: =O46/P46 -> 0.00053111753 | R46: 8008.94 | S46: 3331 | T46: 7.95 | U46: 46204 | V46: 15452 | W46: 372286 | X46: =V46/W46 -> 0.041505724 | Y46: $14,985.00 | Z46: 0 leads | AA46: 2 conversions | AC46: 46204 | AJ46: 46204 | AK46: 3360 | AL46: 807227 | AM46: 0.017 | AN46: 3527.56
C47: =SUM(C26:C46) -> 503601.12 | D47: =SUM(D26:D46) -> 28146308 | E47: =SUM(E26:E46) -> 168731 | F47: =E47/D47 -> 0.0059947827 | H47: SUM | I47: =SUM(I26:I46) -> 29177 | J47: =SUM(J26:J46) -> 1628655 | K47: =I47/J47 -> 0.017914782 | L47: =SUM(L26:L46) -> 108642.39 | N47: SUM | O47: =SUM(O26:O46) -> 9083 | P47: =SUM(P26:P46) -> 16301722 | Q47: =O47/P47 -> 0.0005571804 | R47: =SUM(R26:R46) -> 143420.77 | U47: SUM | V47: =SUM(V26:V46) -> 109571 | W47: =SUM(W26:W46) -> 8371488 | X47: =V47/W47 -> 0.013088593 | Y47: =SUM(Y26:Y46) -> 207699.37 | AC47: SUM | AD47: =SUM(AD32:AD37) -> 1780 | AE47: =SUM(AE32:AE37) -> 421039 | AF47: =AD47/AE47 -> 0.0042276369 | AG47: =SUM(AG32:AG37) -> 3227.7933 | AJ47: SUM | AK47: =SUM(AK34:AK44) -> 14996 | AL47: =SUM(AL34:AL44) -> 595630 | AM47: =AK47/AL47 -> 0.025176704 | AN47: =SUM(AN34:AN44) -> 20282.2 | AZ47: Prev version:
AY48: https://intradiem.sharepoint.com/:x:/s/Marketing/ERhfM-J36aVOgegUmQgdOMIB9StV0fT91DuKqsZTWyNWGQ?e=LVUZ5T

Sheet Event Spend Raw
A1: Events | B1: Date | C1: Spend | D1: MQLs | E1: MQA | F1: Opps | G1: Event Date Parsed
A2: The Forum UK | B2: 11.5.24 | C2: 6561 | D2: 7 | F2: 0 | G2: 45601
A3: Five9 CX Summit | B3: 11.12.24 | C3: 8500 | D3: 2 | F3: 0 | G3: 45608
A4: SWPP Webinar | B4: 12.12.24 | C4: 1500 | D4: 11 | F4: 0 | G4: 45638
A5: SWPP Webinar | B5: 2.25.25 | C5: 1500 | D5: 13 | E5: 12 | F5: 0 | G5: 45713
A6: Execs in the Know: CRS Spring | B6: 3.3.25 | C6: 45000 | D6: 14 | E6: 8 | F6: 1 | G6: 45719
A7: CCW Exchange UK | B7: 3.5.25 | C7: 32000 | D7: 9 | E7: 9 | F7: 2 | G7: 45721
A8: CCW Exchange Austin | B8: 3.12.25 | C8: 30000 | D8: 3 | E8: 2 | F8: 1 | G8: 45728
A9: Forefront Toronto | B9: 3.26.25 | C9: 15000 | D9: 3 | E9: 1 | F9: 0 | G9: 45742
A10: Frost and Sullivan | B10: 4.6.25 | C10: 50000 | D10: 8 | E10: 7 | F10: 1 | G10: 45753
A11: SWPP Conference | B11: 4.25.25 | C11: 20000 | D11: 21 | E11: 15 | F11: 3 | G11: 45772
A12: The Forum UK | B12: 4.30.25 | C12: 8000 | D12: 18 | E12: 13 | F12: 0 | G12: 45777
A13: SWPP Webinar | B13: 5.8.25 | C13: 1500 | D13: 8 | E13: 4 | F13: 0 | G13: 45785
A14: Call Miner UK | B14: 6.3.25 | C14: 2705 | D14: 12 | E14: 6 | F14: 0 | G14: 45811
A15: CCMA Connect | B15: 6.10.25 | C15: 13526 | D15: 16 | E15: 6 | F15: 2 | G15: 45818
A16: Forum Best Practices Showcase | B16: 6.12.25 | C16: 4084 | D16: 13 | E16: 6 | F16: 2 | G16: 45820
A17: Actionary/Intradiem webinar | B17: 6.26.25 | C17: 1500 | D17: 5 | E17: 5 | F17: 0 | G17: 45834
A18: Genesys Partners and Friends webinar | B18: 7.21.25 | C18: 0 | D18: 0 | F18: 0 | G18: 45859
A19: Five9 Ampify webnar | B19: 7.23.25 | C19: 0 | D19: 0 | F19: 0 | G19: 45861
A20: Auriemma | B20: 8.7.25 | C20: 30750 | D20: 39 | E20: 17 | F20: 0 | G20: 45876
A21: Genesys Xperience | B21: 9.10.25 | C21: 35000 | D21: 32 | E21: 28 | F21: 2 | G21: 45910
A22: SWPP Webinar | B22: 9.30.25 | C22: 1500 | D22: 15 | E22: 7 | F22: 0 | G22: 45930
A23: CCW Expo - Amsterdam | B23: 10.6.25 | C23: 14950 | D23: 3 | E23: 3 | F23: 1 | G23: 45936
A24: Call Design WOW | B24: 10.14.25 | C24: 15000 | D24: 0 | F24: 0 | G24: 45944
A25: CCW Exchange | B25: 11.3.25 | C25: 33000 | D25: 8 | E25: 6 | F25: 0 | G25: 45964
A26: The Forum Conference | B26: 11.5 | C26: 8230 | D26: 8 | E26: 6 | F26: 0 | G26: 45966
A27: GTACC Conference | B27: 11.5 | C27: 7752 | D27: 14 | E27: 8 | F27: 0 | G27: 45966
A28: Five9 CX Summit | B28: 11.17.25 | C28: 35000 | D28: 21 | E28: 19 | F28: 2 | G28: 45978
A29: Contact Centre Expo | B29: 11.19.25 | C29: 10437 | D29: 6 | E29: 6 | F29: 0 | G29: 45980
A30: Auriemma WFM Roundtable | B30: 11.20.25 | C30: 30750 | D30: 6 | E30: 4 | F30: 0 | G30: 45981
A31: SWPP Webinar | B31: 1.28.26 | C31: 1500 | D31: 14 | F31: 0 | G31: 46050
A32: Execs in the Know: CRS Spring | B32: 2.25.26 | C32: 47300 | D32: 10 | E32: 7 | G32: 46078
A33: CCW Exchange Austin | B33: 3.4 - 3.6 | C33: 37500 | D33: 8 | E33: 7 | F33: 1 | G33: 46085
A34: CCW Exchange UK | B34: 3.3 - 3.5 | C34: 31000 | D34: 8 | E34: 7 | G34: 46084
A35: CCW Market Report UK | B35: Ongoing | C35: 20000 | D35: 15 | E35: 11 | G35: 46082
A36: Forefront Toronto | B36: 3.25 | C36: 20000 | D36: 2 | E36: 2 | G36: 46106
A37: Frost & Sullivan CCEast | B37: 4.12 - 4.15 | C37: 55000 | D37: 25 | E37: 21 | G37: 46124
A38: Contact NB Awards Gala and Tradeshow | B38: 4.22 | C38: 300 | D38: 0 | G38: 46134
A39: SWPP | B39: 4.27 - 4.29 | C39: 55000 | D39: 30 | E39: 24 | F39: 2 | G39: 46139
A40: The Forum Conference | B40: 4.28 | C40: 16000 | D40: 17 | E40: 14 | G40: 46140
A41: UK Genesys Xperience | B41: 4.28 - 4.29 | C41: 8000 | D41: 8 | E41: 4 | G41: 46140
A42: AUS Connect | B42: 4.29-30 | C42: 0 | D42: 0 | G42: 46141
A43: Genesys Bootcamps | B43: 4.3 | C43: 500 | D43: 0 | G43: 46142
A44: CCW Market Report UK | B44: Ongoing | C44: 20000 | D44: 15 | E44: 15 | G44: 46113
A45: Webinar on Demand - Webinar 01.28.26 - Why AI Alone Isn’t Enough (Watch On Demand form) | B45: Ongoing | D45: 1 | E45: 1 | G45: 46113
A46: UK FEC | B46: 46154 | C46: 20000 | D46: 0 | G46: 46154
A47: CCMA Connect | B47: 46155 | C47: 24000 | D47: 9 | E47: 6 | G47: 46155
A48: SWPP/Humana Webinar | B48: 46162 | C48: 1500 | D48: 10 | E48: 10 | G48: 46162
A49: Consero | B49: 46197 | C49: 19600 | D49: 4 | E49: 4 | G49: 46197
A50: Genesys Drive for Solution Consultants | B50: 7.22 - 23 | C50: 5000 | G50: 46225
A51: Genesys Xperience | B51: 9.1 - 3 | C51: 37500 | G51: 46266
A52: DMG Webinar | B52: 9.2 | C52: comp | G52: 46267
A53: Execs in the Know: CRS Fall | B53: 9.30 - 10.2 | C53: 21000 | G53: 46295
A54: Five9 CX Connect Americas | B54: 10.12 - 10.13 | C54: 12500 | G54: 46307
A55: CX BFSI Exchange | B55: 10.13 - 10.14 | C55: 34000 | G55: 46308
A56: WOW Call Design Australia Conference | B56: 10.13-14 | C56: 17500 | G56: 46308
A57: CCW Exchange | B57: 10.13 10.15 | C57: 31000 | G57: 46308
A58: Alvaria User Conference | B58: 10.13-16 | G58: 46308
A59: The Forum Conference | B59: 45964 | C59: 5000 | G59: 46329

Sheet helper tab
A1: Lead Source | B1: Channel | I1: Stage
A2: Partner | B2: Alliances | I2: Solution Design/Value Creation
A3: BDR Outbound | B3: Cold | I3: Discovery
A4: memoryBlue-US | B4: Cold | I4: Closed Won
A5: Sales | B5: Exclude | I5: Unqualified
A6: Hosted Event | B6: Events | I6: Closed Lost
A7: Website | B7: Digital | I7: Propose | J7: Late Stage
A8: Bing Natural Search | B8: Digital | I8: Qualification
A9: Events | B9: Events | I9: Prove
A10: memoryBlue-UK | B10: Cold | I10: Procure | J10: Late Stage
A11: webhelp-access-requested | B11: Digital | I11: Negotiate
A12: Event | B12: Events | I12: Lost
A13: Referral | B13: Exclude
A14: Outbound Email | B14: Cold
A15: Google Natural Search | B15: Digital
A16: Lusha | B16: Cold
A17: 6sense | B17: Digital
A18: LinkedIn Ad | B18: Digital
A19: Webinar | B19: Digital
A20: Display Ad | B20: Digital
A21: Linkedin Sales Navigator | B21: Digital
A22: Zoominfo | B22: Cold
A23: Google Ad - SEM | B23: Digital
A24: Inside Sales | B24: Cold
... A33: Cold | B33: Cold

Sheet Stage History
A1: Report: | B1: Pipeline Council - Opp Stage History
A2: Field / Event | B2: Old Value | C2: New Value | D2: Edit Date | E2: Opportunity Name | F2: Lead Source | G2: Lead Source Original | H2: Partner | I2: Created Date | J2: Close Date | K2: Amount | L2: Total Net New ACV | M2: Opportunity ID | N2: Account Name | O2: Channel | P2: Change Date | Q2: Is Late Stage | R2: Is Closed Won | S2: LateStage_Unique_Monthly_Flag | T2: ClosedWon_Unique_Monthly_Flag | U2: Is Closed Lost | V2: ClostLost_Unique_Monthly_Flag | W2: Aging | X2: Next Stage Date | Y2: Days in Stage | Z2: Current Stage Flag | AA2: Opp Closed Won Date | AB2: First Late Stage Date | AC2: Days Created to Late Stage | AD2: Days from Late Stage to Closed Won | AE2: Days Created to Won | AF2: Include in Aging Calc
A3: Stage | B3: Qualification | C3: Solution Design/Value Creation | D3: 7/31/2026, 11:49 AM | E3: McKesson - Queue Optimizer | I3: 46122 | J3: 46477 | K3: 16000 | L3: 16000 | M3: 006V500000QLG61 | N3: McKesson | O3: =_xlfn.IFNA(VLOOKUP(Table1[[#This Row],[Lead Source]],'helper tab'!A:B,2,FALSE),"Exclude") -> Exclude | P3: =--SUBSTITUTE(D3,",","") -> 46234.492 | Q3: =IF(OR($C3="Propose",$C3="Procure"),1,0) -> 0 | R3: =IF($C3="Closed Won",1,0) -> 0 | S3: =IF( AND($Q3=1,$M3<>""), IF( COUNTIFS( $M$3:$M3,$M3, $O$3:$O3,$O3, $Q$3:$Q3,1, $P$3:$P3,">="&EOMONTH($P3,-1)+1, $P$3:$P3,"<"&EOMONTH($P3,0)+1 )=1, 1, 0), 0) -> 0 | T3: =IF(AND($R3=1,$M3<>""),IF(COUNTIFS($M$3:$M3,$M3,$O$3:$O3,$O3,$R$3:$R3,1,$P$3:$P3,">="&EOMONTH($P3,-1)+1,$P$3:$P3,"<"&EOMONTH($P3,0)+1)=1,1,0),0) -> 0 | U3: =IF($C3="Closed Lost",1,0) -> 0 | V3: =IF(AND($U3=1,$M3<>""),IF(COUNTIFS($M$3:$M3,$M3,$O$3:$O3,$O3,$U$3:$U3,1,$P$3:$P3,">="&EOMONTH($P3,-1)+1,$P$3:$P3,"<"&EOMONTH($P3,0)+1)=1,1,0),0) -> 0 | W3: =TODAY()-Table1[[#This Row],[Change Date]] -> 23.507639 | X3: =IFERROR( IF( COUNTIFS($M:$M,$M3,$P:$P,">"&$P3)=0, "", _xlfn.MINIFS($P:$P,$M:$M,$M3,$P:$P,">"&$P3) ), "" ) | Y3: =IF(Table1[[#This Row],[Next Stage Date]]<>"",Table1[[#This Row],[Next Stage Date]]-Table1[[#This Row],[Change Date]],TODAY()-Table1[[#This Row],[Change Date]]) -> 23.507639 | Z3: =IF(P3=_xlfn.MAXIFS($P:$P,$M:$M,$M3),1,0) -> 1 | AA3: =IF( COUNTIFS($M:$M,$M3,$C:$C,"Closed Won")=0, "", _xlfn.MINIFS($P:$P,$M:$M,$M3,$C:$C,"Closed Won") ) | AB3: =IF( COUNTIFS($M:$M,$M3,$Q:$Q,1)=0, "", _xlfn.MINIFS($P:$P,$M:$M,$M3,$Q:$Q,1) ) | AC3: =IF(AB3<>"",AB3-I3,"") | AD3: =IF(AND(AB3<>"",AA3<>""),AA3-AB3,"") | AE3: =IF(AA3<>"",AA3-I3,"") | AF3: =IFERROR(_xlfn.XLOOKUP(Table1[[#This Row],[Opportunity ID]],'Aging Detail'!$H$14:$H$20,'Aging Detail'!$F$14:$F$20),TRUE) -> TRUE
A4: Stage | B4: Solution Design/Value Creation | C4: Propose | D4: 7/31/2026, 11:28 AM | E4: Five9 - Telus - NTT Data | F4: Partner | H4: Five9 | I4: 46195 | J4: 46290 | K4: 210184 | L4: 140184 | M4: 006V500000TdK6D | N4: NTT Data Group | O4: =_xlfn.IFNA(VLOOKUP(Table1[[#This Row],[Lead Source]],'helper tab'!A:B,2,FALSE),"Exclude") -> Alliances | P4: =--SUBSTITUTE(D4,",","") -> 46234.478 | Q4: =IF(OR($C4="Propose",$C4="Procure"),1,0) -> 1 | R4: =IF($C4="Closed Won",1,0) -> 0 | S4: =IF( AND($Q4=1,$M4<>""), IF( COUNTIFS( $M$3:$M4,$M4, $O$3:$O4,$O4, $Q$3:$Q4,1, $P$3:$P4,">="&EOMONTH($P4,-1)+1, $P$3:$P4,"<"&EOMONTH($P4,0)+1 )=1, 1, 0), 0) -> 1 | T4: =IF(AND($R4=1,$M4<>""),IF(COUNTIFS($M$3:$M4,$M4,$O$3:$O4,$O4,$R$3:$R4,1,$P$3:$P4,">="&EOMONTH($P4,-1)+1,$P$3:$P4,"<"&EOMONTH($P4,0)+1)=1,1,0),0) -> 0 | U4: =IF($C4="Closed Lost",1,0) -> 0 | V4: =IF(AND($U4=1,$M4<>""),IF(COUNTIFS($M$3:$M4,$M4,$O$3:$O4,$O4,$U$3:$U4,1,$P$3:$P4,">="&EOMONTH($P4,-1)+1,$P$3:$P4,"<"&EOMONTH($P4,0)+1)=1,1,0),0) -> 0 | W4: =TODAY()-Table1[[#This Row],[Change Date]] -> 23.522222 | X4: =IFERROR( IF( COUNTIFS($M:$M,$M4,$P:$P,">"&$P4)=0, "", _xlfn.MINIFS($P:$P,$M:$M,$M4,$P:$P,">"&$P4) ), "" ) | Y4: =IF(Table1[[#This Row],[Next Stage Date]]<>"",Table1[[#This Row],[Next Stage Date]]-Table1[[#This Row],[Change Date]],TODAY()-Table1[[#This Row],[Change Date]]) -> 23.522222 | Z4: =IF(P4=_xlfn.MAXIFS($P:$P,$M:$M,$M4),1,0) -> 1 | AA4: =IF( COUNTIFS($M:$M,$M4,$C:$C,"Closed Won")=0, "", _xlfn.MINIFS($P:$P,$M:$M,$M4,$C:$C,"Closed Won") ) | AB4: =IF( COUNTIFS($M:$M,$M4,$Q:$Q,1)=0, "", _xlfn.MINIFS($P:$P,$M:$M,$M4,$Q:$Q,1) ) -> 46234.478 | AC4: =IF(AB4<>"",AB4-I4,"") -> 39.477778 | AD4: =IF(AND(AB4<>"",AA4<>""),AA4-AB4,"") | AE4: =IF(AA4<>"",AA4-I4,"") | AF4: =IFERROR(_xlfn.XLOOKUP(Table1[[#This Row],[Opportunity ID]],'Aging Detail'!$H$14:$H$20,'Aging Detail'!$F$14:$F$20),TRUE) -> TRUE
A5: Stage | B5: Discovery | C5: Closed Lost | D5: 7/31/2026, 9:18 AM | E5: Rogers - Shaw Communications | F5: Current customer | I5: 45366 | J5: 46234 | L5: 0 | M5: 006V50000052T6M | N5: Rogers Communications Canada | O5: =_xlfn.IFNA(VLOOKUP(Table1[[#This Row],[Lead Source]],'helper tab'!A:B,2,FALSE),"Exclude") -> Exclude | P5: =--SUBSTITUTE(D5,",","") -> 46234.387 | Q5: =IF(OR($C5="Propose",$C5="Procure"),1,0) -> 0 | R5: =IF($C5="Closed Won",1,0) -> 0 | S5: =IF( AND($Q5=1,$M5<>""), IF( COUNTIFS( $M$3:$M5,$M5, $O$3:$O5,$O5, $Q$3:$Q5,1, $P$3:$P5,">="&EOMONTH($P5,-1)+1, $P$3:$P5,"<"&EOMONTH($P5,0)+1 )=1, 1, 0), 0) -> 0 | T5: =IF(AND($R5=1,$M5<>""),IF(COUNTIFS($M$3:$M5,$M5,$O$3:$O5,$O5,$R$3:$R5,1,$P$3:$P5,">="&EOMONTH($P5,-1)+1,$P$3:$P5,"<"&EOMONTH($P5,0)+1)=1,1,0),0) -> 0 | U5: =IF($C5="Closed Lost",1,0) -> 1 | V5: =IF(AND($U5=1,$M5<>""),IF(COUNTIFS($M$3:$M5,$M5,$O$3:$O5,$O5,$U$3:$U5,1,$P$3:$P5,">="&EOMONTH($P5,-1)+1,$P$3:$P5,"<"&EOMONTH($P5,0)+1)=1,1,0),0) -> 1 | W5: =TODAY()-Table1[[#This Row],[Change Date]] -> 23.6125 | X5: =IFERROR( IF( COUNTIFS($M:$M,$M5,$P:$P,">"&$P5)=0, "", _xlfn.MINIFS($P:$P,$M:$M,$M5,$P:$P,">"&$P5) ), "" ) | Y5: =IF(Table1[[#This Row],[Next Stage Date]]<>"",Table1[[#This Row],[Next Stage Date]]-Table1[[#This Row],[Change Date]],TODAY()-Table1[[#This Row],[Change Date]]) -> 23.6125 | Z5: =IF(P5=_xlfn.MAXIFS($P:$P,$M:$M,$M5),1,0) -> 1 | AA5: =IF( COUNTIFS($M:$M,$M5,$C:$C,"Closed Won")=0, "", _xlfn.MINIFS($P:$P,$M:$M,$M5,$C:$C,"Closed Won") ) | AB5: =IF( COUNTIFS($M:$M,$M5,$Q:$Q,1)=0, "", _xlfn.MINIFS($P:$P,$M:$M,$M5,$Q:$Q,1) ) | AC5: =IF(AB5<>"",AB5-I5,"") | AD5: =IF(AND(AB5<>"",AA5<>""),AA5-AB5,"") | AE5: =IF(AA5<>"",AA5-I5,"") | AF5: =IFERROR(_xlfn.XLOOKUP(Table1[[#This Row],[Opportunity ID]],'Aging Detail'!$H$14:$H$20,'Aging Detail'!$F$14:$F$20),TRUE) -> TRUE
A6: Stage | B6: Procure | C6: Propose | D6: 7/31/2026, 9:02 AM | E6: Farmers - Agent-Aux State Analysis | I6: 46127 | J6: 46387 | K6: 31680 | L6: 31680 | M6: 006V500000QVL7f | N6: Farmers Insurance | O6: =_xlfn.IFNA(VLOOKUP(Table1[[#This Row],[Lead Source]],'helper tab'!A:B,2,FALSE),"Exclude") -> Exclude | P6: =--SUBSTITUTE(D6,",","") -> 46234.376 | Q6: =IF(OR($C6="Propose",$C6="Procure"),1,0) -> 1 | R6: =IF($C6="Closed Won",1,0) -> 0 | S6: =IF( AND($Q6=1,$M6<>""), IF( COUNTIFS( $M$3:$M6,$M6, $O$3:$O6,$O6, $Q$3:$Q6,1, $P$3:$P6,">="&EOMONTH($P6,-1)+1, $P$3:$P6,"<"&EOMONTH($P6,0)+1 )=1, 1, 0), 0) -> 1 | T6: =IF(AND($R6=1,$M6<>""),IF(COUNTIFS($M$3:$M6,$M6,$O$3:$O6,$O6,$R$3:$R6,1,$P$3:$P6,">="&EOMONTH($P6,-1)+1,$P$3:$P6,"<"&EOMONTH($P6,0)+1)=1,1,0),0) -> 0 | U6: =IF($C6="Closed Lost",1,0) -> 0 | V6: =IF(AND($U6=1,$M6<>""),IF(COUNTIFS($M$3:$M6,$M6,$O$3:$O6,$O6,$U$3:$U6,1,$P$3:$P6,">="&EOMONTH($P6,-1)+1,$P$3:$P6,"<"&EOMONTH($P6,0)+1)=1,1,0),0) -> 0 | W6: =TODAY()-Table1[[#This Row],[Change Date]] -> 23.623611 | X6: =IFERROR( IF( COUNTIFS($M:$M,$M6,$P:$P,">"&$P6)=0, "", _xlfn.MINIFS($P:$P,$M:$M,$M6,$P:$P,">"&$P6) ), "" ) | Y6: =IF(Table1[[#This Row],[Next Stage Date]]<>"",Table1[[#This Row],[Next Stage Date]]-Table1[[#This Row],[Change Date]],TODAY()-Table1[[#This Row],[Change Date]]) -> 23.623611 | Z6: =IF(P6=_xlfn.MAXIFS($P:$P,$M:$M,$M6),1,0) -> 1 | AA6: =IF( COUNTIFS($M:$M,$M6,$C:$C,"Closed Won")=0, "", _xlfn.MINIFS($P:$P,$M:$M,$M6,$C:$C,"Closed Won") ) | AB6: =IF( COUNTIFS($M:$M,$M6,$Q:$Q,1)=0, "", _xlfn.MINIFS($P:$P,$M:$M,$M6,$Q:$Q,1) ) -> 46205.504 | AC6: =IF(AB6<>"",AB6-I6,"") -> 78.504167 | AD6: =IF(AND(AB6<>"",AA6<>""),AA6-AB6,"") | AE6: =IF(AA6<>"",AA6-I6,"") | AF6: =IFERROR(_xlfn.XLOOKUP(Table1[[#This Row],[Opportunity ID]],'Aging Detail'!$H$14:$H$20,'Aging Detail'!$F$14:$F$20),TRUE) -> TRUE
A7: Stage | B7: Propose | C7: Procure | D7: 7/31/2026, 9:01 AM | E7: Farmers - Agent-Aux State Analysis | I7: 46127 | J7: 46387 | K7: 31680 | L7: 31680 | M7: 006V500000QVL7f | N7: Farmers Insurance | O7: =_xlfn.IFNA(VLOOKUP(Table1[[#This Row],[Lead Source]],'helper tab'!A:B,2,FALSE),"Exclude") -> Exclude | P7: =--SUBSTITUTE(D7,",","") -> 46234.376 | Q7: =IF(OR($C7="Propose",$C7="Procure"),1,0) -> 1 | R7: =IF($C7="Closed Won",1,0) -> 0 | S7: =IF( AND($Q7=1,$M7<>""), IF( COUNTIFS( $M$3:$M7,$M7, $O$3:$O7,$O7, $Q$3:$Q7,1, $P$3:$P7,">="&EOMONTH($P7,-1)+1, $P$3:$P7,"<"&EOMONTH($P7,0)+1 )=1, 1, 0), 0) -> 0 | T7: =IF(AND($R7=1,$M7<>""),IF(COUNTIFS($M$3:$M7,$M7,$O$3:$O7,$O7,$R$3:$R7,1,$P$3:$P7,">="&EOMONTH($P7,-1)+1,$P$3:$P7,"<"&EOMONTH($P7,0)+1)=1,1,0),0) -> 0 | U7: =IF($C7="Closed Lost",1,0) -> 0 | V7: =IF(AND($U7=1,$M7<>""),IF(COUNTIFS($M$3:$M7,$M7,$O$3:$O7,$O7,$U$3:$U7,1,$P$3:$P7,">="&EOMONTH($P7,-1)+1,$P$3:$P7,"<"&EOMONTH($P7,0)+1)=1,1,0),0) -> 0 | W7: =TODAY()-Table1[[#This Row],[Change Date]] -> 23.624306 | X7: =IFERROR( IF( COUNTIFS($M:$M,$M7,$P:$P,">"&$P7)=0, "", _xlfn.MINIFS($P:$P,$M:$M,$M7,$P:$P,">"&$P7) ), "" ) -> 46234.376 | Y7: =IF(Table1[[#This Row],[Next Stage Date]]<>"",Table1[[#This Row],[Next Stage Date]]-Table1[[#This Row],[Change Date]],TODAY()-Table1[[#This Row],[Change Date]]) -> 0.00069444444 | Z7: =IF(P7=_xlfn.MAXIFS($P:$P,$M:$M,$M7),1,0) -> 0 | AA7: =IF( COUNTIFS($M:$M,$M7,$C:$C,"Closed Won")=0, "", _xlfn.MINIFS($P:$P,$M:$M,$M7,$C:$C,"Closed Won") ) | AB7: =IF( COUNTIFS($M:$M,$M7,$Q:$Q,1)=0, "", _xlfn.MINIFS($P:$P,$M:$M,$M7,$Q:$Q,1) ) -> 46205.504 | AC7: =IF(AB7<>"",AB7-I7,"") -> 78.504167 | AD7: =IF(AND(AB7<>"",AA7<>""),AA7-AB7,"") | AE7: =IF(AA7<>"",AA7-I7,"") | AF7: =IFERROR(_xlfn.XLOOKUP(Table1[[#This Row],[Opportunity ID]],'Aging Detail'!$H$14:$H$20,'Aging Detail'!$F$14:$F$20),TRUE) -> TRUE
A8: Stage | B8: Qualification | C8: Closed Lost | D8: 7/31/2026, 8:28 AM | E8: Guardian life insurance | F8: Website | G8: Website | I8: 45720 | J8: 45747 | L8: 0 | M8: 006V500000CPD83 | N8: Guardian Life | O8: =_xlfn.IFNA(VLOOKUP(Table1[[#This Row],[Lead Source]],'helper tab'!A:B,2,FALSE),"Exclude") -> Digital | P8: =--SUBSTITUTE(D8,",","") -> 46234.353 | Q8: =IF(OR($C8="Propose",$C8="Procure"),1,0) -> 0 | R8: =IF($C8="Closed Won",1,0) -> 0 | S8: =IF( AND($Q8=1,$M8<>""), IF( COUNTIFS( $M$3:$M8,$M8, $O$3:$O8,$O8, $Q$3:$Q8,1, $P$3:$P8,">="&EOMONTH($P8,-1)+1, $P$3:$P8,"<"&EOMONTH($P8,0)+1 )=1, 1, 0), 0) -> 0 | T8: =IF(AND($R8=1,$M8<>""),IF(COUNTIFS($M$3:$M8,$M8,$O$3:$O8,$O8,$R$3:$R8,1,$P$3:$P8,">="&EOMONTH($P8,-1)+1,$P$3:$P8,"<"&EOMONTH($P8,0)+1)=1,1,0),0) -> 0 | U8: =IF($C8="Closed Lost",1,0) -> 1 | V8: =IF(AND($U8=1,$M8<>""),IF(COUNTIFS($M$3:$M8,$M8,$O$3:$O8,$O8,$U$3:$U8,1,$P$3:$P8,">="&EOMONTH($P8,-1)+1,$P$3:$P8,"<"&EOMONTH($P8,0)+1)=1,1,0),0) -> 1 | W8: =TODAY()-Table1[[#This Row],[Change Date]] -> 23.647222 | X8: =IFERROR( IF( COUNTIFS($M:$M,$M8,$P:$P,">"&$P8)=0, "", _xlfn.MINIFS($P:$P,$M:$M,$M8,$P:$P,">"&$P8) ), "" ) | Y8: =IF(Table1[[#This Row],[Next Stage Date]]<>"",Table1[[#This Row],[Next Stage Date]]-Table1[[#This Row],[Change Date]],TODAY()-Table1[[#This Row],[Change Date]]) -> 23.647222 | Z8: =IF(P8=_xlfn.MAXIFS($P:$P,$M:$M,$M8),1,0) -> 1 | AA8: =IF( COUNTIFS($M:$M,$M8,$C:$C,"Closed Won")=0, "", _xlfn.MINIFS($P:$P,$M:$M,$M8,$C:$C,"Closed Won") ) | AB8: =IF( COUNTIFS($M:$M,$M8,$Q:$Q,1)=0, "", _xlfn.MINIFS($P:$P,$M:$M,$M8,$Q:$Q,1) ) | AC8: =IF(AB8<>"",AB8-I8,"") | AD8: =IF(AND(AB8<>"",AA8<>""),AA8-AB8,"") | AE8: =IF(AA8<>"",AA8-I8,"") | AF8: =IFERROR(_xlfn.XLOOKUP(Table1[[#This Row],[Opportunity ID]],'Aging Detail'!$H$14:$H$20,'Aging Detail'!$F$14:$F$20),TRUE) -> TRUE
A9: Stage | B9: Qualification | C9: Closed Lost | D9: 7/31/2026, 8:27 AM | E9: Guardian | F9: Website | I9: 45720 | J9: 45747 | L9: 0 | M9: 006V500000CPD82 | N9: Guardian Life | O9: =_xlfn.IFNA(VLOOKUP(Table1[[#This Row],[Lead Source]],'helper tab'!A:B,2,FALSE),"Exclude") -> Digital | P9: =--SUBSTITUTE(D9,",","") -> 46234.352 | Q9: =IF(OR($C9="Propose",$C9="Procure"),1,0) -> 0 | R9: =IF($C9="Closed Won",1,0) -> 0 | S9: =IF( AND($Q9=1,$M9<>""), IF( COUNTIFS( $M$3:$M9,$M9, $O$3:$O9,$O9, $Q$3:$Q9,1, $P$3:$P9,">="&EOMONTH($P9,-1)+1, $P$3:$P9,"<"&EOMONTH($P9,0)+1 )=1, 1, 0), 0) -> 0 | T9: =IF(AND($R9=1,$M9<>""),IF(COUNTIFS($M$3:$M9,$M9,$O$3:$O9,$O9,$R$3:$R9,1,$P$3:$P9,">="&EOMONTH($P9,-1)+1,$P$3:$P9,"<"&EOMONTH($P9,0)+1)=1,1,0),0) -> 0 | U9: =IF($C9="Closed Lost",1,0) -> 1 | V9: =IF(AND($U9=1,$M9<>""),IF(COUNTIFS($M$3:$M9,$M9,$O$3:$O9,$O9,$U$3:$U9,1,$P$3:$P9,">="&EOMONTH($P9,-1)+1,$P$3:$P9,"<"&EOMONTH($P9,0)+1)=1,1,0),0) -> 1 | W9: =TODAY()-Table1[[#This Row],[Change Date]] -> 23.647917 | X9: =IFERROR( IF( COUNTIFS($M:$M,$M9,$P:$P,">"&$P9)=0, "", _xlfn.MINIFS($P:$P,$M:$M,$M9,$P:$P,">"&$P9) ), "" ) | Y9: =IF(Table1[[#This Row],[Next Stage Date]]<>"",Table1[[#This Row],[Next Stage Date]]-Table1[[#This Row],[Change Date]],TODAY()-Table1[[#This Row],[Change Date]]) -> 23.647917 | Z9: =IF(P9=_xlfn.MAXIFS($P:$P,$M:$M,$M9),1,0) -> 1 | AA9: =IF( COUNTIFS($M:$M,$M9,$C:$C,"Closed Won")=0, "", _xlfn.MINIFS($P:$P,$M:$M,$M9,$C:$C,"Closed Won") ) | AB9: =IF( COUNTIFS($M:$M,$M9,$Q:$Q,1)=0, "", _xlfn.MINIFS($P:$P,$M:$M,$M9,$Q:$Q,1) ) | AC9: =IF(AB9<>"",AB9-I9,"") | AD9: =IF(AND(AB9<>"",AA9<>""),AA9-AB9,"") | AE9: =IF(AA9<>"",AA9-I9,"") | AF9: =IFERROR(_xlfn.XLOOKUP(Table1[[#This Row],[Opportunity ID]],'Aging Detail'!$H$14:$H$20,'Aging Detail'!$F$14:$F$20),TRUE) -> TRUE
A10: Stage | B10: Discovery | C10: Solution Design/Value Creation | D10: 7/31/2026, 7:09 AM | E10: Five9 - Telus - NTT Data | F10: Partner | H10: Five9 | I10: 46195 | J10: 46290 | K10: 210184 | L10: 140184 | M10: 006V500000TdK6D | N10: NTT Data Group | O10: =_xlfn.IFNA(VLOOKUP(Table1[[#This Row],[Lead Source]],'helper tab'!A:B,2,FALSE),"Exclude") -> Alliances | P10: =--SUBSTITUTE(D10,",","") -> 46234.298 | Q10: =IF(OR($C10="Propose",$C10="Procure"),1,0) -> 0 | R10: =IF($C10="Closed Won",1,0) -> 0 | S10: =IF( AND($Q10=1,$M10<>""), IF( COUNTIFS( $M$3:$M10,$M10, $O$3:$O10,$O10, $Q$3:$Q10,1, $P$3:$P10,">="&EOMONTH($P10,-1)+1, $P$3:$P10,"<"&EOMONTH($P10,0)+1 )=1, 1, 0), 0) -> 0 | T10: =IF(AND($R10=1,$M10<>""),IF(COUNTIFS($M$3:$M10,$M10,$O$3:$O10,$O10,$R$3:$R10,1,$P$3:$P10,">="&EOMONTH($P10,-1)+1,$P$3:$P10,"<"&EOMONTH($P10,0)+1)=1,1,0),0) -> 0 | U10: =IF($C10="Closed Lost",1,0) -> 0 | V10: =IF(AND($U10=1,$M10<>""),IF(COUNTIFS($M$3:$M10,$M10,$O$3:$O10,$O10,$U$3:$U10,1,$P$3:$P10,">="&EOMONTH($P10,-1)+1,$P$3:$P10,"<"&EOMONTH($P10,0)+1)=1,1,0),0) -> 0 | W10: =TODAY()-Table1[[#This Row],[Change Date]] -> 23.702083 | X10: =IFERROR( IF( COUNTIFS($M:$M,$M10,$P:$P,">"&$P10)=0, "", _xlfn.MINIFS($P:$P,$M:$M,$M10,$P:$P,">"&$P10) ), "" ) -> 46234.478 | Y10: =IF(Table1[[#This Row],[Next Stage Date]]<>"",Table1[[#This Row],[Next Stage Date]]-Table1[[#This Row],[Change Date]],TODAY()-Table1[[#This Row],[Change Date]]) -> 0.17986111 | Z10: =IF(P10=_xlfn.MAXIFS($P:$P,$M:$M,$M10),1,0) -> 0 | AA10: =IF( COUNTIFS($M:$M,$M10,$C:$C,"Closed Won")=0, "", _xlfn.MINIFS($P:$P,$M:$M,$M10,$C:$C,"Closed Won") ) | AB10: =IF( COUNTIFS($M:$M,$M10,$Q:$Q,1)=0, "", _xlfn.MINIFS($P:$P,$M:$M,$M10,$Q:$Q,1) ) -> 46234.478 | AC10: =IF(AB10<>"",AB10-I10,"") -> 39.477778 | AD10: =IF(AND(AB10<>"",AA10<>""),AA10-AB10,"") | AE10: =IF(AA10<>"",AA10-I10,"") | AF10: =IFERROR(_xlfn.XLOOKUP(Table1[[#This Row],[Opportunity ID]],'Aging Detail'!$H$14:$H$20,'Aging Detail'!$F$14:$F$20),TRUE) -> TRUE
A11: Stage | B11: Propose | C11: Closed Lost | D11: 7/30/2026, 12:59 PM | E11: Snap Finance- Additional UK Licenses & Thrive Reset Licenses | I11: 46210 | J11: 46356 | K11: 30950.64 | L11: 30950.64 | M11: 006V500000UF4V3 | N11: Snap Finance LLC | O11: =_xlfn.IFNA(VLOOKUP(Table1[[#This Row],[Lead Source]],'helper tab'!A:B,2,FALSE),"Exclude") -> Exclude | P11: =--SUBSTITUTE(D11,",","") -> 46233.541 | Q11: =IF(OR($C11="Propose",$C11="Procure"),1,0) -> 0 | R11: =IF($C11="Closed Won",1,0) -> 0 | S11: =IF( AND($Q11=1,$M11<>""), IF( COUNTIFS( $M$3:$M11,$M11, $O$3:$O11,$O11, $Q$3:$Q11,1, $P$3:$P11,">="&EOMONTH($P11,-1)+1, $P$3:$P11,"<"&EOMONTH($P11,0)+1 )=1, 1, 0), 0) -> 0 | T11: =IF(AND($R11=1,$M11<>""),IF(COUNTIFS($M$3:$M11,$M11,$O$3:$O11,$O11,$R$3:$R11,1,$P$3:$P11,">="&EOMONTH($P11,-1)+1,$P$3:$P11,"<"&EOMONTH($P11,0)+1)=1,1,0),0) -> 0 | U11: =IF($C11="Closed Lost",1,0) -> 1 | V11: =IF(AND($U11=1,$M11<>""),IF(COUNTIFS($M$3:$M11,$M11,$O$3:$O11,$O11,$U$3:$U11,1,$P$3:$P11,">="&EOMONTH($P11,-1)+1,$P$3:$P11,"<"&EOMONTH($P11,0)+1)=1,1,0),0) -> 1 | W11: =TODAY()-Table1[[#This Row],[Change Date]] -> 24.459028 | X11: =IFERROR( IF( COUNTIFS($M:$M,$M11,$P:$P,">"&$P11)=0, "", _xlfn.MINIFS($P:$P,$M:$M,$M11,$P:$P,">"&$P11) ), "" ) | Y11: =IF(Table1[[#This Row],[Next Stage Date]]<>"",Table1[[#This Row],[Next Stage Date]]-Table1[[#This Row],[Change Date]],TODAY()-Table1[[#This Row],[Change Date]]) -> 24.459028 | Z11: =IF(P11=_xlfn.MAXIFS($P:$P,$M:$M,$M11),1,0) -> 1 | AA11: =IF( COUNTIFS($M:$M,$M11,$C:$C,"Closed Won")=0, "", _xlfn.MINIFS($P:$P,$M:$M,$M11,$C:$C,"Closed Won") ) | AB11: =IF( COUNTIFS($M:$M,$M11,$Q:$Q,1)=0, "", _xlfn.MINIFS($P:$P,$M:$M,$M11,$Q:$Q,1) ) -> 46210.517 | AC11: =IF(AB11<>"",AB11-I11,"") -> 0.51736111 | AD11: =IF(AND(AB11<>"",AA11<>""),AA11-AB11,"") | AE11: =IF(AA11<>"",AA11-I11,"") | AF11: =IFERROR(_xlfn.XLOOKUP(Table1[[#This Row],[Opportunity ID]],'Aging Detail'!$H$14:$H$20,'Aging Detail'!$F$14:$F$20),TRUE) -> TRUE
A12: Stage | B12: Discovery | C12: Solution Design/Value Creation | D12: 7/30/2026, 11:59 AM | E12: Teleperformance | F12: Google Natural Search | G12: Google Natural Search | I12: 45938 | J12: 46752 | K12: 50000 | L12: 50000 | M12: 006V500000J4v1Z | N12: Teleperformance USA | O12: =_xlfn.IFNA(VLOOKUP(Table1[[#This Row],[Lead Source]],'helper tab'!A:B,2,FALSE),"Exclude") -> Digital | P12: =--SUBSTITUTE(D12,",","") -> 46233.499 | Q12: =IF(OR($C12="Propose",$C12="Procure"),1,0) -> 0 | R12: =IF($C12="Closed Won",1,0) -> 0 | S12: =IF( AND($Q12=1,$M12<>""), IF( COUNTIFS( $M$3:$M12,$M12, $O$3:$O12,$O12, $Q$3:$Q12,1, $P$3:$P12,">="&EOMONTH($P12,-1)+1, $P$3:$P12,"<"&EOMONTH($P12,0)+1 )=1, 1, 0), 0) -> 0 | T12: =IF(AND($R12=1,$M12<>""),IF(COUNTIFS($M$3:$M12,$M12,$O$3:$O12,$O12,$R$3:$R12,1,$P$3:$P12,">="&EOMONTH($P12,-1)+1,$P$3:$P12,"<"&EOMONTH($P12,0)+1)=1,1,0),0) -> 0 | U12: =IF($C12="Closed Lost",1,0) -> 0 | V12: =IF(AND($U12=1,$M12<>""),IF(COUNTIFS($M$3:$M12,$M12,$O$3:$O12,$O12,$U$3:$U12,1,$P$3:$P12,">="&EOMONTH($P12,-1)+1,$P$3:$P12,"<"&EOMONTH($P12,0)+1)=1,1,0),0) -> 0 | W12: =TODAY()-Table1[[#This Row],[Change Date]] -> 24.500694 | X12: =IFERROR( IF( COUNTIFS($M:$M,$M12,$P:$P,">"&$P12)=0, "", _xlfn.MINIFS($P:$P,$M:$M,$M12,$P:$P,">"&$P12) ), "" ) | Y12: =IF(Table1[[#This Row],[Next Stage Date]]<>"",Table1[[#This Row],[Next Stage Date]]-Table1[[#This Row],[Change Date]],TODAY()-Table1[[#This Row],[Change Date]]) -> 24.500694 | Z12: =IF(P12=_xlfn.MAXIFS($P:$P,$M:$M,$M12),1,0) -> 1 | AA12: =IF( COUNTIFS($M:$M,$M12,$C:$C,"Closed Won")=0, "", _xlfn.MINIFS($P:$P,$M:$M,$M12,$C:$C,"Closed Won") ) | AB12: =IF( COUNTIFS($M:$M,$M12,$Q:$Q,1)=0, "", _xlfn.MINIFS($P:$P,$M:$M,$M12,$Q:$Q,1) ) | AC12: =IF(AB12<>"",AB12-I12,"") | AD12: =IF(AND(AB12<>"",AA12<>""),AA12-AB12,"") | AE12: =IF(AA12<>"",AA12-I12,"") | AF12: =IFERROR(_xlfn.XLOOKUP(Table1[[#This Row],[Opportunity ID]],'Aging Detail'!$H$14:$H$20,'Aging Detail'!$F$14:$F$20),TRUE) -> TRUE
A13: Stage | B13: Discovery | C13: Solution Design/Value Creation | D13: 7/30/2026, 11:57 AM | E13: AssetMark - NL | F13: Sales | I13: 46097 | J13: 46283 | K13: 100400 | L13: 50400 | M13: 006V500000PFy77 | N13: AssetMark Inc | O13: =_xlfn.IFNA(VLOOKUP(Table1[[#This Row],[Lead Source]],'helper tab'!A:B,2,FALSE),"Exclude") -> Exclude | P13: =--SUBSTITUTE(D13,",","") -> 46233.498 | Q13: =IF(OR($C13="Propose",$C13="Procure"),1,0) -> 0 | R13: =IF($C13="Closed Won",1,0) -> 0 | S13: =IF( AND($Q13=1,$M13<>""), IF( COUNTIFS( $M$3:$M13,$M13, $O$3:$O13,$O13, $Q$3:$Q13,1, $P$3:$P13,">="&EOMONTH($P13,-1)+1, $P$3:$P13,"<"&EOMONTH($P13,0)+1 )=1, 1, 0), 0) -> 0 | T13: =IF(AND($R13=1,$M13<>""),IF(COUNTIFS($M$3:$M13,$M13,$O$3:$O13,$O13,$R$3:$R13,1,$P$3:$P13,">="&EOMONTH($P13,-1)+1,$P$3:$P13,"<"&EOMONTH($P13,0)+1)=1,1,0),0) -> 0 | U13: =IF($C13="Closed Lost",1,0) -> 0 | V13: =IF(AND($U13=1,$M13<>""),IF(COUNTIFS($M$3:$M13,$M13,$O$3:$O13,$O13,$U$3:$U13,1,$P$3:$P13,">="&EOMONTH($P13,-1)+1,$P$3:$P13,"<"&EOMONTH($P13,0)+1)=1,1,0),0) -> 0 | W13: =TODAY()-Table1[[#This Row],[Change Date]] -> 24.502083 | X13: =IFERROR( IF( COUNTIFS($M:$M,$M13,$P:$P,">"&$P13)=0, "", _xlfn.MINIFS($P:$P,$M:$M,$M13,$P:$P,">"&$P13) ), "" ) | Y13: =IF(Table1[[#This Row],[Next Stage Date]]<>"",Table1[[#This Row],[Next Stage Date]]-Table1[[#This Row],[Change Date]],TODAY()-Table1[[#This Row],[Change Date]]) -> 24.502083 | Z13: =IF(P13=_xlfn.MAXIFS($P:$P,$M:$M,$M13),1,0) -> 1 | AA13: =IF( COUNTIFS($M:$M,$M13,$C:$C,"Closed Won")=0, "", _xlfn.MINIFS($P:$P,$M:$M,$M13,$C:$C,"Closed Won") ) | AB13: =IF( COUNTIFS($M:$M,$M13,$Q:$Q,1)=0, "", _xlfn.MINIFS($P:$P,$M:$M,$M13,$Q:$Q,1) ) | AC13: =IF(AB13<>"",AB13-I13,"") | AD13: =IF(AND(AB13<>"",AA13<>""),AA13-AB13,"") | AE13: =IF(AA13<>"",AA13-I13,"") | AF13: =IFERROR(_xlfn.XLOOKUP(Table1[[#This Row],[Opportunity ID]],'Aging Detail'!$H$14:$H$20,'Aging Detail'!$F$14:$F$20),TRUE) -> TRUE
A14: Stage | B14: Discovery | C14: Solution Design/Value Creation | D14: 7/30/2026, 11:56 AM | E14: Capital Group - sys expansion - Thrive & BI | F14: Sales | I14: 46097 | J14: 46374 | K14: 617600 | L14: 537600 | M14: 006V500000PGdbh | N14: Capital Group | O14: =_xlfn.IFNA(VLOOKUP(Table1[[#This Row],[Lead Source]],'helper tab'!A:B,2,FALSE),"Exclude") -> Exclude | P14: =--SUBSTITUTE(D14,",","") -> 46233.497 | Q14: =IF(OR($C14="Propose",$C14="Procure"),1,0) -> 0 | R14: =IF($C14="Closed Won",1,0) -> 0 | S14: =IF( AND($Q14=1,$M14<>""), IF( COUNTIFS( $M$3:$M14,$M14, $O$3:$O14,$O14, $Q$3:$Q14,1, $P$3:$P14,">="&EOMONTH($P14,-1)+1, $P$3:$P14,"<"&EOMONTH($P14,0)+1 )=1, 1, 0), 0) -> 0 | T14: =IF(AND($R14=1,$M14<>""),IF(COUNTIFS($M$3:$M14,$M14,$O$3:$O14,$O14,$R$3:$R14,1,$P$3:$P14,">="&EOMONTH($P14,-1)+1,$P$3:$P14,"<"&EOMONTH($P14,0)+1)=1,1,0),0) -> 0 | U14: =IF($C14="Closed Lost",1,0) -> 0 | V14: =IF(AND($U14=1,$M14<>""),IF(COUNTIFS($M$3:$M14,$M14,$O$3:$O14,$O14,$U$3:$U14,1,$P$3:$P14,">="&EOMONTH($P14,-1)+1,$P$3:$P14,"<"&EOMONTH($P14,0)+1)=1,1,0),0) -> 0 | W14: =TODAY()-Table1[[#This Row],[Change Date]] -> 24.502778 | X14: =IFERROR( IF( COUNTIFS($M:$M,$M14,$P:$P,">"&$P14)=0, "", _xlfn.MINIFS($P:$P,$M:$M,$M14,$P:$P,">"&$P14) ), "" ) | Y14: =IF(Table1[[#This Row],[Next Stage Date]]<>"",Table1[[#This Row],[Next Stage Date]]-Table1[[#This Row],[Change Date]],TODAY()-Table1[[#This Row],[Change Date]]) -> 24.502778 | Z14: =IF(P14=_xlfn.MAXIFS($P:$P,$M:$M,$M14),1,0) -> 1 | AA14: =IF( COUNTIFS($M:$M,$M14,$C:$C,"Closed Won")=0, "", _xlfn.MINIFS($P:$P,$M:$M,$M14,$C:$C,"Closed Won") ) | AB14: =IF( COUNTIFS($M:$M,$M14,$Q:$Q,1)=0, "", _xlfn.MINIFS($P:$P,$M:$M,$M14,$Q:$Q,1) ) | AC14: =IF(AB14<>"",AB14-I14,"") | AD14: =IF(AND(AB14<>"",AA14<>""),AA14-AB14,"") | AE14: =IF(AA14<>"",AA14-I14,"") | AF14: =IFERROR(_xlfn.XLOOKUP(Table1[[#This Row],[Opportunity ID]],'Aging Detail'!$H$14:$H$20,'Aging Detail'!$F$14:$F$20),TRUE) -> TRUE
A15: Stage | B15: Discovery | C15: Solution Design/Value Creation | D15: 7/30/2026, 11:14 AM | E15: MAPFRE Insurance | F15: Sales | G15: 6sense SI | I15: 46137 | J15: 46374 | K15: 178800 | L15: 118800 | M15: 006V500000Quple | N15: MAPFRE Insurance Company | O15: =_xlfn.IFNA(VLOOKUP(Table1[[#This Row],[Lead Source]],'helper tab'!A:B,2,FALSE),"Exclude") -> Exclude | P15: =--SUBSTITUTE(D15,",","") -> 46233.468 | Q15: =IF(OR($C15="Propose",$C15="Procure"),1,0) -> 0 | R15: =IF($C15="Closed Won",1,0) -> 0 | S15: =IF( AND($Q15=1,$M15<>""), IF( COUNTIFS( $M$3:$M15,$M15, $O$3:$O15,$O15, $Q$3:$Q15,1, $P$3:$P15,">="&EOMONTH($P15,-1)+1, $P$3:$P15,"<"&EOMONTH($P15,0)+1 )=1, 1, 0), 0) -> 0 | T15: =IF(AND($R15=1,$M15<>""),IF(COUNTIFS($M$3:$M15,$M15,$O$3:$O15,$O15,$R$3:$R15,1,$P$3:$P15,">="&EOMONTH($P15,-1)+1,$P$3:$P15,"<"&EOMONTH($P15,0)+1)=1,1,0),0) -> 0 | U15: =IF($C15="Closed Lost",1,0) -> 0 | V15: =IF(AND($U15=1,$M15<>""),IF(COUNTIFS($M$3:$M15,$M15,$O$3:$O15,$O15,$U$3:$U15,1,$P$3:$P15,">="&EOMONTH($P15,-1)+1,$P$3:$P15,"<"&EOMONTH($P15,0)+1)=1,1,0),0) -> 0 | W15: =TODAY()-Table1[[#This Row],[Change Date]] -> 24.531944 | X15: =IFERROR( IF( COUNTIFS($M:$M,$M15,$P:$P,">"&$P15)=0, "", _xlfn.MINIFS($P:$P,$M:$M,$M15,$P:$P,">"&$P15) ), "" ) | Y15: =IF(Table1[[#This Row],[Next Stage Date]]<>"",Table1[[#This Row],[Next Stage Date]]-Table1[[#This Row],[Change Date]],TODAY()-Table1[[#This Row],[Change Date]]) -> 24.531944 | Z15: =IF(P15=_xlfn.MAXIFS($P:$P,$M:$M,$M15),1,0) -> 1 | AA15: =IF( COUNTIFS($M:$M,$M15,$C:$C,"Closed Won")=0, "", _xlfn.MINIFS($P:$P,$M:$M,$M15,$C:$C,"Closed Won") ) | AB15: =IF( COUNTIFS($M:$M,$M15,$Q:$Q,1)=0, "", _xlfn.MINIFS($P:$P,$M:$M,$M15,$Q:$Q,1) ) | AC15: =IF(AB15<>"",AB15-I15,"") | AD15: =IF(AND(AB15<>"",AA15<>""),AA15-AB15,"") | AE15: =IF(AA15<>"",AA15-I15,"") | AF15: =IFERROR(_xlfn.XLOOKUP(Table1[[#This Row],[Opportunity ID]],'Aging Detail'!$H$14:$H$20,'Aging Detail'!$F$14:$F$20),TRUE) -> TRUE
A16: Stage | B16: Discovery | C16: Closed Lost | D16: 7/29/2026, 1:09 PM | E16: RBC Pilot - Branch | F16: Sales | I16: 45750 | J16: 46232 | K16: 25000 | L16: 25000 | M16: 006V500000DMjdJ | N16: Royal Bank of Canada (RBC) | O16: =_xlfn.IFNA(VLOOKUP(Table1[[#This Row],[Lead Source]],'helper tab'!A:B,2,FALSE),"Exclude") -> Exclude | P16: =--SUBSTITUTE(D16,",","") -> 46232.548 | Q16: =IF(OR($C16="Propose",$C16="Procure"),1,0) -> 0 | R16: =IF($C16="Closed Won",1,0) -> 0 | S16: =IF( AND($Q16=1,$M16<>""), IF( COUNTIFS( $M$3:$M45,$M16, $O$3:$O45,$O16, $Q$3:$Q45,1, $P$3:$P45,">="&EOMONTH($P16,-1)+1, $P$3:$P45,"<"&EOMONTH($P16,0)+1 )=1, 1, 0), 0) -> 0 | T16: =IF(AND($R16=1,$M16<>""),IF(COUNTIFS($M$3:$M16,$M16,$O$3:$O16,$O16,$R$3:$R16,1,$P$3:$P16,">="&EOMONTH($P16,-1)+1,$P$3:$P16,"<"&EOMONTH($P16,0)+1)=1,1,0),0) -> 0 | U16: =IF($C16="Closed Lost",1,0) -> 1 | V16: =IF(AND($U16=1,$M16<>""),IF(COUNTIFS($M$3:$M16,$M16,$O$3:$O16,$O16,$U$3:$U16,1,$P$3:$P16,">="&EOMONTH($P16,-1)+1,$P$3:$P16,"<"&EOMONTH($P16,0)+1)=1,1,0),0) -> 1 | W16: =TODAY()-Table1[[#This Row],[Change Date]] -> 25.452083 | X16: =IFERROR( IF( COUNTIFS($M:$M,$M16,$P:$P,">"&$P16)=0, "", _xlfn.MINIFS($P:$P,$M:$M,$M16,$P:$P,">"&$P16) ), "" ) | Y16: =IF(Table1[[#This Row],[Next Stage Date]]<>"",Table1[[#This Row],[Next Stage Date]]-Table1[[#This Row],[Change Date]],TODAY()-Table1[[#This Row],[Change Date]]) -> 25.452083 | Z16: =IF(P16=_xlfn.MAXIFS($P:$P,$M:$M,$M16),1,0) -> 1 | AA16: =IF( COUNTIFS($M:$M,$M16,$C:$C,"Closed Won")=0, "", _xlfn.MINIFS($P:$P,$M:$M,$M16,$C:$C,"Closed Won") ) | AB16: =IF( COUNTIFS($M:$M,$M16,$Q:$Q,1)=0, "", _xlfn.MINIFS($P:$P,$M:$M,$M16,$Q:$Q,1) ) | AC16: =IF(AB16<>"",AB16-I16,"") | AD16: =IF(AND(AB16<>"",AA16<>""),AA16-AB16,"") | AE16: =IF(AA16<>"",AA16-I16,"") | AF16: =IFERROR(_xlfn.XLOOKUP(Table1[[#This Row],[Opportunity ID]],'Aging Detail'!$H$14:$H$20,'Aging Detail'!$F$14:$F$20),TRUE) -> TRUE
A17: Stage | B17: Discovery | C17: Solution Design/Value Creation | D17: 7/29/2026, 1:05 PM | E17: Piedmont Healthcare | F17: Other - Marketing | I17: 46118 | J17: 46568 | K17: 189600 | L17: 129600 | M17: 006V500000Q7lhZ | N17: Piedmont Healthcare Incorporated | O17: =_xlfn.IFNA(VLOOKUP(Table1[[#This Row],[Lead Source]],'helper tab'!A:B,2,FALSE),"Exclude") -> Exclude | P17: =--SUBSTITUTE(D17,",","") -> 46232.545 | Q17: =IF(OR($C17="Propose",$C17="Procure"),1,0) -> 0 | R17: =IF($C17="Closed Won",1,0) -> 0 | S17: =IF( AND($Q17=1,$M17<>""), IF( COUNTIFS( $M$3:$M17,$M17, $O$3:$O17,$O17, $Q$3:$Q17,1, $P$3:$P17,">="&EOMONTH($P17,-1)+1, $P$3:$P17,"<"&EOMONTH($P17,0)+1 )=1, 1, 0), 0) -> 0 | T17: =IF(AND($R17=1,$M17<>""),IF(COUNTIFS($M$3:$M17,$M17,$O$3:$O17,$O17,$R$3:$R17,1,$P$3:$P17,">="&EOMONTH($P17,-1)+1,$P$3:$P17,"<"&EOMONTH($P17,0)+1)=1,1,0),0) -> 0 | U17: =IF($C17="Closed Lost",1,0) -> 0 | V17: =IF(AND($U17=1,$M17<>""),IF(COUNTIFS($M$3:$M17,$M17,$O$3:$O17,$O17,$U$3:$U17,1,$P$3:$P17,">="&EOMONTH($P17,-1)+1,$P$3:$P17,"<"&EOMONTH($P17,0)+1)=1,1,0),0) -> 0 | W17: =TODAY()-Table1[[#This Row],[Change Date]] -> 25.454861 | X17: =IFERROR( IF( COUNTIFS($M:$M,$M17,$P:$P,">"&$P17)=0, "", _xlfn.MINIFS($P:$P,$M:$M,$M17,$P:$P,">"&$P17) ), "" ) | Y17: =IF(Table1[[#This Row],[Next Stage Date]]<>"",Table1[[#This Row],[Next Stage Date]]-Table1[[#This Row],[Change Date]],TODAY()-Table1[[#This Row],[Change Date]]) -> 25.454861 | Z17: =IF(P17=_xlfn.MAXIFS($P:$P,$M:$M,$M17),1,0) -> 1 | AA17: =IF( COUNTIFS($M:$M,$M17,$C:$C,"Closed Won")=0, "", _xlfn.MINIFS($P:$P,$M:$M,$M17,$C:$C,"Closed Won") ) | AB17: =IF( COUNTIFS($M:$M,$M17,$Q:$Q,1)=0, "", _xlfn.MINIFS($P:$P,$M:$M,$M17,$Q:$Q,1) ) | AC17: =IF(AB17<>"",AB17-I17,"") | AD17: =IF(AND(AB17<>"",AA17<>""),AA17-AB17,"") | AE17: =IF(AA17<>"",AA17-I17,"") | AF17: =IFERROR(_xlfn.XLOOKUP(Table1[[#This Row],[Opportunity ID]],'Aging Detail'!$H$14:$H$20,'Aging Detail'!$F$14:$F$20),TRUE) -> TRUE
A18: Stage | B18: Solution Design/Value Creation | C18: Propose | D18: 7/29/2026, 1:02 PM | E18: Nationwide - Pilot | F18: Sales | I18: 46212 | J18: 46395 | K18: 100000 | L18: 100000 | M18: 006V500000UL4FR | N18: Nationwide Mutual Insurance Company | O18: =_xlfn.IFNA(VLOOKUP(Table1[[#This Row],[Lead Source]],'helper tab'!A:B,2,FALSE),"Exclude") -> Exclude | P18: =--SUBSTITUTE(D18,",","") -> 46232.543 | Q18: =IF(OR($C18="Propose",$C18="Procure"),1,0) -> 1 | R18: =IF($C18="Closed Won",1,0) -> 0 | S18: =IF( AND($Q18=1,$M18<>""), IF( COUNTIFS( $M$3:$M18,$M18, $O$3:$O18,$O18, $Q$3:$Q18,1, $P$3:$P18,">="&EOMONTH($P18,-1)+1, $P$3:$P18,"<"&EOMONTH($P18,0)+1 )=1, 1, 0), 0) -> 1 | T18: =IF(AND($R18=1,$M18<>""),IF(COUNTIFS($M$3:$M18,$M18,$O$3:$O18,$O18,$R$3:$R18,1,$P$3:$P18,">="&EOMONTH($P18,-1)+1,$P$3:$P18,"<"&EOMONTH($P18,0)+1)=1,1,0),0) -> 0 | U18: =IF($C18="Closed Lost",1,0) -> 0 | V18: =IF(AND($U18=1,$M18<>""),IF(COUNTIFS($M$3:$M18,$M18,$O$3:$O18,$O18,$U$3:$U18,1,$P$3:$P18,">="&EOMONTH($P18,-1)+1,$P$3:$P18,"<"&EOMONTH($P18,0)+1)=1,1,0),0) -> 0 | W18: =TODAY()-Table1[[#This Row],[Change Date]] -> 25.456944 | X18: =IFERROR( IF( COUNTIFS($M:$M,$M18,$P:$P,">"&$P18)=0, "", _xlfn.MINIFS($P:$P,$M:$M,$M18,$P:$P,">"&$P18) ), "" ) | Y18: =IF(Table1[[#This Row],[Next Stage Date]]<>"",Table1[[#This Row],[Next Stage Date]]-Table1[[#This Row],[Change Date]],TODAY()-Table1[[#This Row],[Change Date]]) -> 25.456944 | Z18: =IF(P18=_xlfn.MAXIFS($P:$P,$M:$M,$M18),1,0) -> 1 | AA18: =IF( COUNTIFS($M:$M,$M18,$C:$C,"Closed Won")=0, "", _xlfn.MINIFS($P:$P,$M:$M,$M18,$C:$C,"Closed Won") ) | AB18: =IF( COUNTIFS($M:$M,$M18,$Q:$Q,1)=0, "", _xlfn.MINIFS($P:$P,$M:$M,$M18,$Q:$Q,1) ) -> 46232.543 | AC18: =IF(AB18<>"",AB18-I18,"") -> 20.543056 | AD18: =IF(AND(AB18<>"",AA18<>""),AA18-AB18,"") | AE18: =IF(AA18<>"",AA18-I18,"") | AF18: =IFERROR(_xlfn.XLOOKUP(Table1[[#This Row],[Opportunity ID]],'Aging Detail'!$H$14:$H$20,'Aging Detail'!$F$14:$F$20),TRUE) -> TRUE
A19: Stage | B19: Discovery | C19: Solution Design/Value Creation | D19: 7/29/2026, 1:00 PM | E19: Five9 - Johnson Controls - Initial Solution | F19: Partner | H19: Five9 | I19: 46168 | J19: 46535 | K19: 564000 | L19: 504000 | M19: 006V500000SFYip | N19: Johnson Controls | O19: =_xlfn.IFNA(VLOOKUP(Table1[[#This Row],[Lead Source]],'helper tab'!A:B,2,FALSE),"Exclude") -> Alliances | P19: =--SUBSTITUTE(D19,",","") -> 46232.542 | Q19: =IF(OR($C19="Propose",$C19="Procure"),1,0) -> 0 | R19: =IF($C19="Closed Won",1,0) -> 0 | S19: =IF( AND($Q19=1,$M19<>""), IF( COUNTIFS( $M$3:$M19,$M19, $O$3:$O19,$O19, $Q$3:$Q19,1, $P$3:$P19,">="&EOMONTH($P19,-1)+1, $P$3:$P19,"<"&EOMONTH($P19,0)+1 )=1, 1, 0), 0) -> 0 | T19: =IF(AND($R19=1,$M19<>""),IF(COUNTIFS($M$3:$M19,$M19,$O$3:$O19,$O19,$R$3:$R19,1,$P$3:$P19,">="&EOMONTH($P19,-1)+1,$P$3:$P19,"<"&EOMONTH($P19,0)+1)=1,1,0),0) -> 0 | U19: =IF($C19="Closed Lost",1,0) -> 0 | V19: =IF(AND($U19=1,$M19<>""),IF(COUNTIFS($M$3:$M19,$M19,$O$3:$O19,$O19,$U$3:$U19,1,$P$3:$P19,">="&EOMONTH($P19,-1)+1,$P$3:$P19,"<"&EOMONTH($P19,0)+1)=1,1,0),0) -> 0 | W19: =TODAY()-Table1[[#This Row],[Change Date]] -> 25.458333 | X19: =IFERROR( IF( COUNTIFS($M:$M,$M19,$P:$P,">"&$P19)=0, "", _xlfn.MINIFS($P:$P,$M:$M,$M19,$P:$P,">"&$P19) ), "" ) | Y19: =IF(Table1[[#This Row],[Next Stage Date]]<>"",Table1[[#This Row],[Next Stage Date]]-Table1[[#This Row],[Change Date]],TODAY()-Table1[[#This Row],[Change Date]]) -> 25.458333 | Z19: =IF(P19=_xlfn.MAXIFS($P:$P,$M:$M,$M19),1,0) -> 1 | AA19: =IF( COUNTIFS($M:$M,$M19,$C:$C,"Closed Won")=0, "", _xlfn.MINIFS($P:$P,$M:$M,$M19,$C:$C,"Closed Won") ) | AB19: =IF( COUNTIFS($M:$M,$M19,$Q:$Q,1)=0, "", _xlfn.MINIFS($P:$P,$M:$M,$M19,$Q:$Q,1) ) | AC19: =IF(AB19<>"",AB19-I19,"") | AD19: =IF(AND(AB19<>"",AA19<>""),AA19-AB19,"") | AE19: =IF(AA19<>"",AA19-I19,"") | AF19: =IFERROR(_xlfn.XLOOKUP(Table1[[#This Row],[Opportunity ID]],'Aging Detail'!$H$14:$H$20,'Aging Detail'!$F$14:$F$20),TRUE) -> TRUE
A20: Stage | B20: Discovery | C20: Solution Design/Value Creation | D20: 7/29/2026, 12:59 PM | E20: FedEx - Front Office Deployment | F20: Partner | G20: Partner | H20: Five9 | I20: 45995 | J20: 46374 | K20: 2900000 | L20: 2760000 | M20: 006V500000LH121 | N20: FedEx | O20: =_xlfn.IFNA(VLOOKUP(Table1[[#This Row],[Lead Source]],'helper tab'!A:B,2,FALSE),"Exclude") -> Alliances | P20: =--SUBSTITUTE(D20,",","") -> 46232.541 | Q20: =IF(OR($C20="Propose",$C20="Procure"),1,0) -> 0 | R20: =IF($C20="Closed Won",1,0) -> 0 | S20: =IF( AND($Q20=1,$M20<>""), IF( COUNTIFS( $M$3:$M20,$M20, $O$3:$O20,$O20, $Q$3:$Q20,1, $P$3:$P20,">="&EOMONTH($P20,-1)+1, $P$3:$P20,"<"&EOMONTH($P20,0)+1 )=1, 1, 0), 0) -> 0 | T20: =IF(AND($R20=1,$M20<>""),IF(COUNTIFS($M$3:$M20,$M20,$O$3:$O20,$O20,$R$3:$R20,1,$P$3:$P20,">="&EOMONTH($P20,-1)+1,$P$3:$P20,"<"&EOMONTH($P20,0)+1)=1,1,0),0) -> 0 | U20: =IF($C20="Closed Lost",1,0) -> 0 | V20: =IF(AND($U20=1,$M20<>""),IF(COUNTIFS($M$3:$M20,$M20,$O$3:$O20,$O20,$U$3:$U20,1,$P$3:$P20,">="&EOMONTH($P20,-1)+1,$P$3:$P20,"<"&EOMONTH($P20,0)+1)=1,1,0),0) -> 0 | W20: =TODAY()-Table1[[#This Row],[Change Date]] -> 25.459028 | X20: =IFERROR( IF( COUNTIFS($M:$M,$M20,$P:$P,">"&$P20)=0, "", _xlfn.MINIFS($P:$P,$M:$M,$M20,$P:$P,">"&$P20) ), "" ) | Y20: =IF(Table1[[#This Row],[Next Stage Date]]<>"",Table1[[#This Row],[Next Stage Date]]-Table1[[#This Row],[Change Date]],TODAY()-Table1[[#This Row],[Change Date]]) -> 25.459028 | Z20: =IF(P20=_xlfn.MAXIFS($P:$P,$M:$M,$M20),1,0) -> 1 | AA20: =IF( COUNTIFS($M:$M,$M20,$C:$C,"Closed Won")=0, "", _xlfn.MINIFS($P:$P,$M:$M,$M20,$C:$C,"Closed Won") ) | AB20: =IF( COUNTIFS($M:$M,$M20,$Q:$Q,1)=0, "", _xlfn.MINIFS($P:$P,$M:$M,$M20,$Q:$Q,1) ) | AC20: =IF(AB20<>"",AB20-I20,"") | AD20: =IF(AND(AB20<>"",AA20<>""),AA20-AB20,"") | AE20: =IF(AA20<>"",AA20-I20,"") | AF20: =IFERROR(_xlfn.XLOOKUP(Table1[[#This Row],[Opportunity ID]],'Aging Detail'!$H$14:$H$20,'Aging Detail'!$F$14:$F$20),TRUE) -> TRUE
A21: Stage | B21: Propose | C21: Procure | D21: 7/29/2026, 11:13 AM | E21: Luxottica $0 POV | F21: Events | I21: 46225 | J21: 46234 | L21: 0 | M21: 006V500000UpWvq | N21: Luxottica | O21: =_xlfn.IFNA(VLOOKUP(Table1[[#This Row],[Lead Source]],'helper tab'!A:B,2,FALSE),"Exclude") -> Events | P21: =--SUBSTITUTE(D21,",","") -> 46232.467 | Q21: =IF(OR($C21="Propose",$C21="Procure"),1,0) -> 1 | R21: =IF($C21="Closed Won",1,0) -> 0 | S21: =IF( AND($Q21=1,$M21<>""), IF( COUNTIFS( $M$3:$M21,$M21, $O$3:$O21,$O21, $Q$3:$Q21,1, $P$3:$P21,">="&EOMONTH($P21,-1)+1, $P$3:$P21,"<"&EOMONTH($P21,0)+1 )=1, 1, 0), 0) -> 1 | T21: =IF(AND($R21=1,$M21<>""),IF(COUNTIFS($M$3:$M21,$M21,$O$3:$O21,$O21,$R$3:$R21,1,$P$3:$P21,">="&EOMONTH($P21,-1)+1,$P$3:$P21,"<"&EOMONTH($P21,0)+1)=1,1,0),0) -> 0 | U21: =IF($C21="Closed Lost",1,0) -> 0 | V21: =IF(AND($U21=1,$M21<>""),IF(COUNTIFS($M$3:$M21,$M21,$O$3:$O21,$O21,$U$3:$U21,1,$P$3:$P21,">="&EOMONTH($P21,-1)+1,$P$3:$P21,"<"&EOMONTH($P21,0)+1)=1,1,0),0) -> 0 | W21: =TODAY()-Table1[[#This Row],[Change Date]] -> 25.532639 | X21: =IFERROR( IF( COUNTIFS($M:$M,$M21,$P:$P,">"&$P21)=0, "", _xlfn.MINIFS($P:$P,$M:$M,$M21,$P:$P,">"&$P21) ), "" ) | Y21: =IF(Table1[[#This Row],[Next Stage Date]]<>"",Table1[[#This Row],[Next Stage Date]]-Table1[[#This Row],[Change Date]],TODAY()-Table1[[#This Row],[Change Date]]) -> 25.532639 | Z21: =IF(P21=_xlfn.MAXIFS($P:$P,$M:$M,$M21),1,0) -> 1 | AA21: =IF( COUNTIFS($M:$M,$M21,$C:$C,"Closed Won")=0, "", _xlfn.MINIFS($P:$P,$M:$M,$M21,$C:$C,"Closed Won") ) | AB21: =IF( COUNTIFS($M:$M,$M21,$Q:$Q,1)=0, "", _xlfn.MINIFS($P:$P,$M:$M,$M21,$Q:$Q,1) ) -> 46225.513 | AC21: =IF(AB21<>"",AB21-I21,"") -> 0.51319444 | AD21: =IF(AND(AB21<>"",AA21<>""),AA21-AB21,"") | AE21: =IF(AA21<>"",AA21-I21,"") | AF21: =IFERROR(_xlfn.XLOOKUP(Table1[[#This Row],[Opportunity ID]],'Aging Detail'!$H$14:$H$20,'Aging Detail'!$F$14:$F$20),TRUE) -> TRUE
A22: Stage | B22: Solution Design/Value Creation | C22: Propose | D22: 7/23/2026, 4:43 PM | E22: MMS - Genesys Migration Effort | I22: 46135 | J22: 46387 | K22: 74500 | L22: 10500 | M22: 006V500000Qqpgz | N22: McKesson Medical Surgical | O22: =_xlfn.IFNA(VLOOKUP(Table1[[#This Row],[Lead Source]],'helper tab'!A:B,2,FALSE),"Exclude") -> Exclude | P22: =--SUBSTITUTE(D22,",","") -> 46226.697 | Q22: =IF(OR($C22="Propose",$C22="Procure"),1,0) -> 1 | R22: =IF($C22="Closed Won",1,0) -> 0 | S22: =IF( AND($Q22=1,$M22<>""), IF( COUNTIFS( $M$3:$M22,$M22, $O$3:$O22,$O22, $Q$3:$Q22,1, $P$3:$P22,">="&EOMONTH($P22,-1)+1, $P$3:$P22,"<"&EOMONTH($P22,0)+1 )=1, 1, 0), 0) -> 1 | T22: =IF(AND($R22=1,$M22<>""),IF(COUNTIFS($M$3:$M22,$M22,$O$3:$O22,$O22,$R$3:$R22,1,$P$3:$P22,">="&EOMONTH($P22,-1)+1,$P$3:$P22,"<"&EOMONTH($P22,0)+1)=1,1,0),0) -> 0 | U22: =IF($C22="Closed Lost",1,0) -> 0 | V22: =IF(AND($U22=1,$M22<>""),IF(COUNTIFS($M$3:$M22,$M22,$O$3:$O22,$O22,$U$3:$U22,1,$P$3:$P22,">="&EOMONTH($P22,-1)+1,$P$3:$P22,"<"&EOMONTH($P22,0)+1)=1,1,0),0) -> 0 | W22: =TODAY()-Table1[[#This Row],[Change Date]] -> 31.303472 | X22: =IFERROR( IF( COUNTIFS($M:$M,$M22,$P:$P,">"&$P22)=0, "", _xlfn.MINIFS($P:$P,$M:$M,$M22,$P:$P,">"&$P22) ), "" ) | Y22: =IF(Table1[[#This Row],[Next Stage Date]]<>"",Table1[[#This Row],[Next Stage Date]]-Table1[[#This Row],[Change Date]],TODAY()-Table1[[#This Row],[Change Date]]) -> 31.303472 | Z22: =IF(P22=_xlfn.MAXIFS($P:$P,$M:$M,$M22),1,0) -> 1 | AA22: =IF( COUNTIFS($M:$M,$M22,$C:$C,"Closed Won")=0, "", _xlfn.MINIFS($P:$P,$M:$M,$M22,$C:$C,"Closed Won") ) | AB22: =IF( COUNTIFS($M:$M,$M22,$Q:$Q,1)=0, "", _xlfn.MINIFS($P:$P,$M:$M,$M22,$Q:$Q,1) ) -> 46226.697 | AC22: =IF(AB22<>"",AB22-I22,"") -> 91.696528 | AD22: =IF(AND(AB22<>"",AA22<>""),AA22-AB22,"") | AE22: =IF(AA22<>"",AA22-I22,"") | AF22: =IFERROR(_xlfn.XLOOKUP(Table1[[#This Row],[Opportunity ID]],'Aging Detail'!$H$14:$H$20,'Aging Detail'!$F$14:$F$20),TRUE) -> TRUE
A23: Stage | B23: Solution Design/Value Creation | C23: Propose | D23: 7/23/2026, 2:07 PM | E23: CAA-Club Group (Avaya)- Adaptive Capabilities Solution Add On | F23: Partner | H23: Avaya | I23: 46161 | J23: 46326 | K23: 19824 | L23: 19824 | M23: 006V500000RyeUV | N23: CAA Club Group | O23: =_xlfn.IFNA(VLOOKUP(Table1[[#This Row],[Lead Source]],'helper tab'!A:B,2,FALSE),"Exclude") -> Alliances | P23: =--SUBSTITUTE(D23,",","") -> 46226.588 | Q23: =IF(OR($C23="Propose",$C23="Procure"),1,0) -> 1 | R23: =IF($C23="Closed Won",1,0) -> 0 | S23: =IF( AND($Q23=1,$M23<>""), IF( COUNTIFS( $M$3:$M23,$M23, $O$3:$O23,$O23, $Q$3:$Q23,1, $P$3:$P23,">="&EOMONTH($P23,-1)+1, $P$3:$P23,"<"&EOMONTH($P23,0)+1 )=1, 1, 0), 0) -> 1 | T23: =IF(AND($R23=1,$M23<>""),IF(COUNTIFS($M$3:$M23,$M23,$O$3:$O23,$O23,$R$3:$R23,1,$P$3:$P23,">="&EOMONTH($P23,-1)+1,$P$3:$P23,"<"&EOMONTH($P23,0)+1)=1,1,0),0) -> 0 | U23: =IF($C23="Closed Lost",1,0) -> 0 | V23: =IF(AND($U23=1,$M23<>""),IF(COUNTIFS($M$3:$M23,$M23,$O$3:$O23,$O23,$U$3:$U23,1,$P$3:$P23,">="&EOMONTH($P23,-1)+1,$P$3:$P23,"<"&EOMONTH($P23,0)+1)=1,1,0),0) -> 0 | W23: =TODAY()-Table1[[#This Row],[Change Date]] -> 31.411806 | X23: =IFERROR( IF( COUNTIFS($M:$M,$M23,$P:$P,">"&$P23)=0, "", _xlfn.MINIFS($P:$P,$M:$M,$M23,$P:$P,">"&$P23) ), "" ) | Y23: =IF(Table1[[#This Row],[Next Stage Date]]<>"",Table1[[#This Row],[Next Stage Date]]-Table1[[#This Row],[Change Date]],TODAY()-Table1[[#This Row],[Change Date]]) -> 31.411806 | Z23: =IF(P23=_xlfn.MAXIFS($P:$P,$M:$M,$M23),1,0) -> 1 | AA23: =IF( COUNTIFS($M:$M,$M23,$C:$C,"Closed Won")=0, "", _xlfn.MINIFS($P:$P,$M:$M,$M23,$C:$C,"Closed Won") ) | AB23: =IF( COUNTIFS($M:$M,$M23,$Q:$Q,1)=0, "", _xlfn.MINIFS($P:$P,$M:$M,$M23,$Q:$Q,1) ) -> 46226.588 | AC23: =IF(AB23<>"",AB23-I23,"") -> 65.588194 | AD23: =IF(AND(AB23<>"",AA23<>""),AA23-AB23,"") | AE23: =IF(AA23<>"",AA23-I23,"") | AF23: =IFERROR(_xlfn.XLOOKUP(Table1[[#This Row],[Opportunity ID]],'Aging Detail'!$H$14:$H$20,'Aging Detail'!$F$14:$F$20),TRUE) -> TRUE
A24: Stage | B24: Discovery | C24: Solution Design/Value Creation | D24: 7/23/2026, 2:07 PM | E24: CAA-Club Group (Avaya)- Adaptive Capabilities Solution Add On | F24: Partner | H24: Avaya | I24: 46161 | J24: 46326 | K24: 19824 | L24: 19824 | M24: 006V500000RyeUV | N24: CAA Club Group | O24: =_xlfn.IFNA(VLOOKUP(Table1[[#This Row],[Lead Source]],'helper tab'!A:B,2,FALSE),"Exclude") -> Alliances | P24: =--SUBSTITUTE(D24,",","") -> 46226.588 | Q24: =IF(OR($C24="Propose",$C24="Procure"),1,0) -> 0 | R24: =IF($C24="Closed Won",1,0) -> 0 | S24: =IF( AND($Q24=1,$M24<>""), IF( COUNTIFS( $M$3:$M24,$M24, $O$3:$O24,$O24, $Q$3:$Q24,1, $P$3:$P24,">="&EOMONTH($P24,-1)+1, $P$3:$P24,"<"&EOMONTH($P24,0)+1 )=1, 1, 0), 0) -> 0 | T24: =IF(AND($R24=1,$M24<>""),IF(COUNTIFS($M$3:$M24,$M24,$O$3:$O24,$O24,$R$3:$R24,1,$P$3:$P24,">="&EOMONTH($P24,-1)+1,$P$3:$P24,"<"&EOMONTH($P24,0)+1)=1,1,0),0) -> 0 | U24: =IF($C24="Closed Lost",1,0) -> 0 | V24: =IF(AND($U24=1,$M24<>""),IF(COUNTIFS($M$3:$M24,$M24,$O$3:$O24,$O24,$U$3:$U24,1,$P$3:$P24,">="&EOMONTH($P24,-1)+1,$P$3:$P24,"<"&EOMONTH($P24,0)+1)=1,1,0),0) -> 0 | W24: =TODAY()-Table1[[#This Row],[Change Date]] -> 31.411806 | X24: =IFERROR( IF( COUNTIFS($M:$M,$M24,$P:$P,">"&$P24)=0, "", _xlfn.MINIFS($P:$P,$M:$M,$M24,$P:$P,">"&$P24) ), "" ) | Y24: =IF(Table1[[#This Row],[Next Stage Date]]<>"",Table1[[#This Row],[Next Stage Date]]-Table1[[#This Row],[Change Date]],TODAY()-Table1[[#This Row],[Change Date]]) -> 31.411806 | Z24: =IF(P24=_xlfn.MAXIFS($P:$P,$M:$M,$M24),1,0) -> 1 | AA24: =IF( COUNTIFS($M:$M,$M24,$C:$C,"Closed Won")=0, "", _xlfn.MINIFS($P:$P,$M:$M,$M24,$C:$C,"Closed Won") ) | AB24: =IF( COUNTIFS($M:$M,$M24,$Q:$Q,1)=0, "", _xlfn.MINIFS($P:$P,$M:$M,$M24,$Q:$Q,1) ) -> 46226.588 | AC24: =IF(AB24<>"",AB24-I24,"") -> 65.588194 | AD24: =IF(AND(AB24<>"",AA24<>""),AA24-AB24,"") | AE24: =IF(AA24<>"",AA24-I24,"") | AF24: =IFERROR(_xlfn.XLOOKUP(Table1[[#This Row],[Opportunity ID]],'Aging Detail'!$H$14:$H$20,'Aging Detail'!$F$14:$F$20),TRUE) -> TRUE
A25: Stage | B25: Qualification | C25: Closed Lost | D25: 7/22/2026, 2:24 PM | E25: Encoura ( Anthology)-SSO Migration | I25: 46189 | J25: 46356 | K25: 9000 | L25: 0 | M25: 006V500000TNTS1 | N25: Anthology | O25: =_xlfn.IFNA(VLOOKUP(Table1[[#This Row],[Lead Source]],'helper tab'!A:B,2,FALSE),"Exclude") -> Exclude | P25: =--SUBSTITUTE(D25,",","") -> 46225.6 | Q25: =IF(OR($C25="Propose",$C25="Procure"),1,0) -> 0 | R25: =IF($C25="Closed Won",1,0) -> 0 | S25: =IF( AND($Q25=1,$M25<>""), IF( COUNTIFS( $M$3:$M25,$M25, $O$3:$O25,$O25, $Q$3:$Q25,1, $P$3:$P25,">="&EOMONTH($P25,-1)+1, $P$3:$P25,"<"&EOMONTH($P25,0)+1 )=1, 1, 0), 0) -> 0 | T25: =IF(AND($R25=1,$M25<>""),IF(COUNTIFS($M$3:$M25,$M25,$O$3:$O25,$O25,$R$3:$R25,1,$P$3:$P25,">="&EOMONTH($P25,-1)+1,$P$3:$P25,"<"&EOMONTH($P25,0)+1)=1,1,0),0) -> 0 | U25: =IF($C25="Closed Lost",1,0) -> 1 | V25: =IF(AND($U25=1,$M25<>""),IF(COUNTIFS($M$3:$M25,$M25,$O$3:$O25,$O25,$U$3:$U25,1,$P$3:$P25,">="&EOMONTH($P25,-1)+1,$P$3:$P25,"<"&EOMONTH($P25,0)+1)=1,1,0),0) -> 1 | W25: =TODAY()-Table1[[#This Row],[Change Date]] -> 32.4 | X25: =IFERROR( IF( COUNTIFS($M:$M,$M25,$P:$P,">"&$P25)=0, "", _xlfn.MINIFS($P:$P,$M:$M,$M25,$P:$P,">"&$P25) ), "" ) | Y25: =IF(Table1[[#This Row],[Next Stage Date]]<>"",Table1[[#This Row],[Next Stage Date]]-Table1[[#This Row],[Change Date]],TODAY()-Table1[[#This Row],[Change Date]]) -> 32.4 | Z25: =IF(P25=_xlfn.MAXIFS($P:$P,$M:$M,$M25),1,0) -> 1 | AA25: =IF( COUNTIFS($M:$M,$M25,$C:$C,"Closed Won")=0, "", _xlfn.MINIFS($P:$P,$M:$M,$M25,$C:$C,"Closed Won") ) | AB25: =IF( COUNTIFS($M:$M,$M25,$Q:$Q,1)=0, "", _xlfn.MINIFS($P:$P,$M:$M,$M25,$Q:$Q,1) ) | AC25: =IF(AB25<>"",AB25-I25,"") | AD25: =IF(AND(AB25<>"",AA25<>""),AA25-AB25,"") | AE25: =IF(AA25<>"",AA25-I25,"") | AF25: =IFERROR(_xlfn.XLOOKUP(Table1[[#This Row],[Opportunity ID]],'Aging Detail'!$H$14:$H$20,'Aging Detail'!$F$14:$F$20),TRUE) -> TRUE
